Workbook

Sheet Leia-me
A1: Base de dados – Valor Adicionado e fatores socioeconômicos dos municípios do RN
A2: Extração: 09/10/2026, direto das APIs oficiais (IBGE/SIDRA, IBGE Cidades, IpeaData, Observatório Sebrae). 167 municípios + total do RN.
A4: ABAS
A5: Municipios_RN – 1 linha por município. Colunas agrupadas por setor (Indústria, Serviços, Administração), mais perfil empresarial, socioeconômico e controles. Rankings e % são fórmulas.
A6: Ranking_Setores – Top 15 por setor, por participação no VAB municipal e por VAB absoluto (fórmulas).
A7: Correlacoes – Correlação entre peso de cada setor no VAB e indicadores sociais/empresariais (fórmulas CORREL).
A8: Serie_Historica – Formato longo, filtrável por município e série. PIB e VAB setorial em preços correntes (IBGE, 2002–2023/2021) e em preços constantes de 2010 (IpeaData, 2002–2021), com variação real.
A9: Serie_Participacao – Participação % de cada setor no VAB municipal, ano a ano (2002–2021), pronta para gráfico de linhas.
A10: CNAE_PO_10municipios – Pessoal ocupado por seção CNAE (só 10 municípios cobertos pelo IBGE).
A12: FONTES
A13: IBGE/SIDRA tab. 5938 – PIB dos Municípios (ref. 2010): https://sidra.ibge.gov.br/tabela/5938
A14: IBGE/SIDRA tab. 6579 – Estimativas de população (2021): https://sidra.ibge.gov.br/tabela/6579
... A35: Texto azul = dado importado da fonte · preto = fórmula · verde = fórmula que puxa de outra aba · célula vazia = inexistente/sigiloso/não disponível. Valores monetários do PIB/VAB em mil R$.

Sheet Municipios_RN
A1: IDENTIFICAÇÃO | C1: ECONOMIA GERAL | K1: INDÚSTRIA | S1: SERVIÇOS (exceto adm. pública) | AA1: ADMINISTRAÇÃO PÚBLICA | AI1: AGROPECUÁRIA (ref.) | AK1: PERFIL EMPRESARIAL | AZ1: SOCIOECONÔMICO | BL1: CONTROLE DE QUALIDADE
A2: Código IBGE | B2: Município | C2: PIB 2021 (mil R$) | D2: PIB 2022 (mil R$) | E2: PIB 2023 (mil R$) | F2: VAB total 2021 (mil R$) | G2: Impostos líq. 2021 (mil R$) | H2: População estimada 2021 | I2: PIB per capita 2021 (R$) – IBGE | J2: PIB per capita 2023 (R$) – IBGE | K2: VAB Indústria 2021 (mil R$) | L2: Part. Indústria no VAB (%) | M2: VAB Indústria per capita (R$) | N2: Ranking RN – part. % | O2: Ranking RN – VAB absoluto | P2: Estab. ativos Indústria (Sebrae) | Q2: % estab. Indústria no total | R2: Estab. Indústria EPP + demais portes | S2: VAB Serviços 2021 (mil R$) | T2: Part. Serviços no VAB (%) | U2: VAB Serviços per capita (R$) | V2: Ranking RN – part. % | W2: Ranking RN – VAB absoluto | X2: Estab. ativos Comércio (Sebrae) | Y2: Estab. ativos Serviços (Sebrae) | Z2: % estab. Comércio+Serviços no total | AA2: VAB Adm. pública 2021 (mil R$) | AB2: Part. Adm. pública no VAB (%) | AC2: VAB Adm. per capita (R$) | AD2: Ranking RN – part. % | AE2: Ranking RN – VAB absoluto | AF2: Receita de transferências (% receita) 2025 | AG2: Receitas orçamentárias brutas 2025 (R$) | AH2: Receita bruta per capita 2025 (R$) | AI2: VAB Agropecuária 2021 (mil R$) | AJ2: Part. Agro no VAB (%) | AK2: Empresas atuantes 2022 (CEMPRE) | AL2: Empresas atuantes 2024 (CEMPRE) | AM2: Unidades locais 2024 (CEMPRE) | AN2: Pessoal ocupado 2024 (CEMPRE) | AO2: Pessoal assalariado 2024 (CEMPRE) | AP2: Salário médio mensal 2024 (SM) | AQ2: Empresas por mil hab. 2024 | AR2: Estab. ativos – total (Sebrae) | AS2: MEI (Sebrae) | AT2: ME (Sebrae) | AU2: EPP (Sebrae) | AV2: Demais portes (Sebrae) | AW2: % MEI nos estab. ativos | AX2: Estab. Agro (Sebrae) | AY2: Estab. Adm. pública (Sebrae) | AZ2: População Censo 2022 | BA2: Área (km²) | BB2: Densidade 2022 (hab/km²) | BC2: IDHM 2010 | BD2: % pop. com renda ≤ ½ SM 2010 | BE2: Escolarização 6–14 anos 2022 (%) | BF2: IDEB anos iniciais 2025 (rede pública) | BG2: IDEB anos finais 2025 (rede pública) | BH2: Esgotamento sanitário adequado 2022 (%) | BI2: Pessoal ocupado formal 2024 | BJ2: Salário médio formal 2024 (SM) | BK2: % da população em emprego formal | BL2: Controle: Σ VAB setores − VAB total | BM2: Controle: VAB + impostos − PIB 2021 | BN2: Controle: PIB pc calculado − IBGE (R$)
A3: 2408102 | B3: Natal | C3: 24186139 | D3: 27497422 | E3: 31162043 | F3: 20775502 | G3: 3410637 | H3: 896708 | I3: 26972.15 | J3: 41477.5 | K3: 2556518 | L3: =IFERROR(K3/F3,"") -> 0.12305445 | M3: =IFERROR(K3*1000/H3,"") -> 2851.0039 | N3: =IF(L3="","",RANK(L3,$L$3:$L$168,0)+COUNTIF($L$3:L3,L3)-1) -> 51 | O3: =IF(K3="","",RANK(K3,$K$3:$K$168,0)+COUNTIF($K$3:K3,K3)-1) -> 1 | P3: 15140 | Q3: =IFERROR(P3/AR3,"") -> 0.1347047 | R3: 2492 | S3: 13347894 | T3: =IFERROR(S3/F3,"") -> 0.64248238 | U3: =IFERROR(S3*1000/H3,"") -> 14885.441 | V3: =IF(T3="","",RANK(T3,$T$3:$T$168,0)+COUNTIF($T$3:T3,T3)-1) -> 1 | W3: =IF(S3="","",RANK(S3,$S$3:$S$168,0)+COUNTIF($S$3:S3,S3)-1) -> 1 | X3: 26454 | Y3: 70281 | Z3: =IFERROR((X3+Y3)/AR3,"") -> 0.86067762 | AA3: 4851091 | AB3: =IFERROR(AA3/F3,"") -> 0.23350054 | AC3: =IFERROR(AA3*1000/H3,"") -> 5409.8893 | AD3: =IF(AB3="","",RANK(AB3,$AB$3:$AB$168,0)+COUNTIF($AB$3:AB3,AB3)-1) -> 150 | AE3: =IF(AA3="","",RANK(AA3,$AA$3:$AA$168,0)+COUNTIF($AA$3:AA3,AA3)-1) -> 1 | AF3: 57.6 | AG3: 4.537308e+09 | AH3: =IFERROR(AG3/AZ3,"") -> 6039.276 | AI3: 19998 | AJ3: =IFERROR(AI3/F3,"") -> 0.00096257602 | AK3: 39666 | AL3: 43817 | AM3: 46732 | AN3: 367921 | AO3: 310411 | AP3: 2.8 | AQ3: =IFERROR(AL3*1000/AZ3,"") -> 58.321576 | AR3: 112394 | AS3: 54887 | AT3: 39467 | AU3: 6729 | AV3: 11311 | AW3: =IFERROR(AS3/AR3,"") -> 0.48834457 | AX3: 278 | AY3: 224 | AZ3: 751300 | BA3: 167.401 | BB3: 4488.03 | BC3: 0.763 | BD3: 35.7 | BE3: 97.86 | BF3: 5 | BG3: 3.9 | BH3: 43.74 | BI3: 367921 | BJ3: 2.8 | BK3: =IFERROR(BI3/AZ3,"") -> 0.4897125 | BL3: =IFERROR(AI3+K3+S3+AA3-F3,"") -> -1 | BM3: =IFERROR(F3+G3-C3,"") -> 0 | BN3: =IF(I3="","",IFERROR(C3*1000/H3-I3,"")) -> -0.0041063535
A4: 2408003 | B4: Mossoró | C4: 8071719 | D4: 9582885 | E4: 10323666 | F4: 6898438 | G4: 1173281 | H4: 303792 | I4: 26569.89 | J4: 39019.51 | K4: 1285190 | L4: =IFERROR(K4/F4,"") -> 0.18630159 | M4: =IFERROR(K4*1000/H4,"") -> 4230.4932 | N4: =IF(L4="","",RANK(L4,$L$3:$L$168,0)+COUNTIF($L$3:L4,L4)-1) -> 38 | O4: =IF(K4="","",RANK(K4,$K$3:$K$168,0)+COUNTIF($K$3:K4,K4)-1) -> 3 | P4: 4790 | Q4: =IFERROR(P4/AR4,"") -> 0.15899887 | R4: 771 | S4: 3766138 | T4: =IFERROR(S4/F4,"") -> 0.54594069 | U4: =IFERROR(S4*1000/H4,"") -> 12397.094 | V4: =IF(T4="","",RANK(T4,$T$3:$T$168,0)+COUNTIF($T$3:T4,T4)-1) -> 6 | W4: =IF(S4="","",RANK(S4,$S$3:$S$168,0)+COUNTIF($S$3:S4,S4)-1) -> 2 | X4: 9267 | Y4: 15803 | Z4: =IFERROR((X4+Y4)/AR4,"") -> 0.83217155 | AA4: 1662885 | AB4: =IFERROR(AA4/F4,"") -> 0.24105239 | AC4: =IFERROR(AA4*1000/H4,"") -> 5473.7617 | AD4: =IF(AB4="","",RANK(AB4,$AB$3:$AB$168,0)+COUNTIF($AB$3:AB4,AB4)-1) -> 149 | AE4: =IF(AA4="","",RANK(AA4,$AA$3:$AA$168,0)+COUNTIF($AA$3:AA4,AA4)-1) -> 2 | AF4: 66.4 | AG4: 1.455609e+09 | AH4: =IFERROR(AG4/AZ4,"") -> 5501.646 | AI4: 184225 | AJ4: =IFERROR(AI4/F4,"") -> 0.026705321 | AK4: 11354 | AL4: 12753 | AM4: 13622 | AN4: 97192 | AO4: 81997 | AP4: 2 | AQ4: =IFERROR(AL4*1000/AZ4,"") -> 48.201469 | AR4: 30126 | AS4: 13465 | AT4: 12081 | AU4: 1688 | AV4: 2892 | AW4: =IFERROR(AS4/AR4,"") -> 0.44695612 | AX4: 206 | AY4: 50 | AZ4: 264577 | BA4: 2099.334 | BB4: 126.03 | BC4: 0.72 | BD4: 38 | BE4: 98.56 | BF4: 5.9 | BG4: 4.5 | BH4: 52.96 | BI4: 97079 | BJ4: 2 | BK4: =IFERROR(BI4/AZ4,"") -> 0.36692154 | BL4: =IFERROR(AI4+K4+S4+AA4-F4,"") -> 0 | BM4: =IFERROR(F4+G4-C4,"") -> 0 | BN4: =IF(I4="","",IFERROR(C4*1000/H4-I4,"")) -> -0.0033670406
A5: 2403251 | B5: Parnamirim | C5: 6845358 | D5: 7490688 | E5: 7608526 | F5: 5682309 | G5: 1163049 | H5: 272490 | I5: 25121.5 | J5: 30107.02 | K5: 577662 | L5: =IFERROR(K5/F5,"") -> 0.10165973 | M5: =IFERROR(K5*1000/H5,"") -> 2119.9383 | N5: =IF(L5="","",RANK(L5,$L$3:$L$168,0)+COUNTIF($L$3:L5,L5)-1) -> 58 | O5: =IF(K5="","",RANK(K5,$K$3:$K$168,0)+COUNTIF($K$3:K5,K5)-1) -> 5 | P5: 4745 | Q5: =IFERROR(P5/AR5,"") -> 0.14688583 | R5: 594 | S5: 3470184 | T5: =IFERROR(S5/F5,"") -> 0.61069963 | U5: =IFERROR(S5*1000/H5,"") -> 12735.088 | V5: =IF(T5="","",RANK(T5,$T$3:$T$168,0)+COUNTIF($T$3:T5,T5)-1) -> 3 | W5: =IF(S5="","",RANK(S5,$S$3:$S$168,0)+COUNTIF($S$3:S5,S5)-1) -> 3 | X5: 8341 | Y5: 19136 | Z5: =IFERROR((X5+Y5)/AR5,"") -> 0.85057578 | AA5: 1550432 | AB5: =IFERROR(AA5/F5,"") -> 0.27285246 | AC5: =IFERROR(AA5*1000/H5,"") -> 5689.8675 | AD5: =IF(AB5="","",RANK(AB5,$AB$3:$AB$168,0)+COUNTIF($AB$3:AB5,AB5)-1) -> 144 | AE5: =IF(AA5="","",RANK(AA5,$AA$3:$AA$168,0)+COUNTIF($AA$3:AA5,AA5)-1) -> 3 | AF5: 66.9 | AG5: 1.0390884e+09 | AH5: =IFERROR(AG5/AZ5,"") -> 4111.6844 | AI5: 84031 | AJ5: =IFERROR(AI5/F5,"") -> 0.014788179 | AK5: 9215 | AL5: 10058 | AM5: 10479 | AN5: 63485 | AO5: 52323 | AP5: 1.7 | AQ5: =IFERROR(AL5*1000/AZ5,"") -> 39.799617 | AR5: 32304 | AS5: 18863 | AT5: 9552 | AU5: 1403 | AV5: 2486 | AW5: =IFERROR(AS5/AR5,"") -> 0.5839215 | AX5: 63 | AY5: 19 | AZ5: 252716 | BA5: 124.006 | BB5: 2037.93 | BC5: 0.766 | BD5: 35.5 | BE5: 98.96 | BF5: 5.1 | BG5: 4 | BH5: 16.04 | BI5: 63416 | BJ5: 1.7 | BK5: =IFERROR(BI5/AZ5,"") -> 0.25093781 | BL5: =IFERROR(AI5+K5+S5+AA5-F5,"") -> 0 | BM5: =IFERROR(F5+G5-C5,"") -> 0 | BN5: =IF(I5="","",IFERROR(C5*1000/H5-I5,"")) -> 0.0017064846
A6: 2404507 | B6: Guamaré | C6: 2042133 | D6: 2748777 | E6: 2581922 | F6: 1961362 | G6: 80771 | H6: 16261 | I6: 125584.68 | J6: 168808.24 | K6: 1471020 | L6: =IFERROR(K6/F6,"") -> 0.74999924 | M6: =IFERROR(K6*1000/H6,"") -> 90463.071 | N6: =IF(L6="","",RANK(L6,$L$3:$L$168,0)+COUNTIF($L$3:L6,L6)-1) -> 5 | O6: =IF(K6="","",RANK(K6,$K$3:$K$168,0)+COUNTIF($K$3:K6,K6)-1) -> 2 | P6: 153 | Q6: =IFERROR(P6/AR6,"") -> 0.13385827 | R6: 38 | S6: 258287 | T6: =IFERROR(S6/F6,"") -> 0.13168757 | U6: =IFERROR(S6*1000/H6,"") -> 15883.832 | V6: =IF(T6="","",RANK(T6,$T$3:$T$168,0)+COUNTIF($T$3:T6,T6)-1) -> 156 | W6: =IF(S6="","",RANK(S6,$S$3:$S$168,0)+COUNTIF($S$3:S6,S6)-1) -> 15 | X6: 392 | Y6: 577 | Z6: =IFERROR((X6+Y6)/AR6,"") -> 0.84776903 | AA6: 190763 | AB6: =IFERROR(AA6/F6,"") -> 0.097260475 | AC6: =IFERROR(AA6*1000/H6,"") -> 11731.32 | AD6: =IF(AB6="","",RANK(AB6,$AB$3:$AB$168,0)+COUNTIF($AB$3:AB6,AB6)-1) -> 163 | AE6: =IF(AA6="","",RANK(AA6,$AA$3:$AA$168,0)+COUNTIF($AA$3:AA6,AA6)-1) -> 17 | AF6: 77.94 | AG6: 2.6248183e+08 | AH6: =IFERROR(AG6/AZ6,"") -> 17161.284 | AI6: 41293 | AJ6: =IFERROR(AI6/F6,"") -> 0.021053227 | AK6: 437 | AL6: 475 | AM6: 492 | AN6: 2826 | AO6: 2423 | AP6: 3.6 | AQ6: =IFERROR(AL6*1000/AZ6,"") -> 31.055901 | AR6: 1143 | AS6: 579 | AT6: 364 | AU6: 27 | AV6: 173 | AW6: =IFERROR(AS6/AR6,"") -> 0.50656168 | AX6: 14 | AY6: 6 | AZ6: 15295 | BA6: 258.307 | BB6: 59.21 | BC6: 0.626 | BD6: 44 | BE6: 98.86 | BF6: 5.5 | BG6: 4 | BH6: 26.34 | BI6: 2826 | BJ6: 3.6 | BK6: =IFERROR(BI6/AZ6,"") -> 0.18476626 | BL6: =IFERROR(AI6+K6+S6+AA6-F6,"") -> 1 | BM6: =IFERROR(F6+G6-C6,"") -> 0 | BN6: =IF(I6="","",IFERROR(C6*1000/H6-I6,"")) -> 0.031887338
A7: 2412005 | B7: São Gonçalo do Amarante | C7: 1905641 | D7: 2307194 | E7: 2588564 | F7: 1675162 | G7: 230479 | H7: 104919 | I7: 18162.97 | J7: 22346.41 | K7: 169638 | L7: =IFERROR(K7/F7,"") -> 0.10126662 | M7: =IFERROR(K7*1000/H7,"") -> 1616.8473 | N7: =IF(L7="","",RANK(L7,$L$3:$L$168,0)+COUNTIF($L$3:L7,L7)-1) -> 59 | O7: =IF(K7="","",RANK(K7,$K$3:$K$168,0)+COUNTIF($K$3:K7,K7)-1) -> 21 | P7: 1814 | Q7: =IFERROR(P7/AR7,"") -> 0.19271221 | R7: 266 | S7: 878071 | T7: =IFERROR(S7/F7,"") -> 0.5241708 | U7: =IFERROR(S7*1000/H7,"") -> 8369.0371 | V7: =IF(T7="","",RANK(T7,$T$3:$T$168,0)+COUNTIF($T$3:T7,T7)-1) -> 7 | W7: =IF(S7="","",RANK(S7,$S$3:$S$168,0)+COUNTIF($S$3:S7,S7)-1) -> 4 | X7: 2594 | Y7: 4935 | Z7: =IFERROR((X7+Y7)/AR7,"") -> 0.79985127 | AA7: 589005 | AB7: =IFERROR(AA7/F7,"") -> 0.35161077 | AC7: =IFERROR(AA7*1000/H7,"") -> 5613.9022 | AD7: =IF(AB7="","",RANK(AB7,$AB$3:$AB$168,0)+COUNTIF($AB$3:AB7,AB7)-1) -> 132 | AE7: =IF(AA7="","",RANK(AA7,$AA$3:$AA$168,0)+COUNTIF($AA$3:AA7,AA7)-1) -> 4 | AF7: 61.26 | AG7: 6.2110339e+08 | AH7: =IFERROR(AG7/AZ7,"") -> 5361.8276 | AI7: 38448 | AJ7: =IFERROR(AI7/F7,"") -> 0.02295181 | AK7: 1936 | AL7: 2232 | AM7: 2404 | AN7: 17939 | AO7: 15602 | AP7: 1.7 | AQ7: =IFERROR(AL7*1000/AZ7,"") -> 19.268288 | AR7: 9413 | AS7: 6050 | AT7: 2301 | AU7: 354 | AV7: 708 | AW7: =IFERROR(AS7/AR7,"") -> 0.64272814 | AX7: 56 | AY7: 14 | AZ7: 115838 | BA7: 249.8 | BB7: 463.72 | BC7: 0.661 | BD7: 41.3 | BE7: 99.02 | BF7: 4.7 | BG7: 3.8 | BH7: 32.73 | BI7: 17939 | BJ7: 1.7 | BK7: =IFERROR(BI7/AZ7,"") -> 0.15486283 | BL7: =IFERROR(AI7+K7+S7+AA7-F7,"") -> 0 | BM7: =IFERROR(F7+G7-C7,"") -> 0 | BN7: =IF(I7="","",IFERROR(C7*1000/H7-I7,"")) -> 0.0033413395
A8: 2407104 | B8: Macaíba | C8: 1828142 | D8: 2109145 | E8: 2455739 | F8: 1561048 | G8: 267094 | H8: 82828 | I8: 22071.55 | J8: 29857.38 | K8: 485851 | L8: =IFERROR(K8/F8,"") -> 0.31123386 | M8: =IFERROR(K8*1000/H8,"") -> 5865.7821 | N8: =IF(L8="","",RANK(L8,$L$3:$L$168,0)+COUNTIF($L$3:L8,L8)-1) -> 26 | O8: =IF(K8="","",RANK(K8,$K$3:$K$168,0)+COUNTIF($K$3:K8,K8)-1) -> 9 | P8: 1396 | Q8: =IFERROR(P8/AR8,"") -> 0.25085355 | R8: 376 | S8: 605895 | T8: =IFERROR(S8/F8,"") -> 0.38813348 | U8: =IFERROR(S8*1000/H8,"") -> 7315.0988 | V8: =IF(T8="","",RANK(T8,$T$3:$T$168,0)+COUNTIF($T$3:T8,T8)-1) -> 29 | W8: =IF(S8="","",RANK(S8,$S$3:$S$168,0)+COUNTIF($S$3:S8,S8)-1) -> 6 | X8: 1642 | Y8: 2451 | Z8: =IFERROR((X8+Y8)/AR8,"") -> 0.73548967 | AA8: 433168 | AB8: =IFERROR(AA8/F8,"") -> 0.27748538 | AC8: =IFERROR(AA8*1000/H8,"") -> 5229.7291 | AD8: =IF(AB8="","",RANK(AB8,$AB$3:$AB$168,0)+COUNTIF($AB$3:AB8,AB8)-1) -> 142 | AE8: =IF(AA8="","",RANK(AA8,$AA$3:$AA$168,0)+COUNTIF($AA$3:AA8,AA8)-1) -> 5 | AF8: 73.11 | AG8: 4.1173966e+08 | AH8: =IFERROR(AG8/AZ8,"") -> 5006.0142 | AI8: 36133 | AJ8: =IFERROR(AI8/F8,"") -> 0.02314663 | AK8: 1766 | AL8: 1886 | AM8: 2286 | AN8: 14258 | AO8: 12208 | AP8: 1.9 | AQ8: =IFERROR(AL8*1000/AZ8,"") -> 22.93037 | AR8: 5565 | AS8: 2758 | AT8: 1826 | AU8: 268 | AV8: 713 | AW8: =IFERROR(AS8/AR8,"") -> 0.49559748 | AX8: 59 | AY8: 17 | AZ8: 82249 | BA8: 510.092 | BB8: 161.24 | BC8: 0.64 | BD8: 44.5 | BE8: 96.89 | BF8: 5 | BG8: 4.1 | BH8: 10.23 | BI8: 14239 | BJ8: 1.9 | BK8: =IFERROR(BI8/AZ8,"") -> 0.17312065 | BL8: =IFERROR(AI8+K8+S8+AA8-F8,"") -> -1 | BM8: =IFERROR(F8+G8-C8,"") -> 0 | BN8: =IF(I8="","",IFERROR(C8*1000/H8-I8,"")) -> -0.004145941
A9: 2400208 | B9: Assú | C9: 1467562 | D9: 2146108 | E9: 2170177 | F9: 1368136 | G9: 99426 | H9: 58743 | I9: 24982.76 | J9: 38412.94 | K9: 483176 | L9: =IFERROR(K9/F9,"") -> 0.35316372 | M9: =IFERROR(K9*1000/H9,"") -> 8225.2524 | N9: =IF(L9="","",RANK(L9,$L$3:$L$168,0)+COUNTIF($L$3:L9,L9)-1) -> 22 | O9: =IF(K9="","",RANK(K9,$K$3:$K$168,0)+COUNTIF($K$3:K9,K9)-1) -> 10 | P9: 676 | Q9: =IFERROR(P9/AR9,"") -> 0.15486827 | R9: 145 | S9: 518977 | T9: =IFERROR(S9/F9,"") -> 0.37933144 | U9: =IFERROR(S9*1000/H9,"") -> 8834.7037 | V9: =IF(T9="","",RANK(T9,$T$3:$T$168,0)+COUNTIF($T$3:T9,T9)-1) -> 30 | W9: =IF(S9="","",RANK(S9,$S$3:$S$168,0)+COUNTIF($S$3:S9,S9)-1) -> 7 | X9: 1563 | Y9: 2061 | Z9: =IFERROR((X9+Y9)/AR9,"") -> 0.83024055 | AA9: 330939 | AB9: =IFERROR(AA9/F9,"") -> 0.24189043 | AC9: =IFERROR(AA9*1000/H9,"") -> 5633.6755 | AD9: =IF(AB9="","",RANK(AB9,$AB$3:$AB$168,0)+COUNTIF($AB$3:AB9,AB9)-1) -> 148 | AE9: =IF(AA9="","",RANK(AA9,$AA$3:$AA$168,0)+COUNTIF($AA$3:AA9,AA9)-1) -> 8 | AF9: 77.19 | AG9: 3.2855936e+08 | AH9: =IFERROR(AG9/AZ9,"") -> 5815.6217 | AI9: 35044 | AJ9: =IFERROR(AI9/F9,"") -> 0.025614413 | AK9: 1744 | AL9: 1969 | AM9: 2065 | AN9: 9666 | AO9: 7528 | AP9: 1.8 | AQ9: =IFERROR(AL9*1000/AZ9,"") -> 34.852025 | AR9: 4365 | AS9: 1897 | AT9: 1761 | AU9: 221 | AV9: 486 | AW9: =IFERROR(AS9/AR9,"") -> 0.43459336 | AX9: 53 | AY9: 12 | AZ9: 56496 | BA9: 1303.442 | BB9: 43.34 | BC9: 0.661 | BD9: 44.7 | BE9: 98.04 | BF9: 4.8 | BG9: 3.7 | BH9: 2.6 | BI9: 9658 | BJ9: 1.8 | BK9: =IFERROR(BI9/AZ9,"") -> 0.17095016 | BL9: =IFERROR(AI9+K9+S9+AA9-F9,"") -> 0 | BM9: =IFERROR(F9+G9-C9,"") -> 0 | BN9: =IF(I9="","",IFERROR(C9*1000/H9-I9,"")) -> -0.0046078682
A10: 2402006 | B10: Caicó | C10: 1394838 | D10: 1598739 | E10: 1735797 | F10: 1214573 | G10: 180265 | H10: 68726 | I10: 20295.64 | J10: 28387.75 | K10: 80879 | L10: =IFERROR(K10/F10,"") -> 0.066590481 | M10: =IFERROR(K10*1000/H10,"") -> 1176.8326 | N10: =IF(L10="","",RANK(L10,$L$3:$L$168,0)+COUNTIF($L$3:L10,L10)-1) -> 73 | O10: =IF(K10="","",RANK(K10,$K$3:$K$168,0)+COUNTIF($K$3:K10,K10)-1) -> 31 | P10: 1073 | Q10: =IFERROR(P10/AR10,"") -> 0.1657911 | R10: 94 | S10: 687110 | T10: =IFERROR(S10/F10,"") -> 0.56572145 | U10: =IFERROR(S10*1000/H10,"") -> 9997.8174 | V10: =IF(T10="","",RANK(T10,$T$3:$T$168,0)+COUNTIF($T$3:T10,T10)-1) -> 5 | W10: =IF(S10="","",RANK(S10,$S$3:$S$168,0)+COUNTIF($S$3:S10,S10)-1) -> 5 | X10: 2247 | Y10: 3119 | Z10: =IFERROR((X10+Y10)/AR10,"") -> 0.82911001 | AA10: 392190 | AB10: =IFERROR(AA10/F10,"") -> 0.3229036 | AC10: =IFERROR(AA10*1000/H10,"") -> 5706.5739 | AD10: =IF(AB10="","",RANK(AB10,$AB$3:$AB$168,0)+COUNTIF($AB$3:AB10,AB10)-1) -> 134 | AE10: =IF(AA10="","",RANK(AA10,$AA$3:$AA$168,0)+COUNTIF($AA$3:AA10,AA10)-1) -> 7 | AF10: 81.82 | AG10: 2.9794052e+08 | AH10: =IFERROR(AG10/AZ10,"") -> 4872.6086 | AI10: 54394 | AJ10: =IFERROR(AI10/F10,"") -> 0.044784463 | AK10: 2147 | AL10: 2404 | AM10: 2584 | AN10: 14370 | AO10: 11540 | AP10: 1.7 | AQ10: =IFERROR(AL10*1000/AZ10,"") -> 39.315736 | AR10: 6472 | AS10: 3345 | AT10: 2346 | AU10: 245 | AV10: 536 | AW10: =IFERROR(AS10/AR10,"") -> 0.51684178 | AX10: 15 | AY10: 15 | AZ10: 61146 | BA10: 1228.583 | BB10: 49.77 | BC10: 0.71 | BD10: 37.9 | BE10: 98.92 | BF10: 5.9 | BG10: 4.6 | BH10: 73.59 | BI10: 14370 | BJ10: 1.7 | BK10: =IFERROR(BI10/AZ10,"") -> 0.23501128 | BL10: =IFERROR(AI10+K10+S10+AA10-F10,"") -> 0 | BM10: =IFERROR(F10+G10-C10,"") -> 0 | BN10: =IF(I10="","",IFERROR(C10*1000/H10-I10,"")) -> -0.0022500946
A11: 2405801 | B11: João Câmara | C11: 1269833 | D11: 1419596 | E11: 1527022 | F11: 1197893 | G11: 71940 | H11: 35360 | I11: 35911.56 | J11: 45870.29 | K11: 712023 | L11: =IFERROR(K11/F11,"") -> 0.59439616 | M11: =IFERROR(K11*1000/H11,"") -> 20136.397 | N11: =IF(L11="","",RANK(L11,$L$3:$L$168,0)+COUNTIF($L$3:L11,L11)-1) -> 9 | O11: =IF(K11="","",RANK(K11,$K$3:$K$168,0)+COUNTIF($K$3:K11,K11)-1) -> 4 | P11: 388 | Q11: =IFERROR(P11/AR11,"") -> 0.14526395 | R11: 84 | S11: 241850 | T11: =IFERROR(S11/F11,"") -> 0.20189616 | U11: =IFERROR(S11*1000/H11,"") -> 6839.6493 | V11: =IF(T11="","",RANK(T11,$T$3:$T$168,0)+COUNTIF($T$3:T11,T11)-1) -> 141 | W11: =IF(S11="","",RANK(S11,$S$3:$S$168,0)+COUNTIF($S$3:S11,S11)-1) -> 16 | X11: 1008 | Y11: 1246 | Z11: =IFERROR((X11+Y11)/AR11,"") -> 0.8438787 | AA11: 222640 | AB11: =IFERROR(AA11/F11,"") -> 0.18585967 | AC11: =IFERROR(AA11*1000/H11,"") -> 6296.3801 | AD11: =IF(AB11="","",RANK(AB11,$AB$3:$AB$168,0)+COUNTIF($AB$3:AB11,AB11)-1) -> 156 | AE11: =IF(AA11="","",RANK(AA11,$AA$3:$AA$168,0)+COUNTIF($AA$3:AA11,AA11)-1) -> 12 | AF11: 74.37 | AG11: 2.3548284e+08 | AH11: =IFERROR(AG11/AZ11,"") -> 7073.681 | AI11: 21379 | AJ11: =IFERROR(AI11/F11,"") -> 0.01784717 | AK11: 964 | AL11: 1049 | AM11: 1089 | AN11: 4713 | AO11: 3696 | AP11: 2.1 | AQ11: =IFERROR(AL11*1000/AZ11,"") -> 31.510964 | AR11: 2671 | AS11: 1319 | AT11: 966 | AU11: 106 | AV11: 280 | AW11: =IFERROR(AS11/AR11,"") -> 0.49382254 | AX11: 20 | AY11: 9 | AZ11: 33290 | BA11: 714.971 | BB11: 46.56 | BC11: 0.595 | BD11: 48 | BE11: 97.61 | BF11: 4.6 | BG11: 3.7 | BH11: 30.28 | BI11: 4713 | BJ11: 2.1 | BK11: =IFERROR(BI11/AZ11,"") -> 0.14157405 | BL11: =IFERROR(AI11+K11+S11+AA11-F11,"") -> -1 | BM11: =IFERROR(F11+G11-C11,"") -> 0 | BN11: =IF(I11="","",IFERROR(C11*1000/H11-I11,"")) -> 0.0067420815
A12: 2407203 | B12: Macau | C12: 1111118 | D12: 1493271 | E12: 1315680 | F12: 1065640 | G12: 45478 | H12: 32260 | I12: 34442.58 | J12: 48071.89 | K12: 546975 | L12: =IFERROR(K12/F12,"") -> 0.5132831 | M12: =IFERROR(K12*1000/H12,"") -> 16955.208 | N12: =IF(L12="","",RANK(L12,$L$3:$L$168,0)+COUNTIF($L$3:L12,L12)-1) -> 11 | O12: =IF(K12="","",RANK(K12,$K$3:$K$168,0)+COUNTIF($K$3:K12,K12)-1) -> 7 | P12: 310 | Q12: =IFERROR(P12/AR12,"") -> 0.14065336 | R12: 45 | S12: 290912 | T12: =IFERROR(S12/F12,"") -> 0.27299276 | U12: =IFERROR(S12*1000/H12,"") -> 9017.7309 | V12: =IF(T12="","",RANK(T12,$T$3:$T$168,0)+COUNTIF($T$3:T12,T12)-1) -> 73 | W12: =IF(S12="","",RANK(S12,$S$3:$S$168,0)+COUNTIF($S$3:S12,S12)-1) -> 12 | X12: 874 | Y12: 971 | Z12: =IFERROR((X12+Y12)/AR12,"") -> 0.83711434 | AA12: 186985 | AB12: =IFERROR(AA12/F12,"") -> 0.17546732 | AC12: =IFERROR(AA12*1000/H12,"") -> 5796.1872 | AD12: =IF(AB12="","",RANK(AB12,$AB$3:$AB$168,0)+COUNTIF($AB$3:AB12,AB12)-1) -> 157 | AE12: =IF(AA12="","",RANK(AA12,$AA$3:$AA$168,0)+COUNTIF($AA$3:AA12,AA12)-1) -> 19 | AF12: 90.23 | AG12: 1.8943428e+08 | AH12: =IFERROR(AG12/AZ12,"") -> 6921.4908 | AI12: 40768 | AJ12: =IFERROR(AI12/F12,"") -> 0.038256822 | AK12: 811 | AL12: 836 | AM12: 870 | AN12: 5173 | AO12: 4327 | AP12: 2.4 | AQ12: =IFERROR(AL12*1000/AZ12,"") -> 30.545508 | AR12: 2204 | AS12: 1181 | AT12: 700 | AU12: 76 | AV12: 247 | AW12: =IFERROR(AS12/AR12,"") -> 0.53584392 | AX12: 38 | AY12: 11 | AZ12: 27369 | BA12: 775.302 | BB12: 35.3 | BC12: 0.665 | BD12: 42.8 | BE12: 99.18 | BF12: 5.5 | BG12: 4.3 | BH12: 57.41 | BI12: 5160 | BJ12: 2.4 | BK12: =IFERROR(BI12/AZ12,"") -> 0.18853447 | BL12: =IFERROR(AI12+K12+S12+AA12-F12,"") -> 0 | BM12: =IFERROR(F12+G12-C12,"") -> 0 | BN12: =IF(I12="","",IFERROR(C12*1000/H12-I12,"")) -> 0.011444513
A13: 2412203 | B13: São José de Mipibu | C13: 1040956 | D13: 1359848 | E13: 1457800 | F13: 878691 | G13: 162265 | H13: 44566 | I13: 23357.62 | J13: 30829.42 | K13: 122526 | L13: =IFERROR(K13/F13,"") -> 0.13944151 | M13: =IFERROR(K13*1000/H13,"") -> 2749.3156 | N13: =IF(L13="","",RANK(L13,$L$3:$L$168,0)+COUNTIF($L$3:L13,L13)-1) -> 49 | O13: =IF(K13="","",RANK(K13,$K$3:$K$168,0)+COUNTIF($K$3:K13,K13)-1) -> 23 | P13: 676 | Q13: =IFERROR(P13/AR13,"") -> 0.18576532 | R13: 164 | S13: 435717 | T13: =IFERROR(S13/F13,"") -> 0.49587056 | U13: =IFERROR(S13*1000/H13,"") -> 9776.8927 | V13: =IF(T13="","",RANK(T13,$T$3:$T$168,0)+COUNTIF($T$3:T13,T13)-1) -> 9 | W13: =IF(S13="","",RANK(S13,$S$3:$S$168,0)+COUNTIF($S$3:S13,S13)-1) -> 8 | X13: 1240 | Y13: 1660 | Z13: =IFERROR((X13+Y13)/AR13,"") -> 0.79692223 | AA13: 261506 | AB13: =IFERROR(AA13/F13,"") -> 0.2976086 | AC13: =IFERROR(AA13*1000/H13,"") -> 5867.8365 | AD13: =IF(AB13="","",RANK(AB13,$AB$3:$AB$168,0)+COUNTIF($AB$3:AB13,AB13)-1) -> 136 | AE13: =IF(AA13="","",RANK(AA13,$AA$3:$AA$168,0)+COUNTIF($AA$3:AA13,AA13)-1) -> 9 | AF13: 90.1 | AG13: 2.8549701e+08 | AH13: =IFERROR(AG13/AZ13,"") -> 6037.6646 | AI13: 58942 | AJ13: =IFERROR(AI13/F13,"") -> 0.067079326 | AK13: 1089 | AL13: 1204 | AM13: 1298 | AN13: 9918 | AO13: 8676 | AP13: 1.7 | AQ13: =IFERROR(AL13*1000/AZ13,"") -> 25.462082 | AR13: 3639 | AS13: 1973 | AT13: 1139 | AU13: 148 | AV13: 379 | AW13: =IFERROR(AS13/AR13,"") -> 0.54218192 | AX13: 50 | AY13: 13 | AZ13: 47286 | BA13: 289.987 | BB13: 163.06 | BC13: 0.611 | BD13: 48.2 | BE13: 98.35 | BF13: 5.2 | BG13: 3.7 | BH13: 4.85 | BI13: 9918 | BJ13: 1.7 | BK13: =IFERROR(BI13/AZ13,"") -> 0.20974496 | BL13: =IFERROR(AI13+K13+S13+AA13-F13,"") -> 0 | BM13: =IFERROR(F13+G13-C13,"") -> 0 | BN13: =IF(I13="","",IFERROR(C13*1000/H13-I13,"")) -> 0.0068904546
A14: 2402600 | B14: Ceará-Mirim | C14: 1002193 | D14: 1186374 | E14: 1260346 | F14: 904757 | G14: 97436 | H14: 74268 | I14: 13494.28 | J14: 15930.56 | K14: 45712 | L14: =IFERROR(K14/F14,"") -> 0.050524063 | M14: =IFERROR(K14*1000/H14,"") -> 615.50062 | N14: =IF(L14="","",RANK(L14,$L$3:$L$168,0)+COUNTIF($L$3:L14,L14)-1) -> 88 | O14: =IF(K14="","",RANK(K14,$K$3:$K$168,0)+COUNTIF($K$3:K14,K14)-1) -> 40 | P14: 790 | Q14: =IFERROR(P14/AR14,"") -> 0.1823638 | R14: 165 | S14: 365315 | T14: =IFERROR(S14/F14,"") -> 0.4037714 | U14: =IFERROR(S14*1000/H14,"") -> 4918.8749 | V14: =IF(T14="","",RANK(T14,$T$3:$T$168,0)+COUNTIF($T$3:T14,T14)-1) -> 26 | W14: =IF(S14="","",RANK(S14,$S$3:$S$168,0)+COUNTIF($S$3:S14,S14)-1) -> 10 | X14: 1557 | Y14: 1891 | Z14: =IFERROR((X14+Y14)/AR14,"") -> 0.79593721 | AA14: 419272 | AB14: =IFERROR(AA14/F14,"") -> 0.46340841 | AC14: =IFERROR(AA14*1000/H14,"") -> 5645.3924 | AD14: =IF(AB14="","",RANK(AB14,$AB$3:$AB$168,0)+COUNTIF($AB$3:AB14,AB14)-1) -> 100 | AE14: =IF(AA14="","",RANK(AA14,$AA$3:$AA$168,0)+COUNTIF($AA$3:AA14,AA14)-1) -> 6 | AF14: 74.58 | AG14: 3.9459177e+08 | AH14: =IFERROR(AG14/AZ14,"") -> 4987.5722 | AI14: 74458 | AJ14: =IFERROR(AI14/F14,"") -> 0.08229613 | AK14: 1329 | AL14: 1475 | AM14: 1639 | AN14: 8956 | AO14: 7325 | AP14: 1.7 | AQ14: =IFERROR(AL14*1000/AZ14,"") -> 18.643746 | AR14: 4332 | AS14: 2265 | AT14: 1387 | AU14: 252 | AV14: 428 | AW14: =IFERROR(AS14/AR14,"") -> 0.52285319 | AX14: 78 | AY14: 16 | AZ14: 79115 | BA14: 724.838 | BB14: 109.15 | BC14: 0.616 | BD14: 46.1 | BE14: 98 | BF14: 4.5 | BG14: 3.7 | BH14: 24.78 | BI14: 8956 | BJ14: 1.7 | BK14: =IFERROR(BI14/AZ14,"") -> 0.1132023 | BL14: =IFERROR(AI14+K14+S14+AA14-F14,"") -> 0 | BM14: =IFERROR(F14+G14-C14,"") -> 0 | BN14: =IF(I14="","",IFERROR(C14*1000/H14-I14,"")) -> -0.0025184467
... A42: 2409506 | B42: Pedra Grande | C42: 293283 | D42: 243846 | E42: 325405 | F42: 273296 | G42: 19986 | H42: 3163 | I42: 92722.93 | J42: 89940.55 | K42: 213403 | L42: =IFERROR(K42/F42,"") -> 0.78084934 | M42: =IFERROR(K42*1000/H42,"") -> 67468.543 | N42: =IF(L42="","",RANK(L42,$L$3:$L$168,0)+COUNTIF($L$3:L42,L42)-1) -> 4 | O42: =IF(K42="","",RANK(K42,$K$3:$K$168,0)+COUNTIF($K$3:K42,K42)-1) -> 18 | P42: 43 | Q42: =IFERROR(P42/AR42,"") -> 0.21827411 | R42: 27 | S42: 18822 | T42: =IFERROR(S42/F42,"") -> 0.068870382 | U42: =IFERROR(S42*1000/H42,"") -> 5950.6797 | V42: =IF(T42="","",RANK(T42,$T$3:$T$168,0)+COUNTIF($T$3:T42,T42)-1) -> 163 | W42: =IF(S42="","",RANK(S42,$S$3:$S$168,0)+COUNTIF($S$3:S42,S42)-1) -> 106 | X42: 57 | Y42: 87 | Z42: =IFERROR((X42+Y42)/AR42,"") -> 0.73096447 | AA42: 33888 | AB42: =IFERROR(AA42/F42,"") -> 0.12399742 | AC42: =IFERROR(AA42*1000/H42,"") -> 10713.879 | AD42: =IF(AB42="","",RANK(AB42,$AB$3:$AB$168,0)+COUNTIF($AB$3:AB42,AB42)-1) -> 161 | AE42: =IF(AA42="","",RANK(AA42,$AA$3:$AA$168,0)+COUNTIF($AA$3:AA42,AA42)-1) -> 120 | AF42: 90.01 | AG42: 58690869 | AH42: =IFERROR(AG42/AZ42,"") -> 16221.91 | AI42: 7183 | AJ42: =IFERROR(AI42/F42,"") -> 0.026282858 | AK42: 88 | AL42: 101 | AM42: 101 | AN42: 438 | AO42: 349 | AP42: 2.4 | AQ42: =IFERROR(AL42*1000/AZ42,"") -> 27.915976 | AR42: 197 | AS42: 69 | AT42: 48 | AU42: 2 | AV42: 78 | AW42: =IFERROR(AS42/AR42,"") -> 0.35025381 | AX42: 3 | AY42: 7 | AZ42: 3618 | BA42: 221.167 | BB42: 16.36 | BC42: 0.559 | BD42: 55 | BE42: 99.26 | BF42: 5 | BG42: 4.1 | BH42: 0.81 | BI42: 438 | BJ42: 2.4 | BK42: =IFERROR(BI42/AZ42,"") -> 0.12106136 | BL42: =IFERROR(AI42+K42+S42+AA42-F42,"") -> 0 | BM42: =IFERROR(F42+G42-C42,"") -> -1 | BN42: =IF(I42="","",IFERROR(C42*1000/H42-I42,"")) -> 0.11773949
A43: 2401651 | B43: Bodó | C43: 286574 | D43: 229572 | E43: 240166 | F43: 283980 | G43: 2593 | H43: 2171 | I43: 132000.71 | J43: 104148.52 | K43: 246251 | L43: =IFERROR(K43/F43,"") -> 0.86714205 | M43: =IFERROR(K43*1000/H43,"") -> 113427.45 | N43: =IF(L43="","",RANK(L43,$L$3:$L$168,0)+COUNTIF($L$3:L43,L43)-1) -> 3 | O43: =IF(K43="","",RANK(K43,$K$3:$K$168,0)+COUNTIF($K$3:K43,K43)-1) -> 16 | P43: 37 | Q43: =IFERROR(P43/AR43,"") -> 0.22424242 | R43: 24 | S43: 9465 | T43: =IFERROR(S43/F43,"") -> 0.033329812 | U43: =IFERROR(S43*1000/H43,"") -> 4359.7421 | V43: =IF(T43="","",RANK(T43,$T$3:$T$168,0)+COUNTIF($T$3:T43,T43)-1) -> 166 | W43: =IF(S43="","",RANK(S43,$S$3:$S$168,0)+COUNTIF($S$3:S43,S43)-1) -> 149 | X43: 32 | Y43: 89 | Z43: =IFERROR((X43+Y43)/AR43,"") -> 0.73333333 | AA43: 24181 | AB43: =IFERROR(AA43/F43,"") -> 0.085150363 | AC43: =IFERROR(AA43*1000/H43,"") -> 11138.185 | AD43: =IF(AB43="","",RANK(AB43,$AB$3:$AB$168,0)+COUNTIF($AB$3:AB43,AB43)-1) -> 164 | AE43: =IF(AA43="","",RANK(AA43,$AA$3:$AA$168,0)+COUNTIF($AA$3:AA43,AA43)-1) -> 153 | AF43: 69.91 | AG43: 53841631 | AH43: =IFERROR(AG43/AZ43,"") -> 23348.496 | AI43: 4083 | AJ43: =IFERROR(AI43/F43,"") -> 0.014377773 | AK43: 77 | AL43: 120 | AM43: 123 | AN43: 353 | AO43: 257 | AP43: 2.1 | AQ43: =IFERROR(AL43*1000/AZ43,"") -> 52.038161 | AR43: 165 | AS43: 55 | AT43: 21 | AU43: 6 | AV43: 83 | AW43: =IFERROR(AS43/AR43,"") -> 0.33333333 | AX43: 1 | AY43: 6 | AZ43: 2306 | BA43: 253.519 | BB43: 9.1 | BC43: 0.629 | BD43: 52.4 | BE43: 99 | BF43: 5.3 | BH43: 8.93 | BI43: 353 | BJ43: 2.1 | BK43: =IFERROR(BI43/AZ43,"") -> 0.15307892 | BL43: =IFERROR(AI43+K43+S43+AA43-F43,"") -> 0 | BM43: =IFERROR(F43+G43-C43,"") -> -1 | BN43: =IF(I43="","",IFERROR(C43*1000/H43-I43,"")) -> 0.21123445
A44: 2407807 | B44: Monte Alegre | C44: 271451 | D44: 325278 | E44: 348751 | F44: 252958 | G44: 18493 | H44: 22698 | I44: 11959.26 | J44: 15142.66 | K44: 23674 | L44: =IFERROR(K44/F44,"") -> 0.093588659 | M44: =IFERROR(K44*1000/H44,"") -> 1042.9994 | N44: =IF(L44="","",RANK(L44,$L$3:$L$168,0)+COUNTIF($L$3:L44,L44)-1) -> 61 | O44: =IF(K44="","",RANK(K44,$K$3:$K$168,0)+COUNTIF($K$3:K44,K44)-1) -> 53 | P44: 169 | Q44: =IFERROR(P44/AR44,"") -> 0.15943396 | R44: 22 | S44: 78453 | T44: =IFERROR(S44/F44,"") -> 0.3101424 | U44: =IFERROR(S44*1000/H44,"") -> 3456.3838 | V44: =IF(T44="","",RANK(T44,$T$3:$T$168,0)+COUNTIF($T$3:T44,T44)-1) -> 51 | W44: =IF(S44="","",RANK(S44,$S$3:$S$168,0)+COUNTIF($S$3:S44,S44)-1) -> 36 | X44: 385 | Y44: 473 | Z44: =IFERROR((X44+Y44)/AR44,"") -> 0.80943396 | AA44: 136183 | AB44: =IFERROR(AA44/F44,"") -> 0.5383621 | AC44: =IFERROR(AA44*1000/H44,"") -> 5999.7797 | AD44: =IF(AB44="","",RANK(AB44,$AB$3:$AB$168,0)+COUNTIF($AB$3:AB44,AB44)-1) -> 75 | AE44: =IF(AA44="","",RANK(AA44,$AA$3:$AA$168,0)+COUNTIF($AA$3:AA44,AA44)-1) -> 27 | AF44: 85.02 | AG44: 1.5496355e+08 | AH44: =IFERROR(AG44/AZ44,"") -> 6728.477 | AI44: 14648 | AJ44: =IFERROR(AI44/F44,"") -> 0.057906846 | AK44: 328 | AL44: 374 | AM44: 389 | AN44: 2136 | AO44: 1754 | AP44: 1.9 | AQ44: =IFERROR(AL44*1000/AZ44,"") -> 16.238982 | AR44: 1060 | AS44: 538 | AT44: 352 | AU44: 40 | AV44: 130 | AW44: =IFERROR(AS44/AR44,"") -> 0.50754717 | AX44: 22 | AY44: 11 | AZ44: 23031 | BA44: 211.259 | BB44: 109.02 | BC44: 0.609 | BD44: 50.6 | BE44: 97.97 | BF44: 5 | BG44: 4.6 | BH44: 10.3 | BI44: 2136 | BJ44: 1.9 | BK44: =IFERROR(BI44/AZ44,"") -> 0.092744562 | BL44: =IFERROR(AI44+K44+S44+AA44-F44,"") -> 0 | BM44: =IFERROR(F44+G44-C44,"") -> 0 | BN44: =IF(I44="","",IFERROR(C44*1000/H44-I44,"")) -> -0.012489206
A45: 2406502 | B45: Lagoa Nova | C45: 269032 | D45: 291874 | E45: 326107 | F45: 236730 | G45: 32302 | H45: 15880 | I45: 16941.59 | J45: 20940.54 | K45: 77170 | L45: =IFERROR(K45/F45,"") -> 0.32598319 | M45: =IFERROR(K45*1000/H45,"") -> 4859.5718 | N45: =IF(L45="","",RANK(L45,$L$3:$L$168,0)+COUNTIF($L$3:L45,L45)-1) -> 24 | O45: =IF(K45="","",RANK(K45,$K$3:$K$168,0)+COUNTIF($K$3:K45,K45)-1) -> 34 | P45: 200 | Q45: =IFERROR(P45/AR45,"") -> 0.18709074 | R45: 75 | S45: 47028 | T45: =IFERROR(S45/F45,"") -> 0.1986567 | U45: =IFERROR(S45*1000/H45,"") -> 2961.461 | V45: =IF(T45="","",RANK(T45,$T$3:$T$168,0)+COUNTIF($T$3:T45,T45)-1) -> 144 | W45: =IF(S45="","",RANK(S45,$S$3:$S$168,0)+COUNTIF($S$3:S45,S45)-1) -> 51 | X45: 420 | Y45: 433 | Z45: =IFERROR((X45+Y45)/AR45,"") -> 0.797942 | AA45: 97120 | AB45: =IFERROR(AA45/F45,"") -> 0.41025641 | AC45: =IFERROR(AA45*1000/H45,"") -> 6115.869 | AD45: =IF(AB45="","",RANK(AB45,$AB$3:$AB$168,0)+COUNTIF($AB$3:AB45,AB45)-1) -> 116 | AE45: =IF(AA45="","",RANK(AA45,$AA$3:$AA$168,0)+COUNTIF($AA$3:AA45,AA45)-1) -> 36 | AF45: 91.86 | AG45: 1.0229429e+08 | AH45: =IFERROR(AG45/AZ45,"") -> 6568.6951 | AI45: 15412 | AJ45: =IFERROR(AI45/F45,"") -> 0.065103705 | AK45: 378 | AL45: 440 | AM45: 459 | AN45: 2003 | AO45: 1493 | AP45: 1.8 | AQ45: =IFERROR(AL45*1000/AZ45,"") -> 28.254029 | AR45: 1069 | AS45: 483 | AT45: 346 | AU45: 41 | AV45: 199 | AW45: =IFERROR(AS45/AR45,"") -> 0.45182413 | AX45: 8 | AY45: 8 | AZ45: 15573 | BA45: 176.302 | BB45: 88.33 | BC45: 0.585 | BD45: 54.9 | BE45: 99.36 | BF45: 5.3 | BG45: 4.4 | BH45: 22.75 | BI45: 2003 | BJ45: 1.8 | BK45: =IFERROR(BI45/AZ45,"") -> 0.12862005 | BL45: =IFERROR(AI45+K45+S45+AA45-F45,"") -> 0 | BM45: =IFERROR(F45+G45-C45,"") -> 0 | BN45: =IF(I45="","",IFERROR(C45*1000/H45-I45,"")) -> -0.028287154
A46: 2412609 | B46: São Paulo do Potengi | C46: 231552 | D46: 273442 | E46: 290640 | F46: 212966 | G46: 18586 | H46: 17858 | I46: 12966.29 | J46: 17314.45 | K46: 13377 | L46: =IFERROR(K46/F46,"") -> 0.062812843 | M46: =IFERROR(K46*1000/H46,"") -> 749.07604 | N46: =IF(L46="","",RANK(L46,$L$3:$L$168,0)+COUNTIF($L$3:L46,L46)-1) -> 77 | O46: =IF(K46="","",RANK(K46,$K$3:$K$168,0)+COUNTIF($K$3:K46,K46)-1) -> 61 | P46: 188 | Q46: =IFERROR(P46/AR46,"") -> 0.13642961 | R46: 11 | S46: 86723 | T46: =IFERROR(S46/F46,"") -> 0.40721524 | U46: =IFERROR(S46*1000/H46,"") -> 4856.2549 | V46: =IF(T46="","",RANK(T46,$T$3:$T$168,0)+COUNTIF($T$3:T46,T46)-1) -> 23 | W46: =IF(S46="","",RANK(S46,$S$3:$S$168,0)+COUNTIF($S$3:S46,S46)-1) -> 33 | X46: 499 | Y46: 679 | Z46: =IFERROR((X46+Y46)/AR46,"") -> 0.85486212 | AA46: 105894 | AB46: =IFERROR(AA46/F46,"") -> 0.4972343 | AC46: =IFERROR(AA46*1000/H46,"") -> 5929.7794 | AD46: =IF(AB46="","",RANK(AB46,$AB$3:$AB$168,0)+COUNTIF($AB$3:AB46,AB46)-1) -> 89 | AE46: =IF(AA46="","",RANK(AA46,$AA$3:$AA$168,0)+COUNTIF($AA$3:AA46,AA46)-1) -> 31 | AF46: 88.84 | AG46: 1.1490339e+08 | AH46: =IFERROR(AG46/AZ46,"") -> 6845.192 | AI46: 6972 | AJ46: =IFERROR(AI46/F46,"") -> 0.03273762 | AK46: 358 | AL46: 393 | AM46: 413 | AN46: 2007 | AO46: 1620 | AP46: 1.6 | AQ46: =IFERROR(AL46*1000/AZ46,"") -> 23.412367 | AR46: 1378 | AS46: 809 | AT46: 425 | AU46: 30 | AV46: 114 | AW46: =IFERROR(AS46/AR46,"") -> 0.58708273 | AX46: 5 | AY46: 7 | AZ46: 16786 | BA46: 240.425 | BB46: 69.82 | BC46: 0.622 | BD46: 47.7 | BE46: 100 | BF46: 4.7 | BG46: 3.7 | BH46: 55.12 | BI46: 2007 | BJ46: 1.6 | BK46: =IFERROR(BI46/AZ46,"") -> 0.11956392 | BL46: =IFERROR(AI46+K46+S46+AA46-F46,"") -> 0 | BM46: =IFERROR(F46+G46-C46,"") -> 0 | BN46: =IF(I46="","",IFERROR(C46*1000/H46-I46,"")) -> -0.00038190167
A47: 2414605 | B47: Upanema | C47: 214152 | D47: 330523 | E47: 370220 | F47: 201496 | G47: 12656 | H47: 14937 | I47: 14337.04 | J47: 27268.15 | K47: 40968 | L47: =IFERROR(K47/F47,"") -> 0.20331917 | M47: =IFERROR(K47*1000/H47,"") -> 2742.7194 | N47: =IF(L47="","",RANK(L47,$L$3:$L$168,0)+COUNTIF($L$3:L47,L47)-1) -> 34 | O47: =IF(K47="","",RANK(K47,$K$3:$K$168,0)+COUNTIF($K$3:K47,K47)-1) -> 41 | P47: 110 | Q47: =IFERROR(P47/AR47,"") -> 0.15942029 | R47: 14 | S47: 55723 | T47: =IFERROR(S47/F47,"") -> 0.27654643 | U47: =IFERROR(S47*1000/H47,"") -> 3730.5349 | V47: =IF(T47="","",RANK(T47,$T$3:$T$168,0)+COUNTIF($T$3:T47,T47)-1) -> 69 | W47: =IF(S47="","",RANK(S47,$S$3:$S$168,0)+COUNTIF($S$3:S47,S47)-1) -> 48 | X47: 273 | Y47: 285 | Z47: =IFERROR((X47+Y47)/AR47,"") -> 0.80869565 | AA47: 91275 | AB47: =IFERROR(AA47/F47,"") -> 0.45298666 | AC47: =IFERROR(AA47*1000/H47,"") -> 6110.6648 | AD47: =IF(AB47="","",RANK(AB47,$AB$3:$AB$168,0)+COUNTIF($AB$3:AB47,AB47)-1) -> 104 | AE47: =IF(AA47="","",RANK(AA47,$AA$3:$AA$168,0)+COUNTIF($AA$3:AA47,AA47)-1) -> 39 | AF47: 89.91 | AG47: 91993353 | AH47: =IFERROR(AG47/AZ47,"") -> 6775.676 | AI47: 13530 | AJ47: =IFERROR(AI47/F47,"") -> 0.067147735 | AK47: 263 | AL47: 284 | AM47: 290 | AN47: 1647 | AO47: 1356 | AP47: 2 | AQ47: =IFERROR(AL47*1000/AZ47,"") -> 20.917729 | AR47: 690 | AS47: 335 | AT47: 214 | AU47: 41 | AV47: 100 | AW47: =IFERROR(AS47/AR47,"") -> 0.48550725 | AX47: 13 | AY47: 9 | AZ47: 13577 | BA47: 873.14 | BB47: 15.55 | BC47: 0.596 | BD47: 55.4 | BE47: 99.53 | BF47: 5.2 | BG47: 4.8 | BH47: 17.48 | BI47: 1647 | BJ47: 2 | BK47: =IFERROR(BI47/AZ47,"") -> 0.12130809 | BL47: =IFERROR(AI47+K47+S47+AA47-F47,"") -> 0 | BM47: =IFERROR(F47+G47-C47,"") -> 0 | BN47: =IF(I47="","",IFERROR(C47*1000/H47-I47,"")) -> -0.024535047
A48: 2405603 | B48: Jardim de Piranhas | C48: 213313 | D48: 243966 | E48: 276161 | F48: 196355 | G48: 16959 | H48: 15044 | I48: 14179.29 | J48: 19758.23 | K48: 21275 | L48: =IFERROR(K48/F48,"") -> 0.10834967 | M48: =IFERROR(K48*1000/H48,"") -> 1414.1851 | N48: =IF(L48="","",RANK(L48,$L$3:$L$168,0)+COUNTIF($L$3:L48,L48)-1) -> 56 | O48: =IF(K48="","",RANK(K48,$K$3:$K$168,0)+COUNTIF($K$3:K48,K48)-1) -> 55 | P48: 193 | Q48: =IFERROR(P48/AR48,"") -> 0.24871134 | R48: 18 | S48: 65103 | T48: =IFERROR(S48/F48,"") -> 0.33155764 | U48: =IFERROR(S48*1000/H48,"") -> 4327.506 | V48: =IF(T48="","",RANK(T48,$T$3:$T$168,0)+COUNTIF($T$3:T48,T48)-1) -> 42 | W48: =IF(S48="","",RANK(S48,$S$3:$S$168,0)+COUNTIF($S$3:S48,S48)-1) -> 40 | X48: 341 | Y48: 232 | Z48: =IFERROR((X48+Y48)/AR48,"") -> 0.73840206 | AA48: 89061 | AB48: =IFERROR(AA48/F48,"") -> 0.45357134 | AC48: =IFERROR(AA48*1000/H48,"") -> 5920.0346 | AD48: =IF(AB48="","",RANK(AB48,$AB$3:$AB$168,0)+COUNTIF($AB$3:AB48,AB48)-1) -> 103 | AE48: =IF(AA48="","",RANK(AA48,$AA$3:$AA$168,0)+COUNTIF($AA$3:AA48,AA48)-1) -> 40 | AF48: 91.65 | AG48: 88953554 | AH48: =IFERROR(AG48/AZ48,"") -> 6364.2809 | AI48: 20915 | AJ48: =IFERROR(AI48/F48,"") -> 0.10651626 | AK48: 308 | AL48: 333 | AM48: 351 | AN48: 1853 | AO48: 1529 | AP48: 1.8 | AQ48: =IFERROR(AL48*1000/AZ48,"") -> 23.824855 | AR48: 776 | AS48: 332 | AT48: 327 | AU48: 30 | AV48: 87 | AW48: =IFERROR(AS48/AR48,"") -> 0.42783505 | AX48: 2 | AY48: 8 | AZ48: 13977 | BA48: 330.53 | BB48: 42.29 | BC48: 0.603 | BD48: 44.6 | BE48: 98.75 | BF48: 5.1 | BG48: 4.9 | BH48: 25.96 | BI48: 1853 | BJ48: 1.8 | BK48: =IFERROR(BI48/AZ48,"") -> 0.13257494 | BL48: =IFERROR(AI48+K48+S48+AA48-F48,"") -> -1 | BM48: =IFERROR(F48+G48-C48,"") -> 1 | BN48: =IF(I48="","",IFERROR(C48*1000/H48-I48,"")) -> -0.015870779
A49: 2402501 | B49: Carnaubais | C49: 210948 | D49: 302478 | E49: 231816 | F49: 203394 | G49: 7554 | H49: 10972 | I49: 19226.04 | J49: 23864.16 | K49: 74994 | L49: =IFERROR(K49/F49,"") -> 0.36871294 | M49: =IFERROR(K49*1000/H49,"") -> 6835.0346 | N49: =IF(L49="","",RANK(L49,$L$3:$L$168,0)+COUNTIF($L$3:L49,L49)-1) -> 20 | O49: =IF(K49="","",RANK(K49,$K$3:$K$168,0)+COUNTIF($K$3:K49,K49)-1) -> 36 | P49: 64 | Q49: =IFERROR(P49/AR49,"") -> 0.11700183 | R49: 11 | S49: 47258 | T49: =IFERROR(S49/F49,"") -> 0.23234707 | U49: =IFERROR(S49*1000/H49,"") -> 4307.1455 | V49: =IF(T49="","",RANK(T49,$T$3:$T$168,0)+COUNTIF($T$3:T49,T49)-1) -> 109 | W49: =IF(S49="","",RANK(S49,$S$3:$S$168,0)+COUNTIF($S$3:S49,S49)-1) -> 50 | X49: 194 | Y49: 255 | Z49: =IFERROR((X49+Y49)/AR49,"") -> 0.82084095 | AA49: 69035 | AB49: =IFERROR(AA49/F49,"") -> 0.33941513 | AC49: =IFERROR(AA49*1000/H49,"") -> 6291.9249 | AD49: =IF(AB49="","",RANK(AB49,$AB$3:$AB$168,0)+COUNTIF($AB$3:AB49,AB49)-1) -> 133 | AE49: =IF(AA49="","",RANK(AA49,$AA$3:$AA$168,0)+COUNTIF($AA$3:AA49,AA49)-1) -> 63 | AF49: 94.29 | AG49: 81673307 | AH49: =IFERROR(AG49/AZ49,"") -> 8407.7936 | AI49: 12107 | AJ49: =IFERROR(AI49/F49,"") -> 0.059524863 | AK49: 218 | AL49: 241 | AM49: 252 | AN49: 1028 | AO49: 827 | AP49: 1.9 | AQ49: =IFERROR(AL49*1000/AZ49,"") -> 24.809553 | AR49: 547 | AS49: 245 | AT49: 171 | AU49: 32 | AV49: 99 | AW49: =IFERROR(AS49/AR49,"") -> 0.44789762 | AX49: 25 | AY49: 9 | AZ49: 9714 | BA49: 517.737 | BB49: 18.76 | BC49: 0.589 | BD49: 50.7 | BE49: 99.36 | BF49: 5.4 | BG49: 5 | BH49: 26.52 | BI49: 1028 | BJ49: 1.9 | BK49: =IFERROR(BI49/AZ49,"") -> 0.10582664 | BL49: =IFERROR(AI49+K49+S49+AA49-F49,"") -> 0 | BM49: =IFERROR(F49+G49-C49,"") -> 0 | BN49: =IF(I49="","",IFERROR(C49*1000/H49-I49,"")) -> -0.010105724
A50: 2405702 | B50: Jardim do Seridó | C50: 207991 | D50: 237956 | E50: 244663 | F50: 187190 | G50: 20801 | H50: 12397 | I50: 16777.53 | J50: 20992.11 | K50: 30304 | L50: =IFERROR(K50/F50,"") -> 0.16188899 | M50: =IFERROR(K50*1000/H50,"") -> 2444.4624 | N50: =IF(L50="","",RANK(L50,$L$3:$L$168,0)+COUNTIF($L$3:L50,L50)-1) -> 43 | O50: =IF(K50="","",RANK(K50,$K$3:$K$168,0)+COUNTIF($K$3:K50,K50)-1) -> 47 | P50: 218 | Q50: =IFERROR(P50/AR50,"") -> 0.19516562 | R50: 21 | S50: 68528 | T50: =IFERROR(S50/F50,"") -> 0.36608793 | U50: =IFERROR(S50*1000/H50,"") -> 5527.789 | V50: =IF(T50="","",RANK(T50,$T$3:$T$168,0)+COUNTIF($T$3:T50,T50)-1) -> 32 | W50: =IF(S50="","",RANK(S50,$S$3:$S$168,0)+COUNTIF($S$3:S50,S50)-1) -> 39 | X50: 420 | Y50: 466 | Z50: =IFERROR((X50+Y50)/AR50,"") -> 0.79319606 | AA50: 71059 | AB50: =IFERROR(AA50/F50,"") -> 0.37960895 | AC50: =IFERROR(AA50*1000/H50,"") -> 5731.9513 | AD50: =IF(AB50="","",RANK(AB50,$AB$3:$AB$168,0)+COUNTIF($AB$3:AB50,AB50)-1) -> 121 | AE50: =IF(AA50="","",RANK(AA50,$AA$3:$AA$168,0)+COUNTIF($AA$3:AA50,AA50)-1) -> 59 | AF50: 83.65 | AG50: 71432891 | AH50: =IFERROR(AG50/AZ50,"") -> 6128.9482 | AI50: 17299 | AJ50: =IFERROR(AI50/F50,"") -> 0.092414125 | AK50: 393 | AL50: 433 | AM50: 462 | AN50: 2048 | AO50: 1586 | AP50: 1.6 | AQ50: =IFERROR(AL50*1000/AZ50,"") -> 37.151437 | AR50: 1117 | AS50: 593 | AT50: 364 | AU50: 51 | AV50: 109 | AW50: =IFERROR(AS50/AR50,"") -> 0.5308863 | AX50: 3 | AY50: 10 | AZ50: 11655 | BA50: 367.645 | BB50: 31.7 | BC50: 0.663 | BD50: 41.3 | BE50: 100 | BF50: 6.3 | BG50: 5.4 | BH50: 71.88 | BI50: 2048 | BJ50: 1.6 | BK50: =IFERROR(BI50/AZ50,"") -> 0.17571858 | BL50: =IFERROR(AI50+K50+S50+AA50-F50,"") -> 0 | BM50: =IFERROR(F50+G50-C50,"") -> 0 | BN50: =IF(I50="","",IFERROR(C50*1000/H50-I50,"")) -> -0.0031789949
A51: 2414001 | B51: Tangará | C51: 201782 | D51: 213678 | E51: 225000 | F51: 182311 | G51: 19471 | H51: 16008 | I51: 12605.08 | J51: 16941.5 | K51: 18673 | L51: =IFERROR(K51/F51,"") -> 0.10242388 | M51: =IFERROR(K51*1000/H51,"") -> 1166.4793 | N51: =IF(L51="","",RANK(L51,$L$3:$L$168,0)+COUNTIF($L$3:L51,L51)-1) -> 57 | O51: =IF(K51="","",RANK(K51,$K$3:$K$168,0)+COUNTIF($K$3:K51,K51)-1) -> 57 | P51: 96 | Q51: =IFERROR(P51/AR51,"") -> 0.10946408 | R51: 14 | S51: 64277 | T51: =IFERROR(S51/F51,"") -> 0.35256786 | U51: =IFERROR(S51*1000/H51,"") -> 4015.3048 | V51: =IF(T51="","",RANK(T51,$T$3:$T$168,0)+COUNTIF($T$3:T51,T51)-1) -> 36 | W51: =IF(S51="","",RANK(S51,$S$3:$S$168,0)+COUNTIF($S$3:S51,S51)-1) -> 44 | X51: 400 | Y51: 368 | Z51: =IFERROR((X51+Y51)/AR51,"") -> 0.87571266 | AA51: 94105 | AB51: =IFERROR(AA51/F51,"") -> 0.5161784 | AC51: =IFERROR(AA51*1000/H51,"") -> 5878.6232 | AD51: =IF(AB51="","",RANK(AB51,$AB$3:$AB$168,0)+COUNTIF($AB$3:AB51,AB51)-1) -> 85 | AE51: =IF(AA51="","",RANK(AA51,$AA$3:$AA$168,0)+COUNTIF($AA$3:AA51,AA51)-1) -> 38 | AF51: 88.69 | AG51: 91171164 | AH51: =IFERROR(AG51/AZ51,"") -> 6864.7816 | AI51: 5256 | AJ51: =IFERROR(AI51/F51,"") -> 0.028829857 | AK51: 281 | AL51: 320 | AM51: 324 | AN51: 1449 | AO51: 1148 | AP51: 2.1 | AQ51: =IFERROR(AL51*1000/AZ51,"") -> 24.094571 | AR51: 877 | AS51: 477 | AT51: 274 | AU51: 35 | AV51: 91 | AW51: =IFERROR(AS51/AR51,"") -> 0.54389966 | AX51: 6 | AY51: 6 | AZ51: 13281 | BA51: 339.484 | BB51: 39.12 | BC51: 0.608 | BD51: 51.1 | BE51: 99.58 | BF51: 4.4 | BG51: 4.3 | BH51: 53.25 | BI51: 1449 | BJ51: 2.1 | BK51: =IFERROR(BI51/AZ51,"") -> 0.10910323 | BL51: =IFERROR(AI51+K51+S51+AA51-F51,"") -> 0 | BM51: =IFERROR(F51+G51-C51,"") -> 0 | BN51: =IF(I51="","",IFERROR(C51*1000/H51-I51,"")) -> -0.0075362319
A52: 2404705 | B52: Ipanguaçu | C52: 196498 | D52: 215667 | E52: 263825 | F52: 183123 | G52: 13375 | H52: 15759 | I52: 12468.96 | J52: 18669.94 | K52: 7935 | L52: =IFERROR(K52/F52,"") -> 0.043331531 | M52: =IFERROR(K52*1000/H52,"") -> 503.5218 | N52: =IF(L52="","",RANK(L52,$L$3:$L$168,0)+COUNTIF($L$3:L52,L52)-1) -> 107 | O52: =IF(K52="","",RANK(K52,$K$3:$K$168,0)+COUNTIF($K$3:K52,K52)-1) -> 73 | P52: 79 | Q52: =IFERROR(P52/AR52,"") -> 0.13210702 | R52: 7 | S52: 40826 | T52: =IFERROR(S52/F52,"") -> 0.22294305 | U52: =IFERROR(S52*1000/H52,"") -> 2590.6466 | V52: =IF(T52="","",RANK(T52,$T$3:$T$168,0)+COUNTIF($T$3:T52,T52)-1) -> 120 | W52: =IF(S52="","",RANK(S52,$S$3:$S$168,0)+COUNTIF($S$3:S52,S52)-1) -> 60 | X52: 216 | Y52: 272 | Z52: =IFERROR((X52+Y52)/AR52,"") -> 0.81605351 | AA52: 86022 | AB52: =IFERROR(AA52/F52,"") -> 0.46974984 | AC52: =IFERROR(AA52*1000/H52,"") -> 5458.5951 | AD52: =IF(AB52="","",RANK(AB52,$AB$3:$AB$168,0)+COUNTIF($AB$3:AB52,AB52)-1) -> 97 | AE52: =IF(AA52="","",RANK(AA52,$AA$3:$AA$168,0)+COUNTIF($AA$3:AA52,AA52)-1) -> 42 | AF52: 94.32 | AG52: 83407398 | AH52: =IFERROR(AG52/AZ52,"") -> 5902.4413 | AI52: 48341 | AJ52: =IFERROR(AI52/F52,"") -> 0.26398104 | AK52: 297 | AL52: 369 | AM52: 376 | AN52: 1904 | AO52: 1563 | AP52: 1.6 | AQ52: =IFERROR(AL52*1000/AZ52,"") -> 26.112802 | AR52: 598 | AS52: 223 | AT52: 222 | AU52: 22 | AV52: 131 | AW52: =IFERROR(AS52/AR52,"") -> 0.3729097 | AX52: 24 | AY52: 7 | AZ52: 14131 | BA52: 374.245 | BB52: 37.76 | BC52: 0.603 | BD52: 47.1 | BE52: 98.28 | BF52: 5.3 | BG52: 3.8 | BH52: 0.96 | BI52: 1904 | BJ52: 1.6 | BK52: =IFERROR(BI52/AZ52,"") -> 0.13473923 | BL52: =IFERROR(AI52+K52+S52+AA52-F52,"") -> 1 | BM52: =IFERROR(F52+G52-C52,"") -> 0 | BN52: =IF(I52="","",IFERROR(C52*1000/H52-I52,"")) -> -0.021615585
A53: 2410900 | B53: Riachuelo | C53: 192156 | D53: 345300 | E53: 319931 | F53: 180300 | G53: 11856 | H53: 8310 | I53: 23123.45 | J53: 43298.29 | K53: 84834 | L53: =IFERROR(K53/F53,"") -> 0.47051581 | M53: =IFERROR(K53*1000/H53,"") -> 10208.664 | N53: =IF(L53="","",RANK(L53,$L$3:$L$168,0)+COUNTIF($L$3:L53,L53)-1) -> 14 | O53: =IF(K53="","",RANK(K53,$K$3:$K$168,0)+COUNTIF($K$3:K53,K53)-1) -> 26 | P53: 43 | Q53: =IFERROR(P53/AR53,"") -> 0.13230769 | R53: 10 | S53: 39733 | T53: =IFERROR(S53/F53,"") -> 0.2203716 | U53: =IFERROR(S53*1000/H53,"") -> 4781.3478 | V53: =IF(T53="","",RANK(T53,$T$3:$T$168,0)+COUNTIF($T$3:T53,T53)-1) -> 124 | W53: =IF(S53="","",RANK(S53,$S$3:$S$168,0)+COUNTIF($S$3:S53,S53)-1) -> 64 | X53: 134 | Y53: 136 | Z53: =IFERROR((X53+Y53)/AR53,"") -> 0.83076923 | AA53: 53625 | AB53: =IFERROR(AA53/F53,"") -> 0.29742097 | AC53: =IFERROR(AA53*1000/H53,"") -> 6453.0686 | AD53: =IF(AB53="","",RANK(AB53,$AB$3:$AB$168,0)+COUNTIF($AB$3:AB53,AB53)-1) -> 137 | AE53: =IF(AA53="","",RANK(AA53,$AA$3:$AA$168,0)+COUNTIF($AA$3:AA53,AA53)-1) -> 80 | AF53: 81.42 | AG53: 82118223 | AH53: =IFERROR(AG53/AZ53,"") -> 11113.577 | AI53: 2108 | AJ53: =IFERROR(AI53/F53,"") -> 0.011691625 | AK53: 127 | AL53: 131 | AM53: 133 | AN53: 817 | AO53: 713 | AP53: 2 | AQ53: =IFERROR(AL53*1000/AZ53,"") -> 17.729057 | AR53: 325 | AS53: 149 | AT53: 109 | AU53: 4 | AV53: 63 | AW53: =IFERROR(AS53/AR53,"") -> 0.45846154 | AX53: 3 | AY53: 9 | AZ53: 7389 | BA53: 262.88 | BB53: 28.11 | BC53: 0.592 | BD53: 51.5 | BE53: 99.52 | BF53: 4.7 | BG53: 4.1 | BH53: 52.04 | BI53: 817 | BJ53: 2 | BK53: =IFERROR(BI53/AZ53,"") -> 0.11056977 | BL53: =IFERROR(AI53+K53+S53+AA53-F53,"") -> 0 | BM53: =IFERROR(F53+G53-C53,"") -> 0 | BN53: =IF(I53="","",IFERROR(C53*1000/H53-I53,"")) -> 0.015703971
A54: 2408953 | B54: Rio do Fogo | C54: 185590 | D54: 211825 | E54: 207249 | F54: 176112 | G54: 9478 | H54: 10961 | I54: 16931.82 | J54: 20022.14 | K54: 31176 | L54: =IFERROR(K54/F54,"") -> 0.17702371 | M54: =IFERROR(K54*1000/H54,"") -> 2844.266 | N54: =IF(L54="","",RANK(L54,$L$3:$L$168,0)+COUNTIF($L$3:L54,L54)-1) -> 39 | O54: =IF(K54="","",RANK(K54,$K$3:$K$168,0)+COUNTIF($K$3:K54,K54)-1) -> 46 | P54: 54 | Q54: =IFERROR(P54/AR54,"") -> 0.098540146 | R54: 8 | S54: 35592 | T54: =IFERROR(S54/F54,"") -> 0.20209866 | U54: =IFERROR(S54*1000/H54,"") -> 3247.149 | V54: =IF(T54="","",RANK(T54,$T$3:$T$168,0)+COUNTIF($T$3:T54,T54)-1) -> 140 | W54: =IF(S54="","",RANK(S54,$S$3:$S$168,0)+COUNTIF($S$3:S54,S54)-1) -> 66 | X54: 187 | Y54: 262 | Z54: =IFERROR((X54+Y54)/AR54,"") -> 0.81934307 | AA54: 76527 | AB54: =IFERROR(AA54/F54,"") -> 0.43453598 | AC54: =IFERROR(AA54*1000/H54,"") -> 6981.7535 | AD54: =IF(AB54="","",RANK(AB54,$AB$3:$AB$168,0)+COUNTIF($AB$3:AB54,AB54)-1) -> 111 | AE54: =IF(AA54="","",RANK(AA54,$AA$3:$AA$168,0)+COUNTIF($AA$3:AA54,AA54)-1) -> 49 | AF54: 89.28 | AG54: 86654246 | AH54: =IFERROR(AG54/AZ54,"") -> 8371.582 | AI54: 32817 | AJ54: =IFERROR(AI54/F54,"") -> 0.18634165 | AK54: 204 | AL54: 209 | AM54: 210 | AN54: 817 | AO54: 619 | AP54: 1.3 | AQ54: =IFERROR(AL54*1000/AZ54,"") -> 20.191286 | AR54: 548 | AS54: 259 | AT54: 188 | AU54: 7 | AV54: 94 | AW54: =IFERROR(AS54/AR54,"") -> 0.47262774 | AX54: 40 | AY54: 5 | AZ54: 10351 | BA54: 151.097 | BB54: 68.51 | BC54: 0.569 | BD54: 51.8 | BE54: 99.18 | BF54: 4.5 | BG54: 4.3 | BH54: 1.99 | BI54: 817 | BJ54: 1.9 | BK54: =IFERROR(BI54/AZ54,"") -> 0.078929572 | BL54: =IFERROR(AI54+K54+S54+AA54-F54,"") -> 0 | BM54: =IFERROR(F54+G54-C54,"") -> 0 | BN54: =IF(I54="","",IFERROR(C54*1000/H54-I54,"")) -> 0.029283824
A55: 2400802 | B55: Angicos | C55: 180163 | D55: 214393 | E55: 257919 | F55: 163136 | G55: 17027 | H55: 11695 | I55: 15405.14 | J55: 22173.27 | K55: 6847 | L55: =IFERROR(K55/F55,"") -> 0.041971116 | M55: =IFERROR(K55*1000/H55,"") -> 585.46387 | N55: =IF(L55="","",RANK(L55,$L$3:$L$168,0)+COUNTIF($L$3:L55,L55)-1) -> 113 | O55: =IF(K55="","",RANK(K55,$K$3:$K$168,0)+COUNTIF($K$3:K55,K55)-1) -> 79 | P55: 120 | Q55: =IFERROR(P55/AR55,"") -> 0.13172338 | R55: 13 | S55: 78364 | T55: =IFERROR(S55/F55,"") -> 0.48035995 | U55: =IFERROR(S55*1000/H55,"") -> 6700.6413 | V55: =IF(T55="","",RANK(T55,$T$3:$T$168,0)+COUNTIF($T$3:T55,T55)-1) -> 11 | W55: =IF(S55="","",RANK(S55,$S$3:$S$168,0)+COUNTIF($S$3:S55,S55)-1) -> 37 | X55: 347 | Y55: 426 | Z55: =IFERROR((X55+Y55)/AR55,"") -> 0.84851811 | AA55: 71611 | AB55: =IFERROR(AA55/F55,"") -> 0.43896504 | AC55: =IFERROR(AA55*1000/H55,"") -> 6123.215 | AD55: =IF(AB55="","",RANK(AB55,$AB$3:$AB$168,0)+COUNTIF($AB$3:AB55,AB55)-1) -> 109 | AE55: =IF(AA55="","",RANK(AA55,$AA$3:$AA$168,0)+COUNTIF($AA$3:AA55,AA55)-1) -> 58 | AF55: 92.34 | AG55: 64460124 | AH55: =IFERROR(AG55/AZ55,"") -> 5541.62 | AI55: 6314 | AJ55: =IFERROR(AI55/F55,"") -> 0.038703903 | AK55: 397 | AL55: 457 | AM55: 470 | AN55: 1394 | AO55: 926 | AP55: 1.6 | AQ55: =IFERROR(AL55*1000/AZ55,"") -> 39.288171 | AR55: 911 | AS55: 388 | AT55: 363 | AU55: 37 | AV55: 123 | AW55: =IFERROR(AS55/AR55,"") -> 0.4259056 | AX55: 10 | AY55: 8 | AZ55: 11632 | BA55: 741.582 | BB55: 15.69 | BC55: 0.624 | BD55: 49.2 | BE55: 98.65 | BF55: 4.9 | BG55: 4.8 | BH55: 13.33 | BI55: 1394 | BJ55: 1.6 | BK55: =IFERROR(BI55/AZ55,"") -> 0.11984182 | BL55: =IFERROR(AI55+K55+S55+AA55-F55,"") -> 0 | BM55: =IFERROR(F55+G55-C55,"") -> 0 | BN55: =IF(I55="","",IFERROR(C55*1000/H55-I55,"")) -> -0.0096023942
... A94: 2401305 | B94: Campo Grande | C94: 105354 | D94: 119802 | E94: 136391 | F94: 99870 | G94: 5484 | H94: 9686 | I94: 10876.94 | J94: 14017.6 | K94: 3784 | L94: =IFERROR(K94/F94,"") -> 0.037889256 | M94: =IFERROR(K94*1000/H94,"") -> 390.66694 | N94: =IF(L94="","",RANK(L94,$L$3:$L$168,0)+COUNTIF($L$3:L94,L94)-1) -> 134 | O94: =IF(K94="","",RANK(K94,$K$3:$K$168,0)+COUNTIF($K$3:K94,K94)-1) -> 106 | P94: 49 | Q94: =IFERROR(P94/AR94,"") -> 0.1147541 | R94: 16 | S94: 30123 | T94: =IFERROR(S94/F94,"") -> 0.30162211 | U94: =IFERROR(S94*1000/H94,"") -> 3109.9525 | V94: =IF(T94="","",RANK(T94,$T$3:$T$168,0)+COUNTIF($T$3:T94,T94)-1) -> 54 | W94: =IF(S94="","",RANK(S94,$S$3:$S$168,0)+COUNTIF($S$3:S94,S94)-1) -> 76 | X94: 143 | Y94: 217 | Z94: =IFERROR((X94+Y94)/AR94,"") -> 0.84309133 | AA94: 55108 | AB94: =IFERROR(AA94/F94,"") -> 0.55179734 | AC94: =IFERROR(AA94*1000/H94,"") -> 5689.4487 | AD94: =IF(AB94="","",RANK(AB94,$AB$3:$AB$168,0)+COUNTIF($AB$3:AB94,AB94)-1) -> 74 | AE94: =IF(AA94="","",RANK(AA94,$AA$3:$AA$168,0)+COUNTIF($AA$3:AA94,AA94)-1) -> 79 | AF94: 94.32 | AG94: 51546757 | AH94: =IFERROR(AG94/AZ94,"") -> 5297.714 | AI94: 10856 | AJ94: =IFERROR(AI94/F94,"") -> 0.10870131 | AK94: 221 | AL94: 231 | AM94: 242 | AN94: 619 | AO94: 404 | AP94: 1.9 | AQ94: =IFERROR(AL94*1000/AZ94,"") -> 23.741007 | AR94: 427 | AS94: 130 | AT94: 121 | AU94: 61 | AV94: 115 | AW94: =IFERROR(AS94/AR94,"") -> 0.30444965 | AX94: 11 | AY94: 7 | AZ94: 9730 | BA94: 890.89 | BB94: 10.92 | BC94: 0.621 | BD94: 51.7 | BE94: 98.18 | BF94: 5 | BG94: 4.5 | BH94: 3 | BI94: 614 | BJ94: 1.9 | BK94: =IFERROR(BI94/AZ94,"") -> 0.063103803 | BL94: =IFERROR(AI94+K94+S94+AA94-F94,"") -> 1 | BM94: =IFERROR(F94+G94-C94,"") -> 0 | BN94: =IF(I94="","",IFERROR(C94*1000/H94-I94,"")) -> -0.0042163948
A95: 2405108 | B95: Jandaíra | C95: 101429 | D95: 234017 | E95: 363648 | F95: 82665 | G95: 18764 | H95: 6907 | I95: 14684.92 | J95: 55417.28 | K95: 3878 | L95: =IFERROR(K95/F95,"") -> 0.046912236 | M95: =IFERROR(K95*1000/H95,"") -> 561.45939 | N95: =IF(L95="","",RANK(L95,$L$3:$L$168,0)+COUNTIF($L$3:L95,L95)-1) -> 93 | O95: =IF(K95="","",RANK(K95,$K$3:$K$168,0)+COUNTIF($K$3:K95,K95)-1) -> 103 | P95: 56 | Q95: =IFERROR(P95/AR95,"") -> 0.15598886 | R95: 27 | S95: 22218 | T95: =IFERROR(S95/F95,"") -> 0.26877155 | U95: =IFERROR(S95*1000/H95,"") -> 3216.7366 | V95: =IF(T95="","",RANK(T95,$T$3:$T$168,0)+COUNTIF($T$3:T95,T95)-1) -> 77 | W95: =IF(S95="","",RANK(S95,$S$3:$S$168,0)+COUNTIF($S$3:S95,S95)-1) -> 93 | X95: 129 | Y95: 152 | Z95: =IFERROR((X95+Y95)/AR95,"") -> 0.78272981 | AA95: 48265 | AB95: =IFERROR(AA95/F95,"") -> 0.58386258 | AC95: =IFERROR(AA95*1000/H95,"") -> 6987.8384 | AD95: =IF(AB95="","",RANK(AB95,$AB$3:$AB$168,0)+COUNTIF($AB$3:AB95,AB95)-1) -> 62 | AE95: =IF(AA95="","",RANK(AA95,$AA$3:$AA$168,0)+COUNTIF($AA$3:AA95,AA95)-1) -> 85 | AF95: 87.79 | AG95: 68276051 | AH95: =IFERROR(AG95/AZ95,"") -> 10404.762 | AI95: 8303 | AJ95: =IFERROR(AI95/F95,"") -> 0.10044154 | AK95: 146 | AL95: 154 | AM95: 155 | AN95: 1110 | AO95: 993 | AP95: 1.7 | AQ95: =IFERROR(AL95*1000/AZ95,"") -> 23.468455 | AR95: 359 | AS95: 155 | AT95: 95 | AU95: 20 | AV95: 89 | AW95: =IFERROR(AS95/AR95,"") -> 0.43175487 | AX95: 16 | AY95: 6 | AZ95: 6562 | BA95: 442.754 | BB95: 14.82 | BC95: 0.569 | BD95: 50.4 | BE95: 98.12 | BF95: 4.8 | BH95: 1.36 | BI95: 1110 | BJ95: 1.7 | BK95: =IFERROR(BI95/AZ95,"") -> 0.16915575 | BL95: =IFERROR(AI95+K95+S95+AA95-F95,"") -> -1 | BM95: =IFERROR(F95+G95-C95,"") -> 0 | BN95: =IF(I95="","",IFERROR(C95*1000/H95-I95,"")) -> 0.037289706
A96: 2404853 | B96: Itajá | C96: 99444 | D96: 145395 | E96: 179988 | F96: 90584 | G96: 8859 | H96: 7641 | I96: 13014.47 | J96: 24682.92 | K96: 10198 | L96: =IFERROR(K96/F96,"") -> 0.11258059 | M96: =IFERROR(K96*1000/H96,"") -> 1334.6421 | N96: =IF(L96="","",RANK(L96,$L$3:$L$168,0)+COUNTIF($L$3:L96,L96)-1) -> 54 | O96: =IF(K96="","",RANK(K96,$K$3:$K$168,0)+COUNTIF($K$3:K96,K96)-1) -> 67 | P96: 83 | Q96: =IFERROR(P96/AR96,"") -> 0.17043121 | R96: 13 | S96: 32214 | T96: =IFERROR(S96/F96,"") -> 0.35562572 | U96: =IFERROR(S96*1000/H96,"") -> 4215.9403 | V96: =IF(T96="","",RANK(T96,$T$3:$T$168,0)+COUNTIF($T$3:T96,T96)-1) -> 33 | W96: =IF(S96="","",RANK(S96,$S$3:$S$168,0)+COUNTIF($S$3:S96,S96)-1) -> 71 | X96: 173 | Y96: 225 | Z96: =IFERROR((X96+Y96)/AR96,"") -> 0.81724846 | AA96: 44885 | AB96: =IFERROR(AA96/F96,"") -> 0.49550693 | AC96: =IFERROR(AA96*1000/H96,"") -> 5874.2311 | AD96: =IF(AB96="","",RANK(AB96,$AB$3:$AB$168,0)+COUNTIF($AB$3:AB96,AB96)-1) -> 90 | AE96: =IF(AA96="","",RANK(AA96,$AA$3:$AA$168,0)+COUNTIF($AA$3:AA96,AA96)-1) -> 93 | AF96: 94.4 | AG96: 59622706 | AH96: =IFERROR(AG96/AZ96,"") -> 8176.4544 | AI96: 3287 | AJ96: =IFERROR(AI96/F96,"") -> 0.036286761 | AK96: 200 | AL96: 233 | AM96: 237 | AN96: 1487 | AO96: 1244 | AP96: 1.4 | AQ96: =IFERROR(AL96*1000/AZ96,"") -> 31.952825 | AR96: 487 | AS96: 204 | AT96: 190 | AU96: 24 | AV96: 69 | AW96: =IFERROR(AS96/AR96,"") -> 0.41889117 | AX96: 0 | AY96: 6 | AZ96: 7292 | BA96: 203.624 | BB96: 35.81 | BC96: 0.624 | BD96: 44.1 | BE96: 99.01 | BF96: 5.3 | BG96: 3.9 | BH96: 4.24 | BI96: 1487 | BJ96: 1.4 | BK96: =IFERROR(BI96/AZ96,"") -> 0.20392211 | BL96: =IFERROR(AI96+K96+S96+AA96-F96,"") -> 0 | BM96: =IFERROR(F96+G96-C96,"") -> -1 | BN96: =IF(I96="","",IFERROR(C96*1000/H96-I96,"")) -> 0.056894386
A97: 2403509 | B97: Espírito Santo | C97: 97584 | D97: 113844 | E97: 126682 | F97: 91985 | G97: 5599 | H97: 10463 | I97: 9326.6 | J97: 11928.61 | K97: 3117 | L97: =IFERROR(K97/F97,"") -> 0.03388596 | M97: =IFERROR(K97*1000/H97,"") -> 297.90691 | N97: =IF(L97="","",RANK(L97,$L$3:$L$168,0)+COUNTIF($L$3:L97,L97)-1) -> 142 | O97: =IF(K97="","",RANK(K97,$K$3:$K$168,0)+COUNTIF($K$3:K97,K97)-1) -> 114 | P97: 34 | Q97: =IFERROR(P97/AR97,"") -> 0.062385321 | R97: 4 | S97: 22482 | T97: =IFERROR(S97/F97,"") -> 0.24440941 | U97: =IFERROR(S97*1000/H97,"") -> 2148.7145 | V97: =IF(T97="","",RANK(T97,$T$3:$T$168,0)+COUNTIF($T$3:T97,T97)-1) -> 98 | W97: =IF(S97="","",RANK(S97,$S$3:$S$168,0)+COUNTIF($S$3:S97,S97)-1) -> 92 | X97: 114 | Y97: 386 | Z97: =IFERROR((X97+Y97)/AR97,"") -> 0.91743119 | AA97: 61582 | AB97: =IFERROR(AA97/F97,"") -> 0.66947872 | AC97: =IFERROR(AA97*1000/H97,"") -> 5885.6924 | AD97: =IF(AB97="","",RANK(AB97,$AB$3:$AB$168,0)+COUNTIF($AB$3:AB97,AB97)-1) -> 22 | AE97: =IF(AA97="","",RANK(AA97,$AA$3:$AA$168,0)+COUNTIF($AA$3:AA97,AA97)-1) -> 72 | AF97: 90.5 | AG97: 64955524 | AH97: =IFERROR(AG97/AZ97,"") -> 6116.3393 | AI97: 4803 | AJ97: =IFERROR(AI97/F97,"") -> 0.052215035 | AK97: 193 | AL97: 275 | AM97: 281 | AN97: 2038 | AO97: 1794 | AP97: 1.3 | AQ97: =IFERROR(AL97*1000/AZ97,"") -> 25.894539 | AR97: 545 | AS97: 176 | AT97: 79 | AU97: 6 | AV97: 284 | AW97: =IFERROR(AS97/AR97,"") -> 0.32293578 | AX97: 5 | AY97: 6 | AZ97: 10620 | BA97: 135.837 | BB97: 78.18 | BC97: 0.558 | BD97: 52.4 | BE97: 98.23 | BF97: 4.3 | BG97: 4.1 | BH97: 15.69 | BI97: 2036 | BJ97: 1.3 | BK97: =IFERROR(BI97/AZ97,"") -> 0.19171375 | BL97: =IFERROR(AI97+K97+S97+AA97-F97,"") -> -1 | BM97: =IFERROR(F97+G97-C97,"") -> 0 | BN97: =IF(I97="","",IFERROR(C97*1000/H97-I97,"")) -> -0.02062506
A98: 2406601 | B98: Lagoa Salgada | C98: 94311 | D98: 113114 | E98: 124483 | F98: 89408 | G98: 4902 | H98: 8348 | I98: 11297.4 | J98: 14963.74 | K98: 3545 | L98: =IFERROR(K98/F98,"") -> 0.039649696 | M98: =IFERROR(K98*1000/H98,"") -> 424.65261 | N98: =IF(L98="","",RANK(L98,$L$3:$L$168,0)+COUNTIF($L$3:L98,L98)-1) -> 125 | O98: =IF(K98="","",RANK(K98,$K$3:$K$168,0)+COUNTIF($K$3:K98,K98)-1) -> 110 | P98: 72 | Q98: =IFERROR(P98/AR98,"") -> 0.140625 | R98: 4 | S98: 26199 | T98: =IFERROR(S98/F98,"") -> 0.29302747 | U98: =IFERROR(S98*1000/H98,"") -> 3138.3565 | V98: =IF(T98="","",RANK(T98,$T$3:$T$168,0)+COUNTIF($T$3:T98,T98)-1) -> 58 | W98: =IF(S98="","",RANK(S98,$S$3:$S$168,0)+COUNTIF($S$3:S98,S98)-1) -> 83 | X98: 238 | Y98: 191 | Z98: =IFERROR((X98+Y98)/AR98,"") -> 0.83789062 | AA98: 55367 | AB98: =IFERROR(AA98/F98,"") -> 0.61926226 | AC98: =IFERROR(AA98*1000/H98,"") -> 6632.367 | AD98: =IF(AB98="","",RANK(AB98,$AB$3:$AB$168,0)+COUNTIF($AB$3:AB98,AB98)-1) -> 44 | AE98: =IF(AA98="","",RANK(AA98,$AA$3:$AA$168,0)+COUNTIF($AA$3:AA98,AA98)-1) -> 78 | AF98: 93.8 | AG98: 49841699 | AH98: =IFERROR(AG98/AZ98,"") -> 5991.3089 | AI98: 4297 | AJ98: =IFERROR(AI98/F98,"") -> 0.048060576 | AK98: 144 | AL98: 162 | AM98: 166 | AN98: 896 | AO98: 768 | AP98: 1.4 | AQ98: =IFERROR(AL98*1000/AZ98,"") -> 19.473494 | AR98: 512 | AS98: 278 | AT98: 167 | AU98: 12 | AV98: 55 | AW98: =IFERROR(AS98/AR98,"") -> 0.54296875 | AX98: 5 | AY98: 6 | AZ98: 8319 | BA98: 79.128 | BB98: 105.13 | BC98: 0.582 | BD98: 52.2 | BE98: 100 | BF98: 4.8 | BG98: 4.1 | BH98: 0.48 | BI98: 896 | BJ98: 1.4 | BK98: =IFERROR(BI98/AZ98,"") -> 0.10770525 | BL98: =IFERROR(AI98+K98+S98+AA98-F98,"") -> 0 | BM98: =IFERROR(F98+G98-C98,"") -> -1 | BN98: =IF(I98="","",IFERROR(C98*1000/H98-I98,"")) -> 0.036511739
A99: 2412807 | B99: São Rafael | C99: 88674 | D99: 97419 | E99: 108235 | F99: 84508 | G99: 4166 | H99: 8183 | I99: 10836.41 | J99: 14036.42 | K99: 3755 | L99: =IFERROR(K99/F99,"") -> 0.044433663 | M99: =IFERROR(K99*1000/H99,"") -> 458.87816 | N99: =IF(L99="","",RANK(L99,$L$3:$L$168,0)+COUNTIF($L$3:L99,L99)-1) -> 103 | O99: =IF(K99="","",RANK(K99,$K$3:$K$168,0)+COUNTIF($K$3:K99,K99)-1) -> 107 | P99: 50 | Q99: =IFERROR(P99/AR99,"") -> 0.13477089 | R99: 5 | S99: 20342 | T99: =IFERROR(S99/F99,"") -> 0.24071094 | U99: =IFERROR(S99*1000/H99,"") -> 2485.8854 | V99: =IF(T99="","",RANK(T99,$T$3:$T$168,0)+COUNTIF($T$3:T99,T99)-1) -> 102 | W99: =IF(S99="","",RANK(S99,$S$3:$S$168,0)+COUNTIF($S$3:S99,S99)-1) -> 98 | X99: 152 | Y99: 159 | Z99: =IFERROR((X99+Y99)/AR99,"") -> 0.83827493 | AA99: 47204 | AB99: =IFERROR(AA99/F99,"") -> 0.55857434 | AC99: =IFERROR(AA99*1000/H99,"") -> 5768.5445 | AD99: =IF(AB99="","",RANK(AB99,$AB$3:$AB$168,0)+COUNTIF($AB$3:AB99,AB99)-1) -> 70 | AE99: =IF(AA99="","",RANK(AA99,$AA$3:$AA$168,0)+COUNTIF($AA$3:AA99,AA99)-1) -> 90 | AF99: 96.17 | AG99: 41236786 | AH99: =IFERROR(AG99/AZ99,"") -> 5347.7871 | AI99: 13206 | AJ99: =IFERROR(AI99/F99,"") -> 0.15626923 | AK99: 128 | AL99: 144 | AM99: 144 | AN99: 451 | AO99: 333 | AP99: 2 | AQ99: =IFERROR(AL99*1000/AZ99,"") -> 18.674621 | AR99: 371 | AS99: 194 | AT99: 107 | AU99: 5 | AV99: 65 | AW99: =IFERROR(AS99/AR99,"") -> 0.52291105 | AX99: 2 | AY99: 8 | AZ99: 7711 | BA99: 469.101 | BB99: 16.44 | BC99: 0.611 | BD99: 52.8 | BE99: 99.52 | BF99: 5.3 | BG99: 4.5 | BH99: 58.16 | BI99: 446 | BJ99: 2 | BK99: =IFERROR(BI99/AZ99,"") -> 0.05783945 | BL99: =IFERROR(AI99+K99+S99+AA99-F99,"") -> -1 | BM99: =IFERROR(F99+G99-C99,"") -> 0 | BN99: =IF(I99="","",IFERROR(C99*1000/H99-I99,"")) -> -0.041919834
A100: 2401602 | B100: Bento Fernandes | C100: 88429 | D100: 120353 | E100: 128584 | F100: 85815 | G100: 2614 | H100: 5552 | I100: 15927.4 | J100: 26749.41 | K100: 31441 | L100: =IFERROR(K100/F100,"") -> 0.36638117 | M100: =IFERROR(K100*1000/H100,"") -> 5663.0043 | N100: =IF(L100="","",RANK(L100,$L$3:$L$168,0)+COUNTIF($L$3:L100,L100)-1) -> 21 | O100: =IF(K100="","",RANK(K100,$K$3:$K$168,0)+COUNTIF($K$3:K100,K100)-1) -> 44 | P100: 24 | Q100: =IFERROR(P100/AR100,"") -> 0.12244898 | R100: 4 | S100: 10398 | T100: =IFERROR(S100/F100,"") -> 0.12116763 | U100: =IFERROR(S100*1000/H100,"") -> 1872.8386 | V100: =IF(T100="","",RANK(T100,$T$3:$T$168,0)+COUNTIF($T$3:T100,T100)-1) -> 158 | W100: =IF(S100="","",RANK(S100,$S$3:$S$168,0)+COUNTIF($S$3:S100,S100)-1) -> 141 | X100: 60 | Y100: 103 | Z100: =IFERROR((X100+Y100)/AR100,"") -> 0.83163265 | AA100: 38549 | AB100: =IFERROR(AA100/F100,"") -> 0.44921051 | AC100: =IFERROR(AA100*1000/H100,"") -> 6943.2637 | AD100: =IF(AB100="","",RANK(AB100,$AB$3:$AB$168,0)+COUNTIF($AB$3:AB100,AB100)-1) -> 106 | AE100: =IF(AA100="","",RANK(AA100,$AA$3:$AA$168,0)+COUNTIF($AA$3:AA100,AA100)-1) -> 105 | AF100: 92.97 | AG100: 44260574 | AH100: =IFERROR(AG100/AZ100,"") -> 9207.5252 | AI100: 5428 | AJ100: =IFERROR(AI100/F100,"") -> 0.063252345 | AK100: 75 | AL100: 97 | AM100: 99 | AN100: 544 | AO100: 472 | AP100: 1.8 | AQ100: =IFERROR(AL100*1000/AZ100,"") -> 20.178906 | AR100: 196 | AS100: 71 | AT100: 54 | AU100: 4 | AV100: 67 | AW100: =IFERROR(AS100/AR100,"") -> 0.3622449 | AX100: 3 | AY100: 6 | AZ100: 4807 | BA100: 301.069 | BB100: 15.97 | BC100: 0.582 | BD100: 52.3 | BE100: 96.1 | BF100: 3.8 | BG100: 4.2 | BH100: 1.37 | BI100: 544 | BJ100: 1.8 | BK100: =IFERROR(BI100/AZ100,"") -> 0.1131683 | BL100: =IFERROR(AI100+K100+S100+AA100-F100,"") -> 1 | BM100: =IFERROR(F100+G100-C100,"") -> 0 | BN100: =IF(I100="","",IFERROR(C100*1000/H100-I100,"")) -> 0.013544669
A101: 2407005 | B101: Luís Gomes | C101: 87825 | D101: 97477 | E101: 112399 | F101: 84454 | G101: 3371 | H101: 10175 | I101: 8631.46 | J101: 12392.43 | K101: 2330 | L101: =IFERROR(K101/F101,"") -> 0.027588983 | M101: =IFERROR(K101*1000/H101,"") -> 228.99263 | N101: =IF(L101="","",RANK(L101,$L$3:$L$168,0)+COUNTIF($L$3:L101,L101)-1) -> 155 | O101: =IF(K101="","",RANK(K101,$K$3:$K$168,0)+COUNTIF($K$3:K101,K101)-1) -> 127 | P101: 28 | Q101: =IFERROR(P101/AR101,"") -> 0.085626911 | R101: 2 | S101: 20589 | T101: =IFERROR(S101/F101,"") -> 0.24378952 | U101: =IFERROR(S101*1000/H101,"") -> 2023.4889 | V101: =IF(T101="","",RANK(T101,$T$3:$T$168,0)+COUNTIF($T$3:T101,T101)-1) -> 99 | W101: =IF(S101="","",RANK(S101,$S$3:$S$168,0)+COUNTIF($S$3:S101,S101)-1) -> 97 | X101: 149 | Y101: 142 | Z101: =IFERROR((X101+Y101)/AR101,"") -> 0.88990826 | AA101: 59670 | AB101: =IFERROR(AA101/F101,"") -> 0.70653847 | AC101: =IFERROR(AA101*1000/H101,"") -> 5864.3735 | AD101: =IF(AB101="","",RANK(AB101,$AB$3:$AB$168,0)+COUNTIF($AB$3:AB101,AB101)-1) -> 6 | AE101: =IF(AA101="","",RANK(AA101,$AA$3:$AA$168,0)+COUNTIF($AA$3:AA101,AA101)-1) -> 73 | AF101: 92.78 | AG101: 62026618 | AH101: =IFERROR(AG101/AZ101,"") -> 6838.6569 | AI101: 1866 | AJ101: =IFERROR(AI101/F101,"") -> 0.022094868 | AK101: 152 | AL101: 145 | AM101: 148 | AN101: 608 | AO101: 476 | AP101: 1.7 | AQ101: =IFERROR(AL101*1000/AZ101,"") -> 15.98677 | AR101: 327 | AS101: 128 | AT101: 128 | AU101: 7 | AV101: 64 | AW101: =IFERROR(AS101/AR101,"") -> 0.39143731 | AX101: 0 | AY101: 8 | AZ101: 9070 | BA101: 166.638 | BB101: 54.43 | BC101: 0.608 | BD101: 53.1 | BE101: 98.97 | BF101: 5.6 | BG101: 4.8 | BH101: 9.44 | BI101: 608 | BJ101: 1.7 | BK101: =IFERROR(BI101/AZ101,"") -> 0.067034179 | BL101: =IFERROR(AI101+K101+S101+AA101-F101,"") -> 1 | BM101: =IFERROR(F101+G101-C101,"") -> 0 | BN101: =IF(I101="","",IFERROR(C101*1000/H101-I101,"")) -> -0.01036855
A102: 2405009 | B102: Jaçanã | C102: 86389 | D102: 91188 | E102: 100644 | F102: 82310 | G102: 4078 | H102: 9341 | I102: 9248.35 | J102: 12847.11 | K102: 3671 | L102: =IFERROR(K102/F102,"") -> 0.044599684 | M102: =IFERROR(K102*1000/H102,"") -> 392.99861 | N102: =IF(L102="","",RANK(L102,$L$3:$L$168,0)+COUNTIF($L$3:L102,L102)-1) -> 101 | O102: =IF(K102="","",RANK(K102,$K$3:$K$168,0)+COUNTIF($K$3:K102,K102)-1) -> 108 | P102: 41 | Q102: =IFERROR(P102/AR102,"") -> 0.097619048 | R102: 3 | S102: 19724 | T102: =IFERROR(S102/F102,"") -> 0.23963066 | U102: =IFERROR(S102*1000/H102,"") -> 2111.5512 | V102: =IF(T102="","",RANK(T102,$T$3:$T$168,0)+COUNTIF($T$3:T102,T102)-1) -> 104 | W102: =IF(S102="","",RANK(S102,$S$3:$S$168,0)+COUNTIF($S$3:S102,S102)-1) -> 101 | X102: 209 | Y102: 166 | Z102: =IFERROR((X102+Y102)/AR102,"") -> 0.89285714 | AA102: 52812 | AB102: =IFERROR(AA102/F102,"") -> 0.64162313 | AC102: =IFERROR(AA102*1000/H102,"") -> 5653.7844 | AD102: =IF(AB102="","",RANK(AB102,$AB$3:$AB$168,0)+COUNTIF($AB$3:AB102,AB102)-1) -> 35 | AE102: =IF(AA102="","",RANK(AA102,$AA$3:$AA$168,0)+COUNTIF($AA$3:AA102,AA102)-1) -> 81 | AF102: 94.44 | AG102: 53661677 | AH102: =IFERROR(AG102/AZ102,"") -> 6849.8438 | AI102: 6103 | AJ102: =IFERROR(AI102/F102,"") -> 0.074146519 | AK102: 138 | AL102: 158 | AM102: 160 | AN102: 655 | AO102: 524 | AP102: 1.7 | AQ102: =IFERROR(AL102*1000/AZ102,"") -> 20.168496 | AR102: 420 | AS102: 227 | AT102: 124 | AU102: 7 | AV102: 62 | AW102: =IFERROR(AS102/AR102,"") -> 0.54047619 | AX102: 2 | AY102: 2 | AZ102: 7834 | BA102: 54.56 | BB102: 143.58 | BC102: 0.604 | BD102: 51.9 | BE102: 98.98 | BF102: 6.2 | BG102: 4.3 | BH102: 25.06 | BI102: 655 | BJ102: 1.7 | BK102: =IFERROR(BI102/AZ102,"") -> 0.083609906 | BL102: =IFERROR(AI102+K102+S102+AA102-F102,"") -> 0 | BM102: =IFERROR(F102+G102-C102,"") -> -1 | BN102: =IF(I102="","",IFERROR(C102*1000/H102-I102,"")) -> 0.017412483
A103: 2405306 | B103: Januário Cicco | C103: 84899 | D103: 96939 | E103: 102924 | F103: 80337 | G103: 4562 | H103: 10367 | I103: 8189.32 | J103: 11980.5 | K103: 3843 | L103: =IFERROR(K103/F103,"") -> 0.047835991 | M103: =IFERROR(K103*1000/H103,"") -> 370.69548 | N103: =IF(L103="","",RANK(L103,$L$3:$L$168,0)+COUNTIF($L$3:L103,L103)-1) -> 90 | O103: =IF(K103="","",RANK(K103,$K$3:$K$168,0)+COUNTIF($K$3:K103,K103)-1) -> 104 | P103: 25 | Q103: =IFERROR(P103/AR103,"") -> 0.080385852 | R103: 2 | S103: 17635 | T103: =IFERROR(S103/F103,"") -> 0.2195128 | U103: =IFERROR(S103*1000/H103,"") -> 1701.0707 | V103: =IF(T103="","",RANK(T103,$T$3:$T$168,0)+COUNTIF($T$3:T103,T103)-1) -> 127 | W103: =IF(S103="","",RANK(S103,$S$3:$S$168,0)+COUNTIF($S$3:S103,S103)-1) -> 108 | X103: 140 | Y103: 140 | Z103: =IFERROR((X103+Y103)/AR103,"") -> 0.90032154 | AA103: 55623 | AB103: =IFERROR(AA103/F103,"") -> 0.69237089 | AC103: =IFERROR(AA103*1000/H103,"") -> 5365.3902 | AD103: =IF(AB103="","",RANK(AB103,$AB$3:$AB$168,0)+COUNTIF($AB$3:AB103,AB103)-1) -> 10 | AE103: =IF(AA103="","",RANK(AA103,$AA$3:$AA$168,0)+COUNTIF($AA$3:AA103,AA103)-1) -> 77 | AF103: 89.92 | AG103: 61998285 | AH103: =IFERROR(AG103/AZ103,"") -> 6849.8823 | AI103: 3235 | AJ103: =IFERROR(AI103/F103,"") -> 0.040267872 | AK103: 122 | AL103: 120 | AM103: 124 | AN103: 582 | AO103: 497 | AP103: 1.8 | AQ103: =IFERROR(AL103*1000/AZ103,"") -> 13.258204 | AR103: 311 | AS103: 141 | AT103: 100 | AU103: 5 | AV103: 65 | AW103: =IFERROR(AS103/AR103,"") -> 0.45337621 | AX103: 1 | AY103: 5 | AZ103: 9051 | BA103: 167.042 | BB103: 53.01 | BC103: 0.574 | BD103: 55.7 | BE103: 96.45 | BF103: 5.8 | BG103: 4.5 | BH103: 16.31 | BI103: 582 | BJ103: 1.8 | BK103: =IFERROR(BI103/AZ103,"") -> 0.064302287 | BL103: =IFERROR(AI103+K103+S103+AA103-F103,"") -> -1 | BM103: =IFERROR(F103+G103-C103,"") -> 0 | BN103: =IF(I103="","",IFERROR(C103*1000/H103-I103,"")) -> 0.030824732
A104: 2412104 | B104: São João do Sabugi | C104: 84585 | D104: 94944 | E104: 100073 | F104: 78953 | G104: 5633 | H104: 6221 | I104: 13596.72 | J104: 16802.01 | K104: 3161 | L104: =IFERROR(K104/F104,"") -> 0.040036477 | M104: =IFERROR(K104*1000/H104,"") -> 508.11767 | N104: =IF(L104="","",RANK(L104,$L$3:$L$168,0)+COUNTIF($L$3:L104,L104)-1) -> 123 | O104: =IF(K104="","",RANK(K104,$K$3:$K$168,0)+COUNTIF($K$3:K104,K104)-1) -> 113 | P104: 60 | Q104: =IFERROR(P104/AR104,"") -> 0.15424165 | R104: 3 | S104: 19201 | T104: =IFERROR(S104/F104,"") -> 0.24319532 | U104: =IFERROR(S104*1000/H104,"") -> 3086.4813 | V104: =IF(T104="","",RANK(T104,$T$3:$T$168,0)+COUNTIF($T$3:T104,T104)-1) -> 100 | W104: =IF(S104="","",RANK(S104,$S$3:$S$168,0)+COUNTIF($S$3:S104,S104)-1) -> 105 | X104: 134 | Y104: 181 | Z104: =IFERROR((X104+Y104)/AR104,"") -> 0.80976864 | AA104: 36943 | AB104: =IFERROR(AA104/F104,"") -> 0.46791129 | AC104: =IFERROR(AA104*1000/H104,"") -> 5938.4343 | AD104: =IF(AB104="","",RANK(AB104,$AB$3:$AB$168,0)+COUNTIF($AB$3:AB104,AB104)-1) -> 98 | AE104: =IF(AA104="","",RANK(AA104,$AA$3:$AA$168,0)+COUNTIF($AA$3:AA104,AA104)-1) -> 108 | AF104: 91.63 | AG104: 43710923 | AH104: =IFERROR(AG104/AZ104,"") -> 7338.973 | AI104: 19648 | AJ104: =IFERROR(AI104/F104,"") -> 0.24885691 | AK104: 143 | AL104: 148 | AM104: 163 | AN104: 517 | AO104: 386 | AP104: 2 | AQ104: =IFERROR(AL104*1000/AZ104,"") -> 24.848892 | AR104: 389 | AS104: 193 | AT104: 108 | AU104: 17 | AV104: 71 | AW104: =IFERROR(AS104/AR104,"") -> 0.49614396 | AX104: 2 | AY104: 12 | AZ104: 5956 | BA104: 277.011 | BB104: 21.5 | BC104: 0.655 | BD104: 45 | BE104: 99.7 | BF104: 6.5 | BG104: 5.5 | BH104: 45.92 | BI104: 517 | BJ104: 1.9 | BK104: =IFERROR(BI104/AZ104,"") -> 0.086803224 | BL104: =IFERROR(AI104+K104+S104+AA104-F104,"") -> 0 | BM104: =IFERROR(F104+G104-C104,"") -> 1 | BN104: =IF(I104="","",IFERROR(C104*1000/H104-I104,"")) -> -0.031364732
A105: 2405207 | B105: Janduís | C105: 84497 | D105: 84488 | E105: 104812 | F105: 81235 | G105: 3262 | H105: 5228 | I105: 16162.43 | J105: 22084.25 | K105: 24352 | L105: =IFERROR(K105/F105,"") -> 0.29977227 | M105: =IFERROR(K105*1000/H105,"") -> 4657.9954 | N105: =IF(L105="","",RANK(L105,$L$3:$L$168,0)+COUNTIF($L$3:L105,L105)-1) -> 28 | O105: =IF(K105="","",RANK(K105,$K$3:$K$168,0)+COUNTIF($K$3:K105,K105)-1) -> 51 | P105: 40 | Q105: =IFERROR(P105/AR105,"") -> 0.15564202 | R105: 9 | S105: 16287 | T105: =IFERROR(S105/F105,"") -> 0.2004924 | U105: =IFERROR(S105*1000/H105,"") -> 3115.3405 | V105: =IF(T105="","",RANK(T105,$T$3:$T$168,0)+COUNTIF($T$3:T105,T105)-1) -> 143 | W105: =IF(S105="","",RANK(S105,$S$3:$S$168,0)+COUNTIF($S$3:S105,S105)-1) -> 114 | X105: 91 | Y105: 116 | Z105: =IFERROR((X105+Y105)/AR105,"") -> 0.80544747 | AA105: 36183 | AB105: =IFERROR(AA105/F105,"") -> 0.44541146 | AC105: =IFERROR(AA105*1000/H105,"") -> 6921.0023 | AD105: =IF(AB105="","",RANK(AB105,$AB$3:$AB$168,0)+COUNTIF($AB$3:AB105,AB105)-1) -> 107 | AE105: =IF(AA105="","",RANK(AA105,$AA$3:$AA$168,0)+COUNTIF($AA$3:AA105,AA105)-1) -> 111 | AF105: 96.54 | AG105: 47655076 | AH105: =IFERROR(AG105/AZ105,"") -> 10041.103 | AI105: 4414 | AJ105: =IFERROR(AI105/F105,"") -> 0.054336185 | AK105: 124 | AL105: 145 | AM105: 147 | AN105: 456 | AO105: 352 | AP105: 2.1 | AQ105: =IFERROR(AL105*1000/AZ105,"") -> 30.552044 | AR105: 257 | AS105: 76 | AT105: 87 | AU105: 10 | AV105: 84 | AW105: =IFERROR(AS105/AR105,"") -> 0.29571984 | AX105: 0 | AY105: 10 | AZ105: 4746 | BA105: 303.448 | BB105: 15.64 | BC105: 0.615 | BD105: 48.3 | BE105: 100 | BF105: 6.3 | BG105: 4.4 | BH105: 29.07 | BI105: 456 | BJ105: 2.1 | BK105: =IFERROR(BI105/AZ105,"") -> 0.09608091 | BL105: =IFERROR(AI105+K105+S105+AA105-F105,"") -> 1 | BM105: =IFERROR(F105+G105-C105,"") -> 0 | BN105: =IF(I105="","",IFERROR(C105*1000/H105-I105,"")) -> -0.035202754
A106: 2412401 | B106: São José do Seridó | C106: 83854 | D106: 95606 | E106: 106548 | F106: 76654 | G106: 7199 | H106: 4696 | I106: 17856.45 | J106: 23376.1 | K106: 10076 | L106: =IFERROR(K106/F106,"") -> 0.1314478 | M106: =IFERROR(K106*1000/H106,"") -> 2145.6559 | N106: =IF(L106="","",RANK(L106,$L$3:$L$168,0)+COUNTIF($L$3:L106,L106)-1) -> 50 | O106: =IF(K106="","",RANK(K106,$K$3:$K$168,0)+COUNTIF($K$3:K106,K106)-1) -> 68 | P106: 85 | Q106: =IFERROR(P106/AR106,"") -> 0.22911051 | R106: 11 | S106: 22957 | T106: =IFERROR(S106/F106,"") -> 0.29948861 | U106: =IFERROR(S106*1000/H106,"") -> 4888.6286 | V106: =IF(T106="","",RANK(T106,$T$3:$T$168,0)+COUNTIF($T$3:T106,T106)-1) -> 55 | W106: =IF(S106="","",RANK(S106,$S$3:$S$168,0)+COUNTIF($S$3:S106,S106)-1) -> 88 | X106: 118 | Y106: 157 | Z106: =IFERROR((X106+Y106)/AR106,"") -> 0.74123989 | AA106: 30956 | AB106: =IFERROR(AA106/F106,"") -> 0.40384063 | AC106: =IFERROR(AA106*1000/H106,"") -> 6591.9932 | AD106: =IF(AB106="","",RANK(AB106,$AB$3:$AB$168,0)+COUNTIF($AB$3:AB106,AB106)-1) -> 117 | AE106: =IF(AA106="","",RANK(AA106,$AA$3:$AA$168,0)+COUNTIF($AA$3:AA106,AA106)-1) -> 125 | AF106: 85.32 | AG106: 43418373 | AH106: =IFERROR(AG106/AZ106,"") -> 9525.751 | AI106: 12666 | AJ106: =IFERROR(AI106/F106,"") -> 0.165236 | AK106: 141 | AL106: 153 | AM106: 170 | AN106: 1237 | AO106: 1070 | AP106: 1.4 | AQ106: =IFERROR(AL106*1000/AZ106,"") -> 33.567354 | AR106: 371 | AS106: 178 | AT106: 122 | AU106: 14 | AV106: 57 | AW106: =IFERROR(AS106/AR106,"") -> 0.47978437 | AX106: 1 | AY106: 10 | AZ106: 4558 | BA106: 174.505 | BB106: 26.12 | BC106: 0.694 | BD106: 37.7 | BE106: 100 | BF106: 5.7 | BG106: 4.7 | BH106: 63.82 | BI106: 1237 | BJ106: 1.4 | BK106: =IFERROR(BI106/AZ106,"") -> 0.27139096 | BL106: =IFERROR(AI106+K106+S106+AA106-F106,"") -> 1 | BM106: =IFERROR(F106+G106-C106,"") -> -1 | BN106: =IF(I106="","",IFERROR(C106*1000/H106-I106,"")) -> 0.023594549
A107: 2407302 | B107: Marcelino Vieira | C107: 82889 | D107: 92508 | E107: 101177 | F107: 78943 | G107: 3945 | H107: 8325 | I107: 9956.62 | J107: 12813.75 | K107: 2720 | L107: =IFERROR(K107/F107,"") -> 0.03445524 | M107: =IFERROR(K107*1000/H107,"") -> 326.72673 | N107: =IF(L107="","",RANK(L107,$L$3:$L$168,0)+COUNTIF($L$3:L107,L107)-1) -> 139 | O107: =IF(K107="","",RANK(K107,$K$3:$K$168,0)+COUNTIF($K$3:K107,K107)-1) -> 124 | P107: 39 | Q107: =IFERROR(P107/AR107,"") -> 0.095121951 | R107: 4 | S107: 19383 | T107: =IFERROR(S107/F107,"") -> 0.24553159 | U107: =IFERROR(S107*1000/H107,"") -> 2328.2883 | V107: =IF(T107="","",RANK(T107,$T$3:$T$168,0)+COUNTIF($T$3:T107,T107)-1) -> 96 | W107: =IF(S107="","",RANK(S107,$S$3:$S$168,0)+COUNTIF($S$3:S107,S107)-1) -> 103 | X107: 170 | Y107: 192 | Z107: =IFERROR((X107+Y107)/AR107,"") -> 0.88292683 | AA107: 47215 | AB107: =IFERROR(AA107/F107,"") -> 0.59808976 | AC107: =IFERROR(AA107*1000/H107,"") -> 5671.4715 | AD107: =IF(AB107="","",RANK(AB107,$AB$3:$AB$168,0)+COUNTIF($AB$3:AB107,AB107)-1) -> 54 | AE107: =IF(AA107="","",RANK(AA107,$AA$3:$AA$168,0)+COUNTIF($AA$3:AA107,AA107)-1) -> 89 | AF107: 94.95 | AG107: 45030524 | AH107: =IFERROR(AG107/AZ107,"") -> 5702.954 | AI107: 9625 | AJ107: =IFERROR(AI107/F107,"") -> 0.12192341 | AK107: 124 | AL107: 134 | AM107: 137 | AN107: 559 | AO107: 440 | AP107: 1.8 | AQ107: =IFERROR(AL107*1000/AZ107,"") -> 16.970618 | AR107: 410 | AS107: 219 | AT107: 124 | AU107: 5 | AV107: 62 | AW107: =IFERROR(AS107/AR107,"") -> 0.53414634 | AX107: 3 | AY107: 6 | AZ107: 7896 | BA107: 345.711 | BB107: 22.84 | BC107: 0.609 | BD107: 52.2 | BE107: 100 | BF107: 5.3 | BG107: 4.7 | BH107: 29.96 | BI107: 559 | BJ107: 1.8 | BK107: =IFERROR(BI107/AZ107,"") -> 0.070795339 | BL107: =IFERROR(AI107+K107+S107+AA107-F107,"") -> 0 | BM107: =IFERROR(F107+G107-C107,"") -> -1 | BN107: =IF(I107="","",IFERROR(C107*1000/H107-I107,"")) -> 0.016636637
... A131: 2407609 | B131: Messias Targino | C131: 55529 | D131: 59493 | E131: 65325 | F131: 51547 | G131: 3983 | H131: 4665 | I131: 11903.37 | J131: 15284.31 | K131: 2024 | L131: =IFERROR(K131/F131,"") -> 0.039265137 | M131: =IFERROR(K131*1000/H131,"") -> 433.86924 | N131: =IF(L131="","",RANK(L131,$L$3:$L$168,0)+COUNTIF($L$3:L131,L131)-1) -> 127 | O131: =IF(K131="","",RANK(K131,$K$3:$K$168,0)+COUNTIF($K$3:K131,K131)-1) -> 137 | P131: 18 | Q131: =IFERROR(P131/AR131,"") -> 0.076271186 | R131: 5 | S131: 16792 | T131: =IFERROR(S131/F131,"") -> 0.32576096 | U131: =IFERROR(S131*1000/H131,"") -> 3599.5713 | V131: =IF(T131="","",RANK(T131,$T$3:$T$168,0)+COUNTIF($T$3:T131,T131)-1) -> 44 | W131: =IF(S131="","",RANK(S131,$S$3:$S$168,0)+COUNTIF($S$3:S131,S131)-1) -> 112 | X131: 101 | Y131: 103 | Z131: =IFERROR((X131+Y131)/AR131,"") -> 0.86440678 | AA131: 29496 | AB131: =IFERROR(AA131/F131,"") -> 0.57221565 | AC131: =IFERROR(AA131*1000/H131,"") -> 6322.8296 | AD131: =IF(AB131="","",RANK(AB131,$AB$3:$AB$168,0)+COUNTIF($AB$3:AB131,AB131)-1) -> 67 | AE131: =IF(AA131="","",RANK(AA131,$AA$3:$AA$168,0)+COUNTIF($AA$3:AA131,AA131)-1) -> 133 | AF131: 90.01 | AG131: 38270066 | AH131: =IFERROR(AG131/AZ131,"") -> 8954.1567 | AI131: 3235 | AJ131: =IFERROR(AI131/F131,"") -> 0.062758259 | AK131: 104 | AL131: 125 | AM131: 127 | AN131: 606 | AO131: 504 | AP131: 1.3 | AQ131: =IFERROR(AL131*1000/AZ131,"") -> 29.246607 | AR131: 236 | AS131: 98 | AT131: 73 | AU131: 8 | AV131: 57 | AW131: =IFERROR(AS131/AR131,"") -> 0.41525424 | AX131: 4 | AY131: 10 | AZ131: 4274 | BA131: 142.607 | BB131: 29.97 | BC131: 0.644 | BD131: 43.6 | BE131: 98.83 | BF131: 4.7 | BG131: 4.1 | BH131: 27.72 | BI131: 604 | BJ131: 1.4 | BK131: =IFERROR(BI131/AZ131,"") -> 0.14131961 | BL131: =IFERROR(AI131+K131+S131+AA131-F131,"") -> 0 | BM131: =IFERROR(F131+G131-C131,"") -> 1 | BN131: =IF(I131="","",IFERROR(C131*1000/H131-I131,"")) -> -0.04738478
A132: 2408706 | B132: Paraú | C132: 55256 | D132: 59380 | E132: 62150 | F132: 52273 | G132: 2983 | H132: 3732 | I132: 14806.11 | J132: 17365.08 | K132: 2012 | L132: =IFERROR(K132/F132,"") -> 0.038490234 | M132: =IFERROR(K132*1000/H132,"") -> 539.12111 | N132: =IF(L132="","",RANK(L132,$L$3:$L$168,0)+COUNTIF($L$3:L132,L132)-1) -> 130 | O132: =IF(K132="","",RANK(K132,$K$3:$K$168,0)+COUNTIF($K$3:K132,K132)-1) -> 138 | P132: 23 | Q132: =IFERROR(P132/AR132,"") -> 0.14197531 | R132: 3 | S132: 12992 | T132: =IFERROR(S132/F132,"") -> 0.24854131 | U132: =IFERROR(S132*1000/H132,"") -> 3481.2433 | V132: =IF(T132="","",RANK(T132,$T$3:$T$168,0)+COUNTIF($T$3:T132,T132)-1) -> 93 | W132: =IF(S132="","",RANK(S132,$S$3:$S$168,0)+COUNTIF($S$3:S132,S132)-1) -> 129 | X132: 53 | Y132: 79 | Z132: =IFERROR((X132+Y132)/AR132,"") -> 0.81481481 | AA132: 27172 | AB132: =IFERROR(AA132/F132,"") -> 0.51980946 | AC132: =IFERROR(AA132*1000/H132,"") -> 7280.8146 | AD132: =IF(AB132="","",RANK(AB132,$AB$3:$AB$168,0)+COUNTIF($AB$3:AB132,AB132)-1) -> 82 | AE132: =IF(AA132="","",RANK(AA132,$AA$3:$AA$168,0)+COUNTIF($AA$3:AA132,AA132)-1) -> 141 | AF132: 94.5 | AG132: 33680847 | AH132: =IFERROR(AG132/AZ132,"") -> 9410.6865 | AI132: 10097 | AJ132: =IFERROR(AI132/F132,"") -> 0.19315899 | AK132: 64 | AL132: 81 | AM132: 82 | AN132: 288 | AO132: 236 | AP132: 2.2 | AQ132: =IFERROR(AL132*1000/AZ132,"") -> 22.63202 | AR132: 162 | AS132: 63 | AT132: 47 | AU132: 7 | AV132: 45 | AW132: =IFERROR(AS132/AR132,"") -> 0.38888889 | AX132: 0 | AY132: 7 | AZ132: 3579 | BA132: 383.214 | BB132: 9.34 | BC132: 0.603 | BD132: 46.4 | BE132: 99 | BG132: 3.6 | BH132: 30.72 | BI132: 288 | BJ132: 2.2 | BK132: =IFERROR(BI132/AZ132,"") -> 0.080469405 | BL132: =IFERROR(AI132+K132+S132+AA132-F132,"") -> 0 | BM132: =IFERROR(F132+G132-C132,"") -> 0 | BN132: =IF(I132="","",IFERROR(C132*1000/H132-I132,"")) -> -0.10785638
A133: 2411908 | B133: São Francisco do Oeste | C133: 54447 | D133: 65016 | E133: 74357 | F133: 51660 | G133: 2787 | H133: 4281 | I133: 12718.24 | J133: 17869.95 | K133: 3572 | L133: =IFERROR(K133/F133,"") -> 0.069144406 | M133: =IFERROR(K133*1000/H133,"") -> 834.38449 | N133: =IF(L133="","",RANK(L133,$L$3:$L$168,0)+COUNTIF($L$3:L133,L133)-1) -> 71 | O133: =IF(K133="","",RANK(K133,$K$3:$K$168,0)+COUNTIF($K$3:K133,K133)-1) -> 109 | P133: 42 | Q133: =IFERROR(P133/AR133,"") -> 0.17427386 | R133: 7 | S133: 14869 | T133: =IFERROR(S133/F133,"") -> 0.28782424 | U133: =IFERROR(S133*1000/H133,"") -> 3473.2539 | V133: =IF(T133="","",RANK(T133,$T$3:$T$168,0)+COUNTIF($T$3:T133,T133)-1) -> 63 | W133: =IF(S133="","",RANK(S133,$S$3:$S$168,0)+COUNTIF($S$3:S133,S133)-1) -> 122 | X133: 101 | Y133: 90 | Z133: =IFERROR((X133+Y133)/AR133,"") -> 0.79253112 | AA133: 30777 | AB133: =IFERROR(AA133/F133,"") -> 0.59576074 | AC133: =IFERROR(AA133*1000/H133,"") -> 7189.2081 | AD133: =IF(AB133="","",RANK(AB133,$AB$3:$AB$168,0)+COUNTIF($AB$3:AB133,AB133)-1) -> 56 | AE133: =IF(AA133="","",RANK(AA133,$AA$3:$AA$168,0)+COUNTIF($AA$3:AA133,AA133)-1) -> 126 | AF133: 94.03 | AG133: 41706057 | AH133: =IFERROR(AG133/AZ133,"") -> 10023.085 | AI133: 2443 | AJ133: =IFERROR(AI133/F133,"") -> 0.047289973 | AK133: 84 | AL133: 95 | AM133: 97 | AN133: 589 | AO133: 517 | AP133: 1.7 | AQ133: =IFERROR(AL133*1000/AZ133,"") -> 22.83105 | AR133: 241 | AS133: 133 | AT133: 51 | AU133: 10 | AV133: 47 | AW133: =IFERROR(AS133/AR133,"") -> 0.55186722 | AX133: 1 | AY133: 7 | AZ133: 4161 | BA133: 75.588 | BB133: 55.05 | BC133: 0.628 | BD133: 44.8 | BE133: 99.41 | BF133: 5.7 | BG133: 4.5 | BH133: 3.15 | BI133: 589 | BJ133: 1.7 | BK133: =IFERROR(BI133/AZ133,"") -> 0.14155251 | BL133: =IFERROR(AI133+K133+S133+AA133-F133,"") -> 1 | BM133: =IFERROR(F133+G133-C133,"") -> 0 | BN133: =IF(I133="","",IFERROR(C133*1000/H133-I133,"")) -> 0.050119131
A134: 2413706 | B134: Sítio Novo | C134: 53783 | D134: 58723 | E134: 64195 | F134: 51913 | G134: 1870 | H134: 5600 | I134: 9604.13 | J134: 13793.54 | K134: 1613 | L134: =IFERROR(K134/F134,"") -> 0.031071215 | M134: =IFERROR(K134*1000/H134,"") -> 288.03571 | N134: =IF(L134="","",RANK(L134,$L$3:$L$168,0)+COUNTIF($L$3:L134,L134)-1) -> 149 | O134: =IF(K134="","",RANK(K134,$K$3:$K$168,0)+COUNTIF($K$3:K134,K134)-1) -> 149 | P134: 30 | Q134: =IFERROR(P134/AR134,"") -> 0.12195122 | R134: 1 | S134: 11158 | T134: =IFERROR(S134/F134,"") -> 0.21493653 | U134: =IFERROR(S134*1000/H134,"") -> 1992.5 | V134: =IF(T134="","",RANK(T134,$T$3:$T$168,0)+COUNTIF($T$3:T134,T134)-1) -> 133 | W134: =IF(S134="","",RANK(S134,$S$3:$S$168,0)+COUNTIF($S$3:S134,S134)-1) -> 137 | X134: 94 | Y134: 117 | Z134: =IFERROR((X134+Y134)/AR134,"") -> 0.85772358 | AA134: 36020 | AB134: =IFERROR(AA134/F134,"") -> 0.69385318 | AC134: =IFERROR(AA134*1000/H134,"") -> 6432.1429 | AD134: =IF(AB134="","",RANK(AB134,$AB$3:$AB$168,0)+COUNTIF($AB$3:AB134,AB134)-1) -> 9 | AE134: =IF(AA134="","",RANK(AA134,$AA$3:$AA$168,0)+COUNTIF($AA$3:AA134,AA134)-1) -> 114 | AF134: 95.25 | AG134: 50408587 | AH134: =IFERROR(AG134/AZ134,"") -> 10831.239 | AI134: 3122 | AJ134: =IFERROR(AI134/F134,"") -> 0.060139079 | AK134: 66 | AL134: 81 | AM134: 82 | AN134: 310 | AO134: 258 | AP134: 2.4 | AQ134: =IFERROR(AL134*1000/AZ134,"") -> 17.404383 | AR134: 246 | AS134: 130 | AT134: 59 | AU134: 1 | AV134: 56 | AW134: =IFERROR(AS134/AR134,"") -> 0.52845528 | AX134: 0 | AY134: 5 | AZ134: 4654 | BA134: 213.456 | BB134: 21.8 | BC134: 0.572 | BD134: 52.9 | BE134: 97.93 | BF134: 5.1 | BG134: 4.7 | BH134: 28.65 | BI134: 310 | BJ134: 2.4 | BK134: =IFERROR(BI134/AZ134,"") -> 0.066609368 | BL134: =IFERROR(AI134+K134+S134+AA134-F134,"") -> 0 | BM134: =IFERROR(F134+G134-C134,"") -> 0 | BN134: =IF(I134="","",IFERROR(C134*1000/H134-I134,"")) -> -0.022857143
A135: 2410504 | B135: Rafael Fernandes | C135: 53271 | D135: 57950 | E135: 61865 | F135: 49705 | G135: 3566 | H135: 5158 | I135: 10327.79 | J135: 11389.04 | K135: 1871 | L135: =IFERROR(K135/F135,"") -> 0.037642088 | M135: =IFERROR(K135*1000/H135,"") -> 362.7375 | N135: =IF(L135="","",RANK(L135,$L$3:$L$168,0)+COUNTIF($L$3:L135,L135)-1) -> 135 | O135: =IF(K135="","",RANK(K135,$K$3:$K$168,0)+COUNTIF($K$3:K135,K135)-1) -> 141 | P135: 41 | Q135: =IFERROR(P135/AR135,"") -> 0.13621262 | R135: 6 | S135: 16590 | T135: =IFERROR(S135/F135,"") -> 0.33376924 | U135: =IFERROR(S135*1000/H135,"") -> 3216.3629 | V135: =IF(T135="","",RANK(T135,$T$3:$T$168,0)+COUNTIF($T$3:T135,T135)-1) -> 40 | W135: =IF(S135="","",RANK(S135,$S$3:$S$168,0)+COUNTIF($S$3:S135,S135)-1) -> 113 | X135: 109 | Y135: 141 | Z135: =IFERROR((X135+Y135)/AR135,"") -> 0.83056478 | AA135: 25663 | AB135: =IFERROR(AA135/F135,"") -> 0.51630621 | AC135: =IFERROR(AA135*1000/H135,"") -> 4975.3781 | AD135: =IF(AB135="","",RANK(AB135,$AB$3:$AB$168,0)+COUNTIF($AB$3:AB135,AB135)-1) -> 84 | AE135: =IF(AA135="","",RANK(AA135,$AA$3:$AA$168,0)+COUNTIF($AA$3:AA135,AA135)-1) -> 145 | AF135: 96.71 | AG135: 34013023 | AH135: =IFERROR(AG135/AZ135,"") -> 6261.6022 | AI135: 5580 | AJ135: =IFERROR(AI135/F135,"") -> 0.11226235 | AK135: 118 | AL135: 136 | AM135: 138 | AN135: 365 | AO135: 230 | AP135: 1.9 | AQ135: =IFERROR(AL135*1000/AZ135,"") -> 25.036819 | AR135: 301 | AS135: 129 | AT135: 109 | AU135: 13 | AV135: 50 | AW135: =IFERROR(AS135/AR135,"") -> 0.42857143 | AX135: 2 | AY135: 8 | AZ135: 5432 | BA135: 78.231 | BB135: 69.44 | BC135: 0.608 | BD135: 45.2 | BE135: 97.12 | BF135: 5.5 | BG135: 5.2 | BH135: 1.36 | BI135: 365 | BJ135: 1.9 | BK135: =IFERROR(BI135/AZ135,"") -> 0.067194404 | BL135: =IFERROR(AI135+K135+S135+AA135-F135,"") -> -1 | BM135: =IFERROR(F135+G135-C135,"") -> 0 | BN135: =IF(I135="","",IFERROR(C135*1000/H135-I135,"")) -> 0.050248158
A136: 2402808 | B136: Coronel Ezequiel | C136: 52506 | D136: 58596 | E136: 65460 | F136: 50524 | G136: 1982 | H136: 5501 | I136: 9544.81 | J136: 12792.57 | K136: 1596 | L136: =IFERROR(K136/F136,"") -> 0.031588948 | M136: =IFERROR(K136*1000/H136,"") -> 290.12907 | N136: =IF(L136="","",RANK(L136,$L$3:$L$168,0)+COUNTIF($L$3:L136,L136)-1) -> 145 | O136: =IF(K136="","",RANK(K136,$K$3:$K$168,0)+COUNTIF($K$3:K136,K136)-1) -> 150 | P136: 24 | Q136: =IFERROR(P136/AR136,"") -> 0.1182266 | R136: 3 | S136: 10733 | T136: =IFERROR(S136/F136,"") -> 0.21243369 | U136: =IFERROR(S136*1000/H136,"") -> 1951.0998 | V136: =IF(T136="","",RANK(T136,$T$3:$T$168,0)+COUNTIF($T$3:T136,T136)-1) -> 136 | W136: =IF(S136="","",RANK(S136,$S$3:$S$168,0)+COUNTIF($S$3:S136,S136)-1) -> 138 | X136: 94 | Y136: 79 | Z136: =IFERROR((X136+Y136)/AR136,"") -> 0.85221675 | AA136: 34364 | AB136: =IFERROR(AA136/F136,"") -> 0.68015201 | AC136: =IFERROR(AA136*1000/H136,"") -> 6246.8642 | AD136: =IF(AB136="","",RANK(AB136,$AB$3:$AB$168,0)+COUNTIF($AB$3:AB136,AB136)-1) -> 17 | AE136: =IF(AA136="","",RANK(AA136,$AA$3:$AA$168,0)+COUNTIF($AA$3:AA136,AA136)-1) -> 117 | AF136: 94.95 | AG136: 42248525 | AH136: =IFERROR(AG136/AZ136,"") -> 8256.5028 | AI136: 3831 | AJ136: =IFERROR(AI136/F136,"") -> 0.07582535 | AK136: 58 | AL136: 69 | AM136: 73 | AN136: 329 | AO136: 285 | AP136: 1.9 | AQ136: =IFERROR(AL136*1000/AZ136,"") -> 13.484464 | AR136: 203 | AS136: 110 | AT136: 47 | AU136: 4 | AV136: 42 | AW136: =IFERROR(AS136/AR136,"") -> 0.54187192 | AX136: 0 | AY136: 6 | AZ136: 5117 | BA136: 185.748 | BB136: 27.55 | BC136: 0.587 | BD136: 52.8 | BE136: 99.59 | BF136: 5 | BG136: 3.6 | BH136: 16.42 | BI136: 326 | BJ136: 1.9 | BK136: =IFERROR(BI136/AZ136,"") -> 0.063709205 | BL136: =IFERROR(AI136+K136+S136+AA136-F136,"") -> 0 | BM136: =IFERROR(F136+G136-C136,"") -> 0 | BN136: =IF(I136="","",IFERROR(C136*1000/H136-I136,"")) -> 3.4539175e-05
A137: 2406809 | B137: Lajes Pintadas | C137: 51593 | D137: 62556 | E137: 68290 | F137: 49842 | G137: 1751 | H137: 4768 | I137: 10820.77 | J137: 14265.69 | K137: 2244 | L137: =IFERROR(K137/F137,"") -> 0.04502227 | M137: =IFERROR(K137*1000/H137,"") -> 470.63758 | N137: =IF(L137="","",RANK(L137,$L$3:$L$168,0)+COUNTIF($L$3:L137,L137)-1) -> 99 | O137: =IF(K137="","",RANK(K137,$K$3:$K$168,0)+COUNTIF($K$3:K137,K137)-1) -> 130 | P137: 32 | Q137: =IFERROR(P137/AR137,"") -> 0.10631229 | R137: 8 | S137: 11904 | T137: =IFERROR(S137/F137,"") -> 0.23883472 | U137: =IFERROR(S137*1000/H137,"") -> 2496.6443 | V137: =IF(T137="","",RANK(T137,$T$3:$T$168,0)+COUNTIF($T$3:T137,T137)-1) -> 105 | W137: =IF(S137="","",RANK(S137,$S$3:$S$168,0)+COUNTIF($S$3:S137,S137)-1) -> 133 | X137: 107 | Y137: 156 | Z137: =IFERROR((X137+Y137)/AR137,"") -> 0.87375415 | AA137: 34222 | AB137: =IFERROR(AA137/F137,"") -> 0.68660969 | AC137: =IFERROR(AA137*1000/H137,"") -> 7177.4329 | AD137: =IF(AB137="","",RANK(AB137,$AB$3:$AB$168,0)+COUNTIF($AB$3:AB137,AB137)-1) -> 13 | AE137: =IF(AA137="","",RANK(AA137,$AA$3:$AA$168,0)+COUNTIF($AA$3:AA137,AA137)-1) -> 119 | AF137: 89.63 | AG137: 48698761 | AH137: =IFERROR(AG137/AZ137,"") -> 10173.127 | AI137: 1473 | AJ137: =IFERROR(AI137/F137,"") -> 0.029553389 | AK137: 95 | AL137: 113 | AM137: 117 | AN137: 482 | AO137: 409 | AP137: 1.7 | AQ137: =IFERROR(AL137*1000/AZ137,"") -> 23.605598 | AR137: 301 | AS137: 157 | AT137: 63 | AU137: 4 | AV137: 77 | AW137: =IFERROR(AS137/AR137,"") -> 0.52159468 | AX137: 1 | AY137: 5 | AZ137: 4787 | BA137: 130.211 | BB137: 36.76 | BC137: 0.625 | BD137: 51.3 | BE137: 96.31 | BF137: 5.2 | BG137: 4.7 | BH137: 28.1 | BI137: 482 | BJ137: 1.7 | BK137: =IFERROR(BI137/AZ137,"") -> 0.10068937 | BL137: =IFERROR(AI137+K137+S137+AA137-F137,"") -> 1 | BM137: =IFERROR(F137+G137-C137,"") -> 0 | BN137: =IF(I137="","",IFERROR(C137*1000/H137-I137,"")) -> -0.090469799
A138: 2405405 | B138: Japi | C138: 51547 | D138: 58421 | E138: 69177 | F138: 49951 | G138: 1596 | H138: 4935 | I138: 10445.13 | J138: 13519.14 | K138: 1896 | L138: =IFERROR(K138/F138,"") -> 0.037957198 | M138: =IFERROR(K138*1000/H138,"") -> 384.19453 | N138: =IF(L138="","",RANK(L138,$L$3:$L$168,0)+COUNTIF($L$3:L138,L138)-1) -> 133 | O138: =IF(K138="","",RANK(K138,$K$3:$K$168,0)+COUNTIF($K$3:K138,K138)-1) -> 140 | P138: 25 | Q138: =IFERROR(P138/AR138,"") -> 0.12690355 | R138: 1 | S138: 11357 | T138: =IFERROR(S138/F138,"") -> 0.22736282 | U138: =IFERROR(S138*1000/H138,"") -> 2301.3171 | V138: =IF(T138="","",RANK(T138,$T$3:$T$168,0)+COUNTIF($T$3:T138,T138)-1) -> 114 | W138: =IF(S138="","",RANK(S138,$S$3:$S$168,0)+COUNTIF($S$3:S138,S138)-1) -> 135 | X138: 84 | Y138: 81 | Z138: =IFERROR((X138+Y138)/AR138,"") -> 0.83756345 | AA138: 34372 | AB138: =IFERROR(AA138/F138,"") -> 0.68811435 | AC138: =IFERROR(AA138*1000/H138,"") -> 6964.9443 | AD138: =IF(AB138="","",RANK(AB138,$AB$3:$AB$168,0)+COUNTIF($AB$3:AB138,AB138)-1) -> 11 | AE138: =IF(AA138="","",RANK(AA138,$AA$3:$AA$168,0)+COUNTIF($AA$3:AA138,AA138)-1) -> 116 | AF138: 97 | AG138: 38431432 | AH138: =IFERROR(AG138/AZ138,"") -> 7510.5398 | AI138: 2327 | AJ138: =IFERROR(AI138/F138,"") -> 0.046585654 | AK138: 68 | AL138: 65 | AM138: 65 | AN138: 419 | AO138: 385 | AP138: 1.9 | AQ138: =IFERROR(AL138*1000/AZ138,"") -> 12.702756 | AR138: 197 | AS138: 102 | AT138: 40 | AU138: 3 | AV138: 52 | AW138: =IFERROR(AS138/AR138,"") -> 0.5177665 | AX138: 1 | AY138: 6 | AZ138: 5117 | BA138: 188.99 | BB138: 27.08 | BC138: 0.569 | BD138: 55.5 | BE138: 99.65 | BF138: 4.6 | BG138: 3.9 | BH138: 40.43 | BI138: 419 | BJ138: 1.9 | BK138: =IFERROR(BI138/AZ138,"") -> 0.081883916 | BL138: =IFERROR(AI138+K138+S138+AA138-F138,"") -> 1 | BM138: =IFERROR(F138+G138-C138,"") -> 0 | BN138: =IF(I138="","",IFERROR(C138*1000/H138-I138,"")) -> 0.057436677
A139: 2406908 | B139: Lucrécia | C139: 51509 | D139: 53827 | E139: 61082 | F139: 48489 | G139: 3021 | H139: 4053 | I139: 12708.91 | J139: 17501.97 | K139: 6960 | L139: =IFERROR(K139/F139,"") -> 0.14353771 | M139: =IFERROR(K139*1000/H139,"") -> 1717.2465 | N139: =IF(L139="","",RANK(L139,$L$3:$L$168,0)+COUNTIF($L$3:L139,L139)-1) -> 47 | O139: =IF(K139="","",RANK(K139,$K$3:$K$168,0)+COUNTIF($K$3:K139,K139)-1) -> 77 | P139: 38 | Q139: =IFERROR(P139/AR139,"") -> 0.14074074 | R139: 15 | S139: 13375 | T139: =IFERROR(S139/F139,"") -> 0.27583576 | U139: =IFERROR(S139*1000/H139,"") -> 3300.0247 | V139: =IF(T139="","",RANK(T139,$T$3:$T$168,0)+COUNTIF($T$3:T139,T139)-1) -> 70 | W139: =IF(S139="","",RANK(S139,$S$3:$S$168,0)+COUNTIF($S$3:S139,S139)-1) -> 124 | X139: 80 | Y139: 141 | Z139: =IFERROR((X139+Y139)/AR139,"") -> 0.81851852 | AA139: 25618 | AB139: =IFERROR(AA139/F139,"") -> 0.52832601 | AC139: =IFERROR(AA139*1000/H139,"") -> 6320.7501 | AD139: =IF(AB139="","",RANK(AB139,$AB$3:$AB$168,0)+COUNTIF($AB$3:AB139,AB139)-1) -> 79 | AE139: =IF(AA139="","",RANK(AA139,$AA$3:$AA$168,0)+COUNTIF($AA$3:AA139,AA139)-1) -> 146 | AF139: 95.71 | AG139: 38125612 | AH139: =IFERROR(AG139/AZ139,"") -> 10924.244 | AI139: 2535 | AJ139: =IFERROR(AI139/F139,"") -> 0.052279899 | AK139: 149 | AL139: 165 | AM139: 168 | AN139: 472 | AO139: 324 | AP139: 1.8 | AQ139: =IFERROR(AL139*1000/AZ139,"") -> 47.277937 | AR139: 270 | AS139: 84 | AT139: 93 | AU139: 31 | AV139: 62 | AW139: =IFERROR(AS139/AR139,"") -> 0.31111111 | AX139: 2 | AY139: 8 | AZ139: 3490 | BA139: 30.931 | BB139: 112.83 | BC139: 0.646 | BD139: 49.2 | BE139: 100 | BF139: 5.5 | BG139: 5.2 | BH139: 56.32 | BI139: 472 | BJ139: 1.8 | BK139: =IFERROR(BI139/AZ139,"") -> 0.13524355 | BL139: =IFERROR(AI139+K139+S139+AA139-F139,"") -> -1 | BM139: =IFERROR(F139+G139-C139,"") -> 1 | BN139: =IF(I139="","",IFERROR(C139*1000/H139-I139,"")) -> -0.052363681
A140: 2400604 | B140: Almino Afonso | C140: 50061 | D140: 61042 | E140: 68329 | F140: 47792 | G140: 2269 | H140: 4685 | I140: 10685.4 | J140: 14578.35 | K140: 2238 | L140: =IFERROR(K140/F140,"") -> 0.046827921 | M140: =IFERROR(K140*1000/H140,"") -> 477.69477 | N140: =IF(L140="","",RANK(L140,$L$3:$L$168,0)+COUNTIF($L$3:L140,L140)-1) -> 94 | O140: =IF(K140="","",RANK(K140,$K$3:$K$168,0)+COUNTIF($K$3:K140,K140)-1) -> 131 | P140: 33 | Q140: =IFERROR(P140/AR140,"") -> 0.14347826 | R140: 10 | S140: 12956 | T140: =IFERROR(S140/F140,"") -> 0.2710914 | U140: =IFERROR(S140*1000/H140,"") -> 2765.4216 | V140: =IF(T140="","",RANK(T140,$T$3:$T$168,0)+COUNTIF($T$3:T140,T140)-1) -> 74 | W140: =IF(S140="","",RANK(S140,$S$3:$S$168,0)+COUNTIF($S$3:S140,S140)-1) -> 130 | X140: 98 | Y140: 89 | Z140: =IFERROR((X140+Y140)/AR140,"") -> 0.81304348 | AA140: 29925 | AB140: =IFERROR(AA140/F140,"") -> 0.62615082 | AC140: =IFERROR(AA140*1000/H140,"") -> 6387.4066 | AD140: =IF(AB140="","",RANK(AB140,$AB$3:$AB$168,0)+COUNTIF($AB$3:AB140,AB140)-1) -> 43 | AE140: =IF(AA140="","",RANK(AA140,$AA$3:$AA$168,0)+COUNTIF($AA$3:AA140,AA140)-1) -> 131 | AF140: 96.43 | AG140: 53247031 | AH140: =IFERROR(AG140/AZ140,"") -> 11360.578 | AI140: 2673 | AJ140: =IFERROR(AI140/F140,"") -> 0.055929863 | AK140: 110 | AL140: 120 | AM140: 121 | AN140: 402 | AO140: 306 | AP140: 2 | AQ140: =IFERROR(AL140*1000/AZ140,"") -> 25.602731 | AR140: 230 | AS140: 88 | AT140: 75 | AU140: 14 | AV140: 53 | AW140: =IFERROR(AS140/AR140,"") -> 0.3826087 | AX140: 0 | AY140: 10 | AZ140: 4687 | BA140: 128.038 | BB140: 36.61 | BC140: 0.624 | BD140: 50.7 | BE140: 98.04 | BF140: 6.7 | BG140: 4.5 | BH140: 8.13 | BI140: 402 | BJ140: 2 | BK140: =IFERROR(BI140/AZ140,"") -> 0.085769149 | BL140: =IFERROR(AI140+K140+S140+AA140-F140,"") -> 0 | BM140: =IFERROR(F140+G140-C140,"") -> 0 | BN140: =IF(I140="","",IFERROR(C140*1000/H140-I140,"")) -> -0.02113127
A141: 2413557 | B141: Serrinha dos Pintos | C141: 49786 | D141: 56138 | E141: 64722 | F141: 47329 | G141: 2457 | H141: 4832 | I141: 10303.47 | J141: 13891.79 | K141: 3051 | L141: =IFERROR(K141/F141,"") -> 0.064463648 | M141: =IFERROR(K141*1000/H141,"") -> 631.41556 | N141: =IF(L141="","",RANK(L141,$L$3:$L$168,0)+COUNTIF($L$3:L141,L141)-1) -> 74 | O141: =IF(K141="","",RANK(K141,$K$3:$K$168,0)+COUNTIF($K$3:K141,K141)-1) -> 115 | P141: 39 | Q141: =IFERROR(P141/AR141,"") -> 0.13131313 | R141: 6 | S141: 12535 | T141: =IFERROR(S141/F141,"") -> 0.26484819 | U141: =IFERROR(S141*1000/H141,"") -> 2594.1639 | V141: =IF(T141="","",RANK(T141,$T$3:$T$168,0)+COUNTIF($T$3:T141,T141)-1) -> 81 | W141: =IF(S141="","",RANK(S141,$S$3:$S$168,0)+COUNTIF($S$3:S141,S141)-1) -> 131 | X141: 118 | Y141: 130 | Z141: =IFERROR((X141+Y141)/AR141,"") -> 0.83501684 | AA141: 29640 | AB141: =IFERROR(AA141/F141,"") -> 0.62625452 | AC141: =IFERROR(AA141*1000/H141,"") -> 6134.106 | AD141: =IF(AB141="","",RANK(AB141,$AB$3:$AB$168,0)+COUNTIF($AB$3:AB141,AB141)-1) -> 42 | AE141: =IF(AA141="","",RANK(AA141,$AA$3:$AA$168,0)+COUNTIF($AA$3:AA141,AA141)-1) -> 132 | AF141: 96.12 | AG141: 43098492 | AH141: =IFERROR(AG141/AZ141,"") -> 9250.5884 | AI141: 2102 | AJ141: =IFERROR(AI141/F141,"") -> 0.044412517 | AK141: 107 | AL141: 119 | AM141: 120 | AN141: 513 | AO141: 407 | AP141: 1.7 | AQ141: =IFERROR(AL141*1000/AZ141,"") -> 25.541962 | AR141: 297 | AS141: 151 | AT141: 80 | AU141: 9 | AV141: 57 | AW141: =IFERROR(AS141/AR141,"") -> 0.50841751 | AX141: 0 | AY141: 10 | AZ141: 4659 | BA141: 122.375 | BB141: 38.07 | BC141: 0.598 | BD141: 51.3 | BE141: 100 | BF141: 6.3 | BG141: 6 | BH141: 0.37 | BI141: 513 | BJ141: 1.7 | BK141: =IFERROR(BI141/AZ141,"") -> 0.11010947 | BL141: =IFERROR(AI141+K141+S141+AA141-F141,"") -> -1 | BM141: =IFERROR(F141+G141-C141,"") -> 0 | BN141: =IF(I141="","",IFERROR(C141*1000/H141-I141,"")) -> -0.075960265
A142: 2402907 | B142: Coronel João Pessoa | C142: 48166 | D142: 46989 | E142: 54170 | F142: 46698 | G142: 1468 | H142: 4918 | I142: 9793.87 | J142: 12785.04 | K142: 1156 | L142: =IFERROR(K142/F142,"") -> 0.024754807 | M142: =IFERROR(K142*1000/H142,"") -> 235.0549 | N142: =IF(L142="","",RANK(L142,$L$3:$L$168,0)+COUNTIF($L$3:L142,L142)-1) -> 157 | O142: =IF(K142="","",RANK(K142,$K$3:$K$168,0)+COUNTIF($K$3:K142,K142)-1) -> 157 | P142: 20 | Q142: =IFERROR(P142/AR142,"") -> 0.076628352 | R142: 2 | S142: 9922 | T142: =IFERROR(S142/F142,"") -> 0.21247163 | U142: =IFERROR(S142*1000/H142,"") -> 2017.4868 | V142: =IF(T142="","",RANK(T142,$T$3:$T$168,0)+COUNTIF($T$3:T142,T142)-1) -> 135 | W142: =IF(S142="","",RANK(S142,$S$3:$S$168,0)+COUNTIF($S$3:S142,S142)-1) -> 145 | X142: 58 | Y142: 172 | Z142: =IFERROR((X142+Y142)/AR142,"") -> 0.88122605 | AA142: 33140 | AB142: =IFERROR(AA142/F142,"") -> 0.70966637 | AC142: =IFERROR(AA142*1000/H142,"") -> 6738.5116 | AD142: =IF(AB142="","",RANK(AB142,$AB$3:$AB$168,0)+COUNTIF($AB$3:AB142,AB142)-1) -> 4 | AE142: =IF(AA142="","",RANK(AA142,$AA$3:$AA$168,0)+COUNTIF($AA$3:AA142,AA142)-1) -> 122 | AF142: 84.85 | AG142: 42009552 | AH142: =IFERROR(AG142/AZ142,"") -> 9914.9285 | AI142: 2481 | AJ142: =IFERROR(AI142/F142,"") -> 0.053128614 | AK142: 72 | AL142: 73 | AM142: 74 | AN142: 278 | AO142: 234 | AP142: 2 | AQ142: =IFERROR(AL142*1000/AZ142,"") -> 17.229172 | AR142: 261 | AS142: 167 | AT142: 37 | AU142: 2 | AV142: 55 | AW142: =IFERROR(AS142/AR142,"") -> 0.63984674 | AX142: 1 | AY142: 10 | AZ142: 4237 | BA142: 117.139 | BB142: 36.17 | BC142: 0.578 | BD142: 52.4 | BE142: 99.45 | BF142: 5.6 | BG142: 3.7 | BH142: 3.38 | BI142: 278 | BJ142: 2 | BK142: =IFERROR(BI142/AZ142,"") -> 0.065612462 | BL142: =IFERROR(AI142+K142+S142+AA142-F142,"") -> 1 | BM142: =IFERROR(F142+G142-C142,"") -> 0 | BN142: =IF(I142="","",IFERROR(C142*1000/H142-I142,"")) -> -0.051374542
A143: 2407252 | B143: Major Sales | C143: 48003 | D143: 56007 | E143: 65725 | F143: 45694 | G143: 2309 | H143: 4102 | I143: 11702.31 | J143: 16749.53 | K143: 968 | L143: =IFERROR(K143/F143,"") -> 0.021184401 | M143: =IFERROR(K143*1000/H143,"") -> 235.98245 | N143: =IF(L143="","",RANK(L143,$L$3:$L$168,0)+COUNTIF($L$3:L143,L143)-1) -> 162 | O143: =IF(K143="","",RANK(K143,$K$3:$K$168,0)+COUNTIF($K$3:K143,K143)-1) -> 163 | P143: 16 | Q143: =IFERROR(P143/AR143,"") -> 0.072072072 | R143: 0 | S143: 13168 | T143: =IFERROR(S143/F143,"") -> 0.28817788 | U143: =IFERROR(S143*1000/H143,"") -> 3210.1414 | V143: =IF(T143="","",RANK(T143,$T$3:$T$168,0)+COUNTIF($T$3:T143,T143)-1) -> 61 | W143: =IF(S143="","",RANK(S143,$S$3:$S$168,0)+COUNTIF($S$3:S143,S143)-1) -> 127 | X143: 74 | Y143: 126 | Z143: =IFERROR((X143+Y143)/AR143,"") -> 0.9009009 | AA143: 29332 | AB143: =IFERROR(AA143/F143,"") -> 0.64192235 | AC143: =IFERROR(AA143*1000/H143,"") -> 7150.6582 | AD143: =IF(AB143="","",RANK(AB143,$AB$3:$AB$168,0)+COUNTIF($AB$3:AB143,AB143)-1) -> 34 | AE143: =IF(AA143="","",RANK(AA143,$AA$3:$AA$168,0)+COUNTIF($AA$3:AA143,AA143)-1) -> 134 | AF143: 88.98 | AG143: 43321265 | AH143: =IFERROR(AG143/AZ143,"") -> 11040.078 | AI143: 2225 | AJ143: =IFERROR(AI143/F143,"") -> 0.048693483 | AK143: 80 | AL143: 99 | AM143: 101 | AN143: 327 | AO143: 251 | AP143: 2.6 | AQ143: =IFERROR(AL143*1000/AZ143,"") -> 25.229358 | AR143: 222 | AS143: 104 | AT143: 64 | AU143: 8 | AV143: 46 | AW143: =IFERROR(AS143/AR143,"") -> 0.46846847 | AX143: 1 | AY143: 5 | AZ143: 3924 | BA143: 31.971 | BB143: 122.74 | BC143: 0.617 | BD143: 48.5 | BE143: 100 | BF143: 6.1 | BG143: 5.7 | BH143: 24.62 | BI143: 327 | BJ143: 2.6 | BK143: =IFERROR(BI143/AZ143,"") -> 0.083333333 | BL143: =IFERROR(AI143+K143+S143+AA143-F143,"") -> -1 | BM143: =IFERROR(F143+G143-C143,"") -> 0 | BN143: =IF(I143="","",IFERROR(C143*1000/H143-I143,"")) -> 0.030321794
A144: 2408409 | B144: Olho d'Água do Borges | C144: 47532 | D144: 48871 | E144: 58972 | F144: 45635 | G144: 1897 | H144: 4231 | I144: 11234.26 | J144: 15101.6 | K144: 5355 | L144: =IFERROR(K144/F144,"") -> 0.11734414 | M144: =IFERROR(K144*1000/H144,"") -> 1265.6582 | N144: =IF(L144="","",RANK(L144,$L$3:$L$168,0)+COUNTIF($L$3:L144,L144)-1) -> 52 | O144: =IF(K144="","",RANK(K144,$K$3:$K$168,0)+COUNTIF($K$3:K144,K144)-1) -> 88 | P144: 28 | Q144: =IFERROR(P144/AR144,"") -> 0.11336032 | R144: 3 | S144: 10288 | T144: =IFERROR(S144/F144,"") -> 0.225441 | U144: =IFERROR(S144*1000/H144,"") -> 2431.5765 | V144: =IF(T144="","",RANK(T144,$T$3:$T$168,0)+COUNTIF($T$3:T144,T144)-1) -> 117 | W144: =IF(S144="","",RANK(S144,$S$3:$S$168,0)+COUNTIF($S$3:S144,S144)-1) -> 142 | X144: 94 | Y144: 114 | Z144: =IFERROR((X144+Y144)/AR144,"") -> 0.84210526 | AA144: 26708 | AB144: =IFERROR(AA144/F144,"") -> 0.58525255 | AC144: =IFERROR(AA144*1000/H144,"") -> 6312.4557 | AD144: =IF(AB144="","",RANK(AB144,$AB$3:$AB$168,0)+COUNTIF($AB$3:AB144,AB144)-1) -> 61 | AE144: =IF(AA144="","",RANK(AA144,$AA$3:$AA$168,0)+COUNTIF($AA$3:AA144,AA144)-1) -> 142 | AF144: 91.01 | AG144: 39315828 | AH144: =IFERROR(AG144/AZ144,"") -> 10068.074 | AI144: 3285 | AJ144: =IFERROR(AI144/F144,"") -> 0.071984223 | AK144: 103 | AL144: 127 | AM144: 129 | AN144: 543 | AO144: 444 | AP144: 1.4 | AQ144: =IFERROR(AL144*1000/AZ144,"") -> 32.522407 | AR144: 247 | AS144: 102 | AT144: 82 | AU144: 7 | AV144: 56 | AW144: =IFERROR(AS144/AR144,"") -> 0.41295547 | AX144: 0 | AY144: 10 | AZ144: 3905 | BA144: 136.393 | BB144: 27.66 | BC144: 0.585 | BD144: 51.4 | BE144: 98.63 | BF144: 4.4 | BG144: 4.6 | BH144: 13.56 | BI144: 543 | BJ144: 1.4 | BK144: =IFERROR(BI144/AZ144,"") -> 0.1390525 | BL144: =IFERROR(AI144+K144+S144+AA144-F144,"") -> 1 | BM144: =IFERROR(F144+G144-C144,"") -> 0 | BN144: =IF(I144="","",IFERROR(C144*1000/H144-I144,"")) -> -0.036412196
A145: 2409209 | B145: Passagem | C145: 46128 | D145: 52292 | E145: 46583 | F145: 44599 | G145: 1529 | H145: 3114 | I145: 14813.1 | J145: 14954.29 | K145: 1796 | L145: =IFERROR(K145/F145,"") -> 0.040269961 | M145: =IFERROR(K145*1000/H145,"") -> 576.75016 | N145: =IF(L145="","",RANK(L145,$L$3:$L$168,0)+COUNTIF($L$3:L145,L145)-1) -> 121 | O145: =IF(K145="","",RANK(K145,$K$3:$K$168,0)+COUNTIF($K$3:K145,K145)-1) -> 142 | P145: 26 | Q145: =IFERROR(P145/AR145,"") -> 0.080745342 | R145: 2 | S145: 15810 | T145: =IFERROR(S145/F145,"") -> 0.35449225 | U145: =IFERROR(S145*1000/H145,"") -> 5077.0713 | V145: =IF(T145="","",RANK(T145,$T$3:$T$168,0)+COUNTIF($T$3:T145,T145)-1) -> 35 | W145: =IF(S145="","",RANK(S145,$S$3:$S$168,0)+COUNTIF($S$3:S145,S145)-1) -> 116 | X145: 63 | Y145: 225 | Z145: =IFERROR((X145+Y145)/AR145,"") -> 0.89440994 | AA145: 24886 | AB145: =IFERROR(AA145/F145,"") -> 0.55799457 | AC145: =IFERROR(AA145*1000/H145,"") -> 7991.6506 | AD145: =IF(AB145="","",RANK(AB145,$AB$3:$AB$168,0)+COUNTIF($AB$3:AB145,AB145)-1) -> 71 | AE145: =IF(AA145="","",RANK(AA145,$AA$3:$AA$168,0)+COUNTIF($AA$3:AA145,AA145)-1) -> 150 | AF145: 95.82 | AG145: 36420993 | AH145: =IFERROR(AG145/AZ145,"") -> 11692.133 | AI145: 2108 | AJ145: =IFERROR(AI145/F145,"") -> 0.047265634 | AK145: 57 | AL145: 88 | AM145: 90 | AN145: 314 | AO145: 243 | AP145: 1.6 | AQ145: =IFERROR(AL145*1000/AZ145,"") -> 28.250401 | AR145: 322 | AS145: 205 | AT145: 34 | AU145: 10 | AV145: 73 | AW145: =IFERROR(AS145/AR145,"") -> 0.63664596 | AX145: 0 | AY145: 8 | AZ145: 3115 | BA145: 41.215 | BB145: 75.58 | BC145: 0.589 | BD145: 48.2 | BE145: 99.27 | BF145: 4.7 | BG145: 3.8 | BH145: 2.38 | BI145: 314 | BJ145: 1.6 | BK145: =IFERROR(BI145/AZ145,"") -> 0.10080257 | BL145: =IFERROR(AI145+K145+S145+AA145-F145,"") -> 1 | BM145: =IFERROR(F145+G145-C145,"") -> 0 | BN145: =IF(I145="","",IFERROR(C145*1000/H145-I145,"")) -> 0.0021194605
A146: 2401503 | B146: Barcelona | C146: 45864 | D146: 55408 | E146: 63583 | F146: 44310 | G146: 1554 | H146: 3989 | I146: 11497.52 | J146: 15951.65 | K146: 1790 | L146: =IFERROR(K146/F146,"") -> 0.040397202 | M146: =IFERROR(K146*1000/H146,"") -> 448.73402 | N146: =IF(L146="","",RANK(L146,$L$3:$L$168,0)+COUNTIF($L$3:L146,L146)-1) -> 120 | O146: =IF(K146="","",RANK(K146,$K$3:$K$168,0)+COUNTIF($K$3:K146,K146)-1) -> 143 | P146: 20 | Q146: =IFERROR(P146/AR146,"") -> 0.10810811 | R146: 1 | S146: 10446 | T146: =IFERROR(S146/F146,"") -> 0.23574814 | U146: =IFERROR(S146*1000/H146,"") -> 2618.7014 | V146: =IF(T146="","",RANK(T146,$T$3:$T$168,0)+COUNTIF($T$3:T146,T146)-1) -> 107 | W146: =IF(S146="","",RANK(S146,$S$3:$S$168,0)+COUNTIF($S$3:S146,S146)-1) -> 140 | X146: 58 | Y146: 98 | Z146: =IFERROR((X146+Y146)/AR146,"") -> 0.84324324 | AA146: 30481 | AB146: =IFERROR(AA146/F146,"") -> 0.68790341 | AC146: =IFERROR(AA146*1000/H146,"") -> 7641.2635 | AD146: =IF(AB146="","",RANK(AB146,$AB$3:$AB$168,0)+COUNTIF($AB$3:AB146,AB146)-1) -> 12 | AE146: =IF(AA146="","",RANK(AA146,$AA$3:$AA$168,0)+COUNTIF($AA$3:AA146,AA146)-1) -> 128 | AF146: 96.77 | AG146: 35696717 | AH146: =IFERROR(AG146/AZ146,"") -> 8955.5236 | AI146: 1593 | AJ146: =IFERROR(AI146/F146,"") -> 0.035951253 | AK146: 56 | AL146: 72 | AM146: 73 | AN146: 563 | AO146: 522 | AP146: 1.5 | AQ146: =IFERROR(AL146*1000/AZ146,"") -> 18.063221 | AR146: 185 | AS146: 87 | AT146: 50 | AU146: 4 | AV146: 44 | AW146: =IFERROR(AS146/AR146,"") -> 0.47027027 | AX146: 2 | AY146: 7 | AZ146: 3986 | BA146: 152.626 | BB146: 26.12 | BC146: 0.566 | BD146: 50.6 | BE146: 99.55 | BG146: 3.6 | BH146: 4.14 | BI146: 563 | BJ146: 1.5 | BK146: =IFERROR(BI146/AZ146,"") -> 0.14124436 | BL146: =IFERROR(AI146+K146+S146+AA146-F146,"") -> 0 | BM146: =IFERROR(F146+G146-C146,"") -> 0 | BN146: =IF(I146="","",IFERROR(C146*1000/H146-I146,"")) -> 0.09845074
A147: 2414456 | B147: Triunfo Potiguar | C147: 45829 | D147: 52839 | E147: 55944 | F147: 44047 | G147: 1783 | H147: 3195 | I147: 14344.12 | J147: 16571.2 | K147: 1789 | L147: =IFERROR(K147/F147,"") -> 0.040615706 | M147: =IFERROR(K147*1000/H147,"") -> 559.9374 | N147: =IF(L147="","",RANK(L147,$L$3:$L$168,0)+COUNTIF($L$3:L147,L147)-1) -> 119 | O147: =IF(K147="","",RANK(K147,$K$3:$K$168,0)+COUNTIF($K$3:K147,K147)-1) -> 144 | P147: 17 | Q147: =IFERROR(P147/AR147,"") -> 0.10828025 | R147: 7 | S147: 10043 | T147: =IFERROR(S147/F147,"") -> 0.22800645 | U147: =IFERROR(S147*1000/H147,"") -> 3143.349 | V147: =IF(T147="","",RANK(T147,$T$3:$T$168,0)+COUNTIF($T$3:T147,T147)-1) -> 113 | W147: =IF(S147="","",RANK(S147,$S$3:$S$168,0)+COUNTIF($S$3:S147,S147)-1) -> 144 | X147: 65 | Y147: 69 | Z147: =IFERROR((X147+Y147)/AR147,"") -> 0.85350318 | AA147: 27621 | AB147: =IFERROR(AA147/F147,"") -> 0.62708016 | AC147: =IFERROR(AA147*1000/H147,"") -> 8645.0704 | AD147: =IF(AB147="","",RANK(AB147,$AB$3:$AB$168,0)+COUNTIF($AB$3:AB147,AB147)-1) -> 41 | AE147: =IF(AA147="","",RANK(AA147,$AA$3:$AA$168,0)+COUNTIF($AA$3:AA147,AA147)-1) -> 139 | AF147: 90.98 | AG147: 39892118 | AH147: =IFERROR(AG147/AZ147,"") -> 11816.386 | AI147: 4594 | AJ147: =IFERROR(AI147/F147,"") -> 0.10429768 | AK147: 74 | AL147: 89 | AM147: 93 | AN147: 451 | AO147: 374 | AP147: 1.5 | AQ147: =IFERROR(AL147*1000/AZ147,"") -> 26.362559 | AR147: 157 | AS147: 46 | AT147: 49 | AU147: 12 | AV147: 50 | AW147: =IFERROR(AS147/AR147,"") -> 0.29299363 | AX147: 1 | AY147: 5 | AZ147: 3376 | BA147: 268.725 | BB147: 12.56 | BC147: 0.602 | BD147: 48.4 | BE147: 99.22 | BF147: 4.8 | BG147: 4.2 | BH147: 13.92 | BI147: 449 | BJ147: 1.5 | BK147: =IFERROR(BI147/AZ147,"") -> 0.13299763 | BL147: =IFERROR(AI147+K147+S147+AA147-F147,"") -> 0 | BM147: =IFERROR(F147+G147-C147,"") -> 1 | BN147: =IF(I147="","",IFERROR(C147*1000/H147-I147,"")) -> -0.14503912
A148: 2411700 | B148: São Bento do Trairí | C148: 45623 | D148: 55558 | E148: 58251 | F148: 44260 | G148: 1362 | H148: 4541 | I148: 10046.8 | J148: 15361.52 | K148: 1741 | L148: =IFERROR(K148/F148,"") -> 0.039335743 | M148: =IFERROR(K148*1000/H148,"") -> 383.39573 | N148: =IF(L148="","",RANK(L148,$L$3:$L$168,0)+COUNTIF($L$3:L148,L148)-1) -> 126 | O148: =IF(K148="","",RANK(K148,$K$3:$K$168,0)+COUNTIF($K$3:K148,K148)-1) -> 147 | P148: 14 | Q148: =IFERROR(P148/AR148,"") -> 0.084337349 | R148: 2 | S148: 8121 | T148: =IFERROR(S148/F148,"") -> 0.18348396 | U148: =IFERROR(S148*1000/H148,"") -> 1788.3726 | V148: =IF(T148="","",RANK(T148,$T$3:$T$168,0)+COUNTIF($T$3:T148,T148)-1) -> 150 | W148: =IF(S148="","",RANK(S148,$S$3:$S$168,0)+COUNTIF($S$3:S148,S148)-1) -> 155 | X148: 48 | Y148: 97 | Z148: =IFERROR((X148+Y148)/AR148,"") -> 0.87349398 | AA148: 30965 | AB148: =IFERROR(AA148/F148,"") -> 0.69961591 | AC148: =IFERROR(AA148*1000/H148,"") -> 6818.9826 | AD148: =IF(AB148="","",RANK(AB148,$AB$3:$AB$168,0)+COUNTIF($AB$3:AB148,AB148)-1) -> 8 | AE148: =IF(AA148="","",RANK(AA148,$AA$3:$AA$168,0)+COUNTIF($AA$3:AA148,AA148)-1) -> 124 | AF148: 89.05 | AG148: 43326245 | AH148: =IFERROR(AG148/AZ148,"") -> 11425.698 | AI148: 3432 | AJ148: =IFERROR(AI148/F148,"") -> 0.077541798 | AK148: 57 | AL148: 70 | AM148: 70 | AN148: 397 | AO148: 354 | AP148: 1.8 | AQ148: =IFERROR(AL148*1000/AZ148,"") -> 18.459916 | AR148: 166 | AS148: 79 | AT148: 36 | AU148: 2 | AV148: 49 | AW148: =IFERROR(AS148/AR148,"") -> 0.47590361 | AX148: 2 | AY148: 5 | AZ148: 3792 | BA148: 190.818 | BB148: 19.87 | BC148: 0.595 | BD148: 53.4 | BE148: 100 | BF148: 4.6 | BG148: 4.8 | BH148: 58.89 | BI148: 397 | BJ148: 1.8 | BK148: =IFERROR(BI148/AZ148,"") -> 0.10469409 | BL148: =IFERROR(AI148+K148+S148+AA148-F148,"") -> -1 | BM148: =IFERROR(F148+G148-C148,"") -> -1 | BN148: =IF(I148="","",IFERROR(C148*1000/H148-I148,"")) -> 0.10596785
A149: 2404002 | B149: Frutuoso Gomes | C149: 44911 | D149: 52614 | E149: 58994 | F149: 42208 | G149: 2703 | H149: 4015 | I149: 11185.81 | J149: 14311.89 | K149: 2284 | L149: =IFERROR(K149/F149,"") -> 0.054112964 | M149: =IFERROR(K149*1000/H149,"") -> 568.86675 | N149: =IF(L149="","",RANK(L149,$L$3:$L$168,0)+COUNTIF($L$3:L149,L149)-1) -> 84 | O149: =IF(K149="","",RANK(K149,$K$3:$K$168,0)+COUNTIF($K$3:K149,K149)-1) -> 129 | P149: 19 | Q149: =IFERROR(P149/AR149,"") -> 0.09947644 | R149: 8 | S149: 13145 | T149: =IFERROR(S149/F149,"") -> 0.31143385 | U149: =IFERROR(S149*1000/H149,"") -> 3273.9726 | V149: =IF(T149="","",RANK(T149,$T$3:$T$168,0)+COUNTIF($T$3:T149,T149)-1) -> 50 | W149: =IF(S149="","",RANK(S149,$S$3:$S$168,0)+COUNTIF($S$3:S149,S149)-1) -> 128 | X149: 78 | Y149: 87 | Z149: =IFERROR((X149+Y149)/AR149,"") -> 0.86387435 | AA149: 24771 | AB149: =IFERROR(AA149/F149,"") -> 0.58687926 | AC149: =IFERROR(AA149*1000/H149,"") -> 6169.6139 | AD149: =IF(AB149="","",RANK(AB149,$AB$3:$AB$168,0)+COUNTIF($AB$3:AB149,AB149)-1) -> 60 | AE149: =IF(AA149="","",RANK(AA149,$AA$3:$AA$168,0)+COUNTIF($AA$3:AA149,AA149)-1) -> 152 | AH149: =IFERROR(AG149/AZ149,"") -> 0 | AI149: 2009 | AJ149: =IFERROR(AI149/F149,"") -> 0.047597612 | AK149: 95 | AL149: 105 | AM149: 108 | AN149: 452 | AO149: 354 | AP149: 1.5 | AQ149: =IFERROR(AL149*1000/AZ149,"") -> 25.473071 | AR149: 191 | AS149: 52 | AT149: 75 | AU149: 10 | AV149: 54 | AW149: =IFERROR(AS149/AR149,"") -> 0.27225131 | AX149: 0 | AY149: 7 | AZ149: 4122 | BA149: 63.279 | BB149: 65.14 | BC149: 0.597 | BD149: 50.8 | BE149: 98.87 | BF149: 5.5 | BG149: 4.7 | BH149: 0.85 | BI149: 452 | BJ149: 1.5 | BK149: =IFERROR(BI149/AZ149,"") -> 0.10965551 | BL149: =IFERROR(AI149+K149+S149+AA149-F149,"") -> 1 | BM149: =IFERROR(F149+G149-C149,"") -> 0 | BN149: =IF(I149="","",IFERROR(C149*1000/H149-I149,"")) -> -0.006762142
A150: 2415008 | B150: Vila Flor | C150: 44403 | D150: 47194 | E150: 49863 | F150: 42348 | G150: 2055 | H150: 3217 | I150: 13802.59 | J150: 15709.84 | K150: 1976 | L150: =IFERROR(K150/F150,"") -> 0.046660999 | M150: =IFERROR(K150*1000/H150,"") -> 614.23687 | N150: =IF(L150="","",RANK(L150,$L$3:$L$168,0)+COUNTIF($L$3:L150,L150)-1) -> 95 | O150: =IF(K150="","",RANK(K150,$K$3:$K$168,0)+COUNTIF($K$3:K150,K150)-1) -> 139 | P150: 26 | Q150: =IFERROR(P150/AR150,"") -> 0.16149068 | R150: 1 | S150: 9616 | T150: =IFERROR(S150/F150,"") -> 0.22707094 | U150: =IFERROR(S150*1000/H150,"") -> 2989.1203 | V150: =IF(T150="","",RANK(T150,$T$3:$T$168,0)+COUNTIF($T$3:T150,T150)-1) -> 115 | W150: =IF(S150="","",RANK(S150,$S$3:$S$168,0)+COUNTIF($S$3:S150,S150)-1) -> 146 | X150: 43 | Y150: 81 | Z150: =IFERROR((X150+Y150)/AR150,"") -> 0.77018634 | AA150: 24950 | AB150: =IFERROR(AA150/F150,"") -> 0.58916596 | AC150: =IFERROR(AA150*1000/H150,"") -> 7755.673 | AD150: =IF(AB150="","",RANK(AB150,$AB$3:$AB$168,0)+COUNTIF($AB$3:AB150,AB150)-1) -> 58 | AE150: =IF(AA150="","",RANK(AA150,$AA$3:$AA$168,0)+COUNTIF($AA$3:AA150,AA150)-1) -> 149 | AF150: 95.72 | AG150: 35198036 | AH150: =IFERROR(AG150/AZ150,"") -> 11089.488 | AI150: 5807 | AJ150: =IFERROR(AI150/F150,"") -> 0.13712572 | AK150: 59 | AL150: 74 | AM150: 75 | AN150: 428 | AO150: 381 | AP150: 1.4 | AQ150: =IFERROR(AL150*1000/AZ150,"") -> 23.31443 | AR150: 161 | AS150: 77 | AT150: 41 | AU150: 3 | AV150: 40 | AW150: =IFERROR(AS150/AR150,"") -> 0.47826087 | AX150: 4 | AY150: 7 | AZ150: 3174 | BA150: 47.656 | BB150: 66.6 | BC150: 0.576 | BD150: 48.3 | BE150: 98.29 | BF150: 4.4 | BG150: 3.4 | BH150: 4.92 | BI150: 428 | BJ150: 1.4 | BK150: =IFERROR(BI150/AZ150,"") -> 0.13484562 | BL150: =IFERROR(AI150+K150+S150+AA150-F150,"") -> 1 | BM150: =IFERROR(F150+G150-C150,"") -> 0 | BN150: =IF(I150="","",IFERROR(C150*1000/H150-I150,"")) -> 0.02112838
A151: 2408607 | B151: Paraná | C151: 43930 | D151: 50385 | E151: 56062 | F151: 42517 | G151: 1413 | H151: 4298 | I151: 10221.11 | J151: 14250.66 | K151: 829 | L151: =IFERROR(K151/F151,"") -> 0.019498083 | M151: =IFERROR(K151*1000/H151,"") -> 192.88041 | N151: =IF(L151="","",RANK(L151,$L$3:$L$168,0)+COUNTIF($L$3:L151,L151)-1) -> 165 | O151: =IF(K151="","",RANK(K151,$K$3:$K$168,0)+COUNTIF($K$3:K151,K151)-1) -> 164 | P151: 10 | Q151: =IFERROR(P151/AR151,"") -> 0.076335878 | R151: 3 | S151: 9234 | T151: =IFERROR(S151/F151,"") -> 0.21718371 | U151: =IFERROR(S151*1000/H151,"") -> 2148.4411 | V151: =IF(T151="","",RANK(T151,$T$3:$T$168,0)+COUNTIF($T$3:T151,T151)-1) -> 131 | W151: =IF(S151="","",RANK(S151,$S$3:$S$168,0)+COUNTIF($S$3:S151,S151)-1) -> 150 | X151: 51 | Y151: 62 | Z151: =IFERROR((X151+Y151)/AR151,"") -> 0.86259542 | AA151: 29928 | AB151: =IFERROR(AA151/F151,"") -> 0.70390667 | AC151: =IFERROR(AA151*1000/H151,"") -> 6963.2387 | AD151: =IF(AB151="","",RANK(AB151,$AB$3:$AB$168,0)+COUNTIF($AB$3:AB151,AB151)-1) -> 7 | AE151: =IF(AA151="","",RANK(AA151,$AA$3:$AA$168,0)+COUNTIF($AA$3:AA151,AA151)-1) -> 130 | AF151: 95.42 | AG151: 34622815 | AH151: =IFERROR(AG151/AZ151,"") -> 8800.919 | AI151: 2526 | AJ151: =IFERROR(AI151/F151,"") -> 0.05941153 | AK151: 58 | AL151: 66 | AM151: 68 | AN151: 228 | AO151: 176 | AP151: 2.6 | AQ151: =IFERROR(AL151*1000/AZ151,"") -> 16.776817 | AR151: 131 | AS151: 42 | AT151: 43 | AU151: 2 | AV151: 44 | AW151: =IFERROR(AS151/AR151,"") -> 0.32061069 | AX151: 0 | AY151: 8 | AZ151: 3934 | BA151: 81.39 | BB151: 48.34 | BC151: 0.589 | BD151: 56.3 | BE151: 99.36 | BF151: 4.9 | BG151: 5 | BH151: 3.33 | BI151: 228 | BJ151: 2.6 | BK151: =IFERROR(BI151/AZ151,"") -> 0.057956279 | BL151: =IFERROR(AI151+K151+S151+AA151-F151,"") -> 0 | BM151: =IFERROR(F151+G151-C151,"") -> 0 | BN151: =IF(I151="","",IFERROR(C151*1000/H151-I151,"")) -> -0.076961377
A152: 2414308 | B152: Timbaúba dos Batistas | C152: 43617 | D152: 44947 | E152: 47341 | F152: 41148 | G152: 2469 | H152: 2427 | I152: 17971.71 | J152: 20162.37 | K152: 1281 | L152: =IFERROR(K152/F152,"") -> 0.031131525 | M152: =IFERROR(K152*1000/H152,"") -> 527.81211 | N152: =IF(L152="","",RANK(L152,$L$3:$L$168,0)+COUNTIF($L$3:L152,L152)-1) -> 148 | O152: =IF(K152="","",RANK(K152,$K$3:$K$168,0)+COUNTIF($K$3:K152,K152)-1) -> 155 | P152: 65 | Q152: =IFERROR(P152/AR152,"") -> 0.32019704 | R152: 2 | S152: 8684 | T152: =IFERROR(S152/F152,"") -> 0.21104306 | U152: =IFERROR(S152*1000/H152,"") -> 3578.0799 | V152: =IF(T152="","",RANK(T152,$T$3:$T$168,0)+COUNTIF($T$3:T152,T152)-1) -> 137 | W152: =IF(S152="","",RANK(S152,$S$3:$S$168,0)+COUNTIF($S$3:S152,S152)-1) -> 152 | X152: 48 | Y152: 83 | Z152: =IFERROR((X152+Y152)/AR152,"") -> 0.6453202 | AA152: 20312 | AB152: =IFERROR(AA152/F152,"") -> 0.49363274 | AC152: =IFERROR(AA152*1000/H152,"") -> 8369.1801 | AD152: =IF(AB152="","",RANK(AB152,$AB$3:$AB$168,0)+COUNTIF($AB$3:AB152,AB152)-1) -> 92 | AE152: =IF(AA152="","",RANK(AA152,$AA$3:$AA$168,0)+COUNTIF($AA$3:AA152,AA152)-1) -> 164 | AF152: 94.84 | AG152: 36103353 | AH152: =IFERROR(AG152/AZ152,"") -> 15376.215 | AI152: 10870 | AJ152: =IFERROR(AI152/F152,"") -> 0.26416837 | AK152: 63 | AL152: 71 | AM152: 71 | AN152: 219 | AO152: 167 | AP152: 1.6 | AQ152: =IFERROR(AL152*1000/AZ152,"") -> 30.238501 | AR152: 203 | AS152: 118 | AT152: 44 | AU152: 2 | AV152: 39 | AW152: =IFERROR(AS152/AR152,"") -> 0.58128079 | AX152: 1 | AY152: 6 | AZ152: 2348 | BA152: 135.456 | BB152: 17.33 | BC152: 0.64 | BD152: 40.2 | BE152: 99.03 | BF152: 5.4 | BG152: 5.2 | BH152: 26.96 | BI152: 219 | BJ152: 1.6 | BK152: =IFERROR(BI152/AZ152,"") -> 0.093270869 | BL152: =IFERROR(AI152+K152+S152+AA152-F152,"") -> -1 | BM152: =IFERROR(F152+G152-C152,"") -> 0 | BN152: =IF(I152="","",IFERROR(C152*1000/H152-I152,"")) -> -0.14016069
A153: 2410801 | B153: Riacho de Santana | C153: 43512 | D153: 48437 | E153: 53836 | F153: 42112 | G153: 1400 | H153: 4194 | I153: 10374.93 | J153: 13044.94 | K153: 1136 | L153: =IFERROR(K153/F153,"") -> 0.026975684 | M153: =IFERROR(K153*1000/H153,"") -> 270.86314 | N153: =IF(L153="","",RANK(L153,$L$3:$L$168,0)+COUNTIF($L$3:L153,L153)-1) -> 156 | O153: =IF(K153="","",RANK(K153,$K$3:$K$168,0)+COUNTIF($K$3:K153,K153)-1) -> 158 | P153: 8 | Q153: =IFERROR(P153/AR153,"") -> 0.051948052 | R153: 1 | S153: 9478 | T153: =IFERROR(S153/F153,"") -> 0.22506649 | U153: =IFERROR(S153*1000/H153,"") -> 2259.8951 | V153: =IF(T153="","",RANK(T153,$T$3:$T$168,0)+COUNTIF($T$3:T153,T153)-1) -> 118 | W153: =IF(S153="","",RANK(S153,$S$3:$S$168,0)+COUNTIF($S$3:S153,S153)-1) -> 148 | X153: 54 | Y153: 85 | Z153: =IFERROR((X153+Y153)/AR153,"") -> 0.9025974 | AA153: 28696 | AB153: =IFERROR(AA153/F153,"") -> 0.68142097 | AC153: =IFERROR(AA153*1000/H153,"") -> 6842.1555 | AD153: =IF(AB153="","",RANK(AB153,$AB$3:$AB$168,0)+COUNTIF($AB$3:AB153,AB153)-1) -> 15 | AE153: =IF(AA153="","",RANK(AA153,$AA$3:$AA$168,0)+COUNTIF($AA$3:AA153,AA153)-1) -> 136 | AF153: 95.68 | AG153: 38640486 | AH153: =IFERROR(AG153/AZ153,"") -> 9362.851 | AI153: 2802 | AJ153: =IFERROR(AI153/F153,"") -> 0.066536854 | AK153: 56 | AL153: 59 | AM153: 61 | AN153: 389 | AO153: 333 | AP153: 1.7 | AQ153: =IFERROR(AL153*1000/AZ153,"") -> 14.296099 | AR153: 154 | AS153: 73 | AT153: 33 | AU153: 2 | AV153: 46 | AW153: =IFERROR(AS153/AR153,"") -> 0.47402597 | AX153: 0 | AY153: 7 | AZ153: 4127 | BA153: 128.106 | BB153: 32.22 | BC153: 0.591 | BD153: 50 | BE153: 99.27 | BF153: 5.5 | BG153: 5 | BH153: 7.73 | BI153: 389 | BJ153: 1.7 | BK153: =IFERROR(BI153/AZ153,"") -> 0.09425733 | BL153: =IFERROR(AI153+K153+S153+AA153-F153,"") -> 0 | BM153: =IFERROR(F153+G153-C153,"") -> 0 | BN153: =IF(I153="","",IFERROR(C153*1000/H153-I153,"")) -> -0.1088269
A154: 2410603 | B154: Rafael Godeiro | C154: 43450 | D154: 45690 | E154: 48290 | F154: 41725 | G154: 1725 | H154: 3214 | I154: 13519.06 | J154: 16458.77 | K154: 3794 | L154: =IFERROR(K154/F154,"") -> 0.0909287 | M154: =IFERROR(K154*1000/H154,"") -> 1180.4605 | N154: =IF(L154="","",RANK(L154,$L$3:$L$168,0)+COUNTIF($L$3:L154,L154)-1) -> 64 | O154: =IF(K154="","",RANK(K154,$K$3:$K$168,0)+COUNTIF($K$3:K154,K154)-1) -> 105 | P154: 15 | Q154: =IFERROR(P154/AR154,"") -> 0.10869565 | R154: 2 | S154: 9584 | T154: =IFERROR(S154/F154,"") -> 0.22969443 | U154: =IFERROR(S154*1000/H154,"") -> 2981.954 | V154: =IF(T154="","",RANK(T154,$T$3:$T$168,0)+COUNTIF($T$3:T154,T154)-1) -> 111 | W154: =IF(S154="","",RANK(S154,$S$3:$S$168,0)+COUNTIF($S$3:S154,S154)-1) -> 147 | X154: 58 | Y154: 58 | Z154: =IFERROR((X154+Y154)/AR154,"") -> 0.84057971 | AA154: 25054 | AB154: =IFERROR(AA154/F154,"") -> 0.60045536 | AC154: =IFERROR(AA154*1000/H154,"") -> 7795.2707 | AD154: =IF(AB154="","",RANK(AB154,$AB$3:$AB$168,0)+COUNTIF($AB$3:AB154,AB154)-1) -> 52 | AE154: =IF(AA154="","",RANK(AA154,$AA$3:$AA$168,0)+COUNTIF($AA$3:AA154,AA154)-1) -> 148 | AF154: 95.52 | AG154: 42196359 | AH154: =IFERROR(AG154/AZ154,"") -> 14381.854 | AI154: 3293 | AJ154: =IFERROR(AI154/F154,"") -> 0.07892151 | AK154: 71 | AL154: 75 | AM154: 77 | AN154: 364 | AO154: 304 | AP154: 2.2 | AQ154: =IFERROR(AL154*1000/AZ154,"") -> 25.562372 | AR154: 138 | AS154: 54 | AT154: 40 | AU154: 5 | AV154: 39 | AW154: =IFERROR(AS154/AR154,"") -> 0.39130435 | AX154: 1 | AY154: 6 | AZ154: 2934 | BA154: 100.073 | BB154: 29.32 | BC154: 0.654 | BD154: 47.3 | BE154: 97.64 | BF154: 6.4 | BG154: 5.8 | BH154: 0.17 | BI154: 364 | BJ154: 2.2 | BK154: =IFERROR(BI154/AZ154,"") -> 0.12406271 | BL154: =IFERROR(AI154+K154+S154+AA154-F154,"") -> 0 | BM154: =IFERROR(F154+G154-C154,"") -> 0 | BN154: =IF(I154="","",IFERROR(C154*1000/H154-I154,"")) -> -0.080535159
A155: 2414753 | B155: Venha-Ver | C155: 43202 | D155: 42294 | E155: 47870 | F155: 41871 | G155: 1331 | H155: 4232 | I155: 10208.37 | J155: 15882.39 | K155: 1032 | L155: =IFERROR(K155/F155,"") -> 0.02464713 | M155: =IFERROR(K155*1000/H155,"") -> 243.85633 | N155: =IF(L155="","",RANK(L155,$L$3:$L$168,0)+COUNTIF($L$3:L155,L155)-1) -> 158 | O155: =IF(K155="","",RANK(K155,$K$3:$K$168,0)+COUNTIF($K$3:K155,K155)-1) -> 160 | P155: 8 | Q155: =IFERROR(P155/AR155,"") -> 0.069565217 | R155: 1 | S155: 8432 | T155: =IFERROR(S155/F155,"") -> 0.20138043 | U155: =IFERROR(S155*1000/H155,"") -> 1992.4386 | V155: =IF(T155="","",RANK(T155,$T$3:$T$168,0)+COUNTIF($T$3:T155,T155)-1) -> 142 | W155: =IF(S155="","",RANK(S155,$S$3:$S$168,0)+COUNTIF($S$3:S155,S155)-1) -> 154 | X155: 34 | Y155: 66 | Z155: =IFERROR((X155+Y155)/AR155,"") -> 0.86956522 | AA155: 30311 | AB155: =IFERROR(AA155/F155,"") -> 0.72391393 | AC155: =IFERROR(AA155*1000/H155,"") -> 7162.3346 | AD155: =IF(AB155="","",RANK(AB155,$AB$3:$AB$168,0)+COUNTIF($AB$3:AB155,AB155)-1) -> 2 | AE155: =IF(AA155="","",RANK(AA155,$AA$3:$AA$168,0)+COUNTIF($AA$3:AA155,AA155)-1) -> 129 | AF155: 93.72 | AG155: 42285175 | AH155: =IFERROR(AG155/AZ155,"") -> 14029.587 | AI155: 2096 | AJ155: =IFERROR(AI155/F155,"") -> 0.050058513 | AK155: 61 | AL155: 60 | AM155: 61 | AN155: 293 | AO155: 256 | AP155: 2 | AQ155: =IFERROR(AL155*1000/AZ155,"") -> 19.9071 | AR155: 115 | AS155: 33 | AT155: 23 | AU155: 2 | AV155: 57 | AW155: =IFERROR(AS155/AR155,"") -> 0.28695652 | AX155: 0 | AY155: 7 | AZ155: 3014 | BA155: 71.621 | BB155: 42.08 | BC155: 0.555 | BD155: 58.3 | BE155: 98.38 | BF155: 5.1 | BG155: 4.5 | BH155: 6.3 | BI155: 292 | BJ155: 2 | BK155: =IFERROR(BI155/AZ155,"") -> 0.096881221 | BL155: =IFERROR(AI155+K155+S155+AA155-F155,"") -> 0 | BM155: =IFERROR(F155+G155-C155,"") -> 0 | BN155: =IF(I155="","",IFERROR(C155*1000/H155-I155,"")) -> 0.042098299
A156: 2406155 | B156: Jundiá | C156: 42147 | D156: 47189 | E156: 47291 | F156: 41100 | G156: 1046 | H156: 3945 | I156: 10683.63 | J156: 12648.01 | K156: 1185 | L156: =IFERROR(K156/F156,"") -> 0.028832117 | M156: =IFERROR(K156*1000/H156,"") -> 300.38023 | N156: =IF(L156="","",RANK(L156,$L$3:$L$168,0)+COUNTIF($L$3:L156,L156)-1) -> 154 | O156: =IF(K156="","",RANK(K156,$K$3:$K$168,0)+COUNTIF($K$3:K156,K156)-1) -> 156 | P156: 20 | Q156: =IFERROR(P156/AR156,"") -> 0.12269939 | R156: 1 | S156: 7499 | T156: =IFERROR(S156/F156,"") -> 0.18245742 | U156: =IFERROR(S156*1000/H156,"") -> 1900.8872 | V156: =IF(T156="","",RANK(T156,$T$3:$T$168,0)+COUNTIF($T$3:T156,T156)-1) -> 151 | W156: =IF(S156="","",RANK(S156,$S$3:$S$168,0)+COUNTIF($S$3:S156,S156)-1) -> 161 | X156: 47 | Y156: 84 | Z156: =IFERROR((X156+Y156)/AR156,"") -> 0.80368098 | AA156: 29090 | AB156: =IFERROR(AA156/F156,"") -> 0.70778589 | AC156: =IFERROR(AA156*1000/H156,"") -> 7373.891 | AD156: =IF(AB156="","",RANK(AB156,$AB$3:$AB$168,0)+COUNTIF($AB$3:AB156,AB156)-1) -> 5 | AE156: =IF(AA156="","",RANK(AA156,$AA$3:$AA$168,0)+COUNTIF($AA$3:AA156,AA156)-1) -> 135 | AF156: 95.48 | AG156: 41654536 | AH156: =IFERROR(AG156/AZ156,"") -> 11140.555 | AI156: 3326 | AJ156: =IFERROR(AI156/F156,"") -> 0.080924574 | AK156: 51 | AL156: 71 | AM156: 73 | AN156: 238 | AO156: 200 | AP156: 2.1 | AQ156: =IFERROR(AL156*1000/AZ156,"") -> 18.989035 | AR156: 163 | AS156: 77 | AT156: 34 | AU156: 1 | AV156: 51 | AW156: =IFERROR(AS156/AR156,"") -> 0.47239264 | AX156: 2 | AY156: 10 | AZ156: 3739 | BA156: 44.641 | BB156: 83.76 | BC156: 0.595 | BD156: 48.1 | BE156: 98.35 | BF156: 5.5 | BG156: 4.2 | BH156: 0.3 | BI156: 238 | BJ156: 2.1 | BK156: =IFERROR(BI156/AZ156,"") -> 0.063653383 | BL156: =IFERROR(AI156+K156+S156+AA156-F156,"") -> 0 | BM156: =IFERROR(F156+G156-C156,"") -> -1 | BN156: =IF(I156="","",IFERROR(C156*1000/H156-I156,"")) -> 0.020190114
A157: 2410009 | B157: Pilões | C157: 41829 | D157: 43979 | E157: 50550 | F157: 39511 | G157: 2317 | H157: 3900 | I157: 10725.27 | J157: 17049.05 | K157: 1290 | L157: =IFERROR(K157/F157,"") -> 0.032649136 | M157: =IFERROR(K157*1000/H157,"") -> 330.76923 | N157: =IF(L157="","",RANK(L157,$L$3:$L$168,0)+COUNTIF($L$3:L157,L157)-1) -> 144 | O157: =IF(K157="","",RANK(K157,$K$3:$K$168,0)+COUNTIF($K$3:K157,K157)-1) -> 154 | P157: 11 | Q157: =IFERROR(P157/AR157,"") -> 0.076388889 | R157: 3 | S157: 11231 | T157: =IFERROR(S157/F157,"") -> 0.28424996 | U157: =IFERROR(S157*1000/H157,"") -> 2879.7436 | V157: =IF(T157="","",RANK(T157,$T$3:$T$168,0)+COUNTIF($T$3:T157,T157)-1) -> 65 | W157: =IF(S157="","",RANK(S157,$S$3:$S$168,0)+COUNTIF($S$3:S157,S157)-1) -> 136 | X157: 51 | Y157: 71 | Z157: =IFERROR((X157+Y157)/AR157,"") -> 0.84722222 | AA157: 25145 | AB157: =IFERROR(AA157/F157,"") -> 0.63640505 | AC157: =IFERROR(AA157*1000/H157,"") -> 6447.4359 | AD157: =IF(AB157="","",RANK(AB157,$AB$3:$AB$168,0)+COUNTIF($AB$3:AB157,AB157)-1) -> 37 | AE157: =IF(AA157="","",RANK(AA157,$AA$3:$AA$168,0)+COUNTIF($AA$3:AA157,AA157)-1) -> 147 | AF157: 96.23 | AG157: 33453565 | AH157: =IFERROR(AG157/AZ157,"") -> 11282.821 | AI157: 1846 | AJ157: =IFERROR(AI157/F157,"") -> 0.046721166 | AK157: 63 | AL157: 75 | AM157: 75 | AN157: 252 | AO157: 194 | AP157: 2.5 | AQ157: =IFERROR(AL157*1000/AZ157,"") -> 25.29511 | AR157: 144 | AS157: 58 | AT157: 41 | AU157: 5 | AV157: 40 | AW157: =IFERROR(AS157/AR157,"") -> 0.40277778 | AX157: 3 | AY157: 8 | AZ157: 2965 | BA157: 82.69 | BB157: 35.86 | BC157: 0.614 | BD157: 50 | BE157: 100 | BF157: 6.2 | BG157: 5.2 | BH157: 53.53 | BI157: 252 | BJ157: 2.5 | BK157: =IFERROR(BI157/AZ157,"") -> 0.084991568 | BL157: =IFERROR(AI157+K157+S157+AA157-F157,"") -> 1 | BM157: =IFERROR(F157+G157-C157,"") -> -1 | BN157: =IF(I157="","",IFERROR(C157*1000/H157-I157,"")) -> 0.11461538
A158: 2403756 | B158: Fernando Pedroza | C158: 39069 | D158: 43862 | E158: 61994 | F158: 37398 | G158: 1671 | H158: 3081 | I158: 12680.57 | J158: 21100.64 | K158: 1768 | L158: =IFERROR(K158/F158,"") -> 0.047275255 | M158: =IFERROR(K158*1000/H158,"") -> 573.83966 | N158: =IF(L158="","",RANK(L158,$L$3:$L$168,0)+COUNTIF($L$3:L158,L158)-1) -> 91 | O158: =IF(K158="","",RANK(K158,$K$3:$K$168,0)+COUNTIF($K$3:K158,K158)-1) -> 145 | P158: 27 | Q158: =IFERROR(P158/AR158,"") -> 0.11392405 | R158: 8 | S158: 10633 | T158: =IFERROR(S158/F158,"") -> 0.28432002 | U158: =IFERROR(S158*1000/H158,"") -> 3451.1522 | V158: =IF(T158="","",RANK(T158,$T$3:$T$168,0)+COUNTIF($T$3:T158,T158)-1) -> 64 | W158: =IF(S158="","",RANK(S158,$S$3:$S$168,0)+COUNTIF($S$3:S158,S158)-1) -> 139 | X158: 52 | Y158: 147 | Z158: =IFERROR((X158+Y158)/AR158,"") -> 0.83966245 | AA158: 23689 | AB158: =IFERROR(AA158/F158,"") -> 0.6334296 | AC158: =IFERROR(AA158*1000/H158,"") -> 7688.7374 | AD158: =IF(AB158="","",RANK(AB158,$AB$3:$AB$168,0)+COUNTIF($AB$3:AB158,AB158)-1) -> 39 | AE158: =IF(AA158="","",RANK(AA158,$AA$3:$AA$168,0)+COUNTIF($AA$3:AA158,AA158)-1) -> 154 | AF158: 93.82 | AG158: 34626463 | AH158: =IFERROR(AG158/AZ158,"") -> 11785.726 | AI158: 1308 | AJ158: =IFERROR(AI158/F158,"") -> 0.034975132 | AK158: 89 | AL158: 105 | AM158: 105 | AN158: 286 | AO158: 183 | AP158: 2 | AQ158: =IFERROR(AL158*1000/AZ158,"") -> 35.738598 | AR158: 237 | AS158: 125 | AT158: 48 | AU158: 4 | AV158: 60 | AW158: =IFERROR(AS158/AR158,"") -> 0.52742616 | AX158: 2 | AY158: 9 | AZ158: 2938 | BA158: 322.628 | BB158: 9.11 | BC158: 0.597 | BD158: 52.9 | BE158: 98.27 | BF158: 3.9 | BG158: 4 | BH158: 3.37 | BI158: 286 | BJ158: 2 | BK158: =IFERROR(BI158/AZ158,"") -> 0.097345133 | BL158: =IFERROR(AI158+K158+S158+AA158-F158,"") -> 0 | BM158: =IFERROR(F158+G158-C158,"") -> 0 | BN158: =IF(I158="","",IFERROR(C158*1000/H158-I158,"")) -> 0.053174294
A159: 2406403 | B159: Lagoa de Velhos | C159: 38240 | D159: 42744 | E159: 48944 | F159: 37215 | G159: 1025 | H159: 2732 | I159: 13997.23 | J159: 19066.57 | K159: 5959 | L159: =IFERROR(K159/F159,"") -> 0.16012361 | M159: =IFERROR(K159*1000/H159,"") -> 2181.1859 | N159: =IF(L159="","",RANK(L159,$L$3:$L$168,0)+COUNTIF($L$3:L159,L159)-1) -> 44 | O159: =IF(K159="","",RANK(K159,$K$3:$K$168,0)+COUNTIF($K$3:K159,K159)-1) -> 85 | P159: 29 | Q159: =IFERROR(P159/AR159,"") -> 0.16022099 | R159: 6 | S159: 7104 | T159: =IFERROR(S159/F159,"") -> 0.19089077 | U159: =IFERROR(S159*1000/H159,"") -> 2600.2928 | V159: =IF(T159="","",RANK(T159,$T$3:$T$168,0)+COUNTIF($T$3:T159,T159)-1) -> 148 | W159: =IF(S159="","",RANK(S159,$S$3:$S$168,0)+COUNTIF($S$3:S159,S159)-1) -> 162 | X159: 59 | Y159: 83 | Z159: =IFERROR((X159+Y159)/AR159,"") -> 0.78453039 | AA159: 22391 | AB159: =IFERROR(AA159/F159,"") -> 0.60166599 | AC159: =IFERROR(AA159*1000/H159,"") -> 8195.8272 | AD159: =IF(AB159="","",RANK(AB159,$AB$3:$AB$168,0)+COUNTIF($AB$3:AB159,AB159)-1) -> 50 | AE159: =IF(AA159="","",RANK(AA159,$AA$3:$AA$168,0)+COUNTIF($AA$3:AA159,AA159)-1) -> 157 | AF159: 91.77 | AG159: 37141390 | AH159: =IFERROR(AG159/AZ159,"") -> 14468.792 | AI159: 1762 | AJ159: =IFERROR(AI159/F159,"") -> 0.0473465 | AK159: 65 | AL159: 72 | AM159: 73 | AN159: 333 | AO159: 288 | AP159: 2 | AQ159: =IFERROR(AL159*1000/AZ159,"") -> 28.048305 | AR159: 181 | AS159: 78 | AT159: 51 | AU159: 7 | AV159: 45 | AW159: =IFERROR(AS159/AR159,"") -> 0.43093923 | AX159: 2 | AY159: 8 | AZ159: 2567 | BA159: 111.607 | BB159: 23 | BC159: 0.589 | BD159: 48.2 | BE159: 100 | BF159: 4.5 | BG159: 3.8 | BH159: 0.71 | BI159: 333 | BJ159: 2 | BK159: =IFERROR(BI159/AZ159,"") -> 0.12972341 | BL159: =IFERROR(AI159+K159+S159+AA159-F159,"") -> 1 | BM159: =IFERROR(F159+G159-C159,"") -> 0 | BN159: =IF(I159="","",IFERROR(C159*1000/H159-I159,"")) -> -0.15825769
A160: 2410702 | B160: Riacho da Cruz | C160: 37507 | D160: 37690 | E160: 42857 | F160: 36126 | G160: 1380 | H160: 3648 | I160: 10281.41 | J160: 15867.02 | K160: 1679 | L160: =IFERROR(K160/F160,"") -> 0.046476222 | M160: =IFERROR(K160*1000/H160,"") -> 460.25219 | N160: =IF(L160="","",RANK(L160,$L$3:$L$168,0)+COUNTIF($L$3:L160,L160)-1) -> 96 | O160: =IF(K160="","",RANK(K160,$K$3:$K$168,0)+COUNTIF($K$3:K160,K160)-1) -> 148 | P160: 21 | Q160: =IFERROR(P160/AR160,"") -> 0.15441176 | R160: 9 | S160: 7704 | T160: =IFERROR(S160/F160,"") -> 0.21325361 | U160: =IFERROR(S160*1000/H160,"") -> 2111.8421 | V160: =IF(T160="","",RANK(T160,$T$3:$T$168,0)+COUNTIF($T$3:T160,T160)-1) -> 134 | W160: =IF(S160="","",RANK(S160,$S$3:$S$168,0)+COUNTIF($S$3:S160,S160)-1) -> 158 | X160: 39 | Y160: 61 | Z160: =IFERROR((X160+Y160)/AR160,"") -> 0.73529412 | AA160: 24804 | AB160: =IFERROR(AA160/F160,"") -> 0.68659691 | AC160: =IFERROR(AA160*1000/H160,"") -> 6799.3421 | AD160: =IF(AB160="","",RANK(AB160,$AB$3:$AB$168,0)+COUNTIF($AB$3:AB160,AB160)-1) -> 14 | AE160: =IF(AA160="","",RANK(AA160,$AA$3:$AA$168,0)+COUNTIF($AA$3:AA160,AA160)-1) -> 151 | AF160: 91.41 | AG160: 41501781 | AH160: =IFERROR(AG160/AZ160,"") -> 15365.339 | AI160: 1939 | AJ160: =IFERROR(AI160/F160,"") -> 0.053673255 | AK160: 70 | AL160: 86 | AM160: 87 | AN160: 348 | AO160: 271 | AP160: 1.8 | AQ160: =IFERROR(AL160*1000/AZ160,"") -> 31.840059 | AR160: 136 | AS160: 42 | AT160: 41 | AU160: 4 | AV160: 49 | AW160: =IFERROR(AS160/AR160,"") -> 0.30882353 | AX160: 2 | AY160: 13 | AZ160: 2701 | BA160: 127.223 | BB160: 21.23 | BC160: 0.584 | BD160: 50.1 | BE160: 98 | BF160: 4.7 | BH160: 41.84 | BI160: 348 | BJ160: 1.8 | BK160: =IFERROR(BI160/AZ160,"") -> 0.12884117 | BL160: =IFERROR(AI160+K160+S160+AA160-F160,"") -> 0 | BM160: =IFERROR(F160+G160-C160,"") -> -1 | BN160: =IF(I160="","",IFERROR(C160*1000/H160-I160,"")) -> 0.11412281
A161: 2411429 | B161: Santana do Seridó | C161: 36353 | D161: 44373 | E161: 51449 | F161: 34553 | G161: 1801 | H161: 2699 | I161: 13469.23 | J161: 19083.45 | K161: 3284 | L161: =IFERROR(K161/F161,"") -> 0.095042399 | M161: =IFERROR(K161*1000/H161,"") -> 1216.7469 | N161: =IF(L161="","",RANK(L161,$L$3:$L$168,0)+COUNTIF($L$3:L161,L161)-1) -> 60 | O161: =IF(K161="","",RANK(K161,$K$3:$K$168,0)+COUNTIF($K$3:K161,K161)-1) -> 111 | P161: 42 | Q161: =IFERROR(P161/AR161,"") -> 0.1875 | R161: 12 | S161: 7772 | T161: =IFERROR(S161/F161,"") -> 0.22492982 | U161: =IFERROR(S161*1000/H161,"") -> 2879.585 | V161: =IF(T161="","",RANK(T161,$T$3:$T$168,0)+COUNTIF($T$3:T161,T161)-1) -> 119 | W161: =IF(S161="","",RANK(S161,$S$3:$S$168,0)+COUNTIF($S$3:S161,S161)-1) -> 157 | X161: 71 | Y161: 102 | Z161: =IFERROR((X161+Y161)/AR161,"") -> 0.77232143 | AA161: 20660 | AB161: =IFERROR(AA161/F161,"") -> 0.59792203 | AC161: =IFERROR(AA161*1000/H161,"") -> 7654.6869 | AD161: =IF(AB161="","",RANK(AB161,$AB$3:$AB$168,0)+COUNTIF($AB$3:AB161,AB161)-1) -> 55 | AE161: =IF(AA161="","",RANK(AA161,$AA$3:$AA$168,0)+COUNTIF($AA$3:AA161,AA161)-1) -> 162 | AF161: 91.74 | AG161: 37877323 | AH161: =IFERROR(AG161/AZ161,"") -> 14049.452 | AI161: 2836 | AJ161: =IFERROR(AI161/F161,"") -> 0.08207681 | AK161: 98 | AL161: 93 | AM161: 95 | AN161: 553 | AO161: 462 | AP161: 1.5 | AQ161: =IFERROR(AL161*1000/AZ161,"") -> 34.495549 | AR161: 224 | AS161: 110 | AT161: 57 | AU161: 4 | AV161: 53 | AW161: =IFERROR(AS161/AR161,"") -> 0.49107143 | AX161: 2 | AY161: 7 | AZ161: 2696 | BA161: 188.403 | BB161: 14.31 | BC161: 0.642 | BD161: 41.7 | BE161: 100 | BF161: 6.4 | BG161: 3.9 | BH161: 68.35 | BI161: 553 | BJ161: 1.5 | BK161: =IFERROR(BI161/AZ161,"") -> 0.20511869 | BL161: =IFERROR(AI161+K161+S161+AA161-F161,"") -> -1 | BM161: =IFERROR(F161+G161-C161,"") -> 1 | BN161: =IF(I161="","",IFERROR(C161*1000/H161-I161,"")) -> -0.16738422
A162: 2409605 | B162: Pedra Preta | C162: 36126 | D162: 43026 | E162: 65240 | F162: 33704 | G162: 2422 | H162: 2419 | I162: 14934.43 | J162: 26726.71 | K162: 808 | L162: =IFERROR(K162/F162,"") -> 0.023973416 | M162: =IFERROR(K162*1000/H162,"") -> 334.02232 | N162: =IF(L162="","",RANK(L162,$L$3:$L$168,0)+COUNTIF($L$3:L162,L162)-1) -> 159 | O162: =IF(K162="","",RANK(K162,$K$3:$K$168,0)+COUNTIF($K$3:K162,K162)-1) -> 165 | P162: 15 | Q162: =IFERROR(P162/AR162,"") -> 0.13761468 | R162: 12 | S162: 6585 | T162: =IFERROR(S162/F162,"") -> 0.1953774 | U162: =IFERROR(S162*1000/H162,"") -> 2722.1993 | V162: =IF(T162="","",RANK(T162,$T$3:$T$168,0)+COUNTIF($T$3:T162,T162)-1) -> 146 | W162: =IF(S162="","",RANK(S162,$S$3:$S$168,0)+COUNTIF($S$3:S162,S162)-1) -> 164 | X162: 37 | Y162: 49 | Z162: =IFERROR((X162+Y162)/AR162,"") -> 0.78899083 | AA162: 22804 | AB162: =IFERROR(AA162/F162,"") -> 0.67659625 | AC162: =IFERROR(AA162*1000/H162,"") -> 9427.036 | AD162: =IF(AB162="","",RANK(AB162,$AB$3:$AB$168,0)+COUNTIF($AB$3:AB162,AB162)-1) -> 19 | AE162: =IF(AA162="","",RANK(AA162,$AA$3:$AA$168,0)+COUNTIF($AA$3:AA162,AA162)-1) -> 155 | AF162: 90.52 | AG162: 39205766 | AH162: =IFERROR(AG162/AZ162,"") -> 16061.354 | AI162: 3507 | AJ162: =IFERROR(AI162/F162,"") -> 0.10405293 | AK162: 51 | AL162: 66 | AM162: 66 | AN162: 263 | AO162: 231 | AP162: 1.9 | AQ162: =IFERROR(AL162*1000/AZ162,"") -> 27.038099 | AR162: 109 | AS162: 30 | AT162: 28 | AU162: 1 | AV162: 50 | AW162: =IFERROR(AS162/AR162,"") -> 0.27522936 | AX162: 1 | AY162: 7 | AZ162: 2441 | BA162: 294.985 | BB162: 8.27 | BC162: 0.558 | BD162: 55.1 | BE162: 99.15 | BF162: 4.8 | BG162: 4.1 | BH162: 1.73 | BI162: 263 | BJ162: 1.9 | BK162: =IFERROR(BI162/AZ162,"") -> 0.10774273 | BL162: =IFERROR(AI162+K162+S162+AA162-F162,"") -> 0 | BM162: =IFERROR(F162+G162-C162,"") -> 0 | BN162: =IF(I162="","",IFERROR(C162*1000/H162-I162,"")) -> -0.15964035
A163: 2404804 | B163: Ipueira | C163: 34929 | D163: 37971 | E163: 42669 | F163: 33229 | G163: 1700 | H163: 2264 | I163: 15427.96 | J163: 20967.76 | K163: 1491 | L163: =IFERROR(K163/F163,"") -> 0.044870444 | M163: =IFERROR(K163*1000/H163,"") -> 658.5689 | N163: =IF(L163="","",RANK(L163,$L$3:$L$168,0)+COUNTIF($L$3:L163,L163)-1) -> 100 | O163: =IF(K163="","",RANK(K163,$K$3:$K$168,0)+COUNTIF($K$3:K163,K163)-1) -> 152 | P163: 17 | Q163: =IFERROR(P163/AR163,"") -> 0.10759494 | R163: 2 | S163: 7640 | T163: =IFERROR(S163/F163,"") -> 0.22991965 | U163: =IFERROR(S163*1000/H163,"") -> 3374.5583 | V163: =IF(T163="","",RANK(T163,$T$3:$T$168,0)+COUNTIF($T$3:T163,T163)-1) -> 110 | W163: =IF(S163="","",RANK(S163,$S$3:$S$168,0)+COUNTIF($S$3:S163,S163)-1) -> 160 | X163: 39 | Y163: 93 | Z163: =IFERROR((X163+Y163)/AR163,"") -> 0.83544304 | AA163: 19281 | AB163: =IFERROR(AA163/F163,"") -> 0.58024617 | AC163: =IFERROR(AA163*1000/H163,"") -> 8516.3428 | AD163: =IF(AB163="","",RANK(AB163,$AB$3:$AB$168,0)+COUNTIF($AB$3:AB163,AB163)-1) -> 64 | AE163: =IF(AA163="","",RANK(AA163,$AA$3:$AA$168,0)+COUNTIF($AA$3:AA163,AA163)-1) -> 166 | AF163: 93.79 | AG163: 30806233 | AH163: =IFERROR(AG163/AZ163,"") -> 15138.198 | AI163: 4817 | AJ163: =IFERROR(AI163/F163,"") -> 0.14496374 | AK163: 57 | AL163: 55 | AM163: 55 | AN163: 328 | AO163: 289 | AP163: 2 | AQ163: =IFERROR(AL163*1000/AZ163,"") -> 27.027027 | AR163: 158 | AS163: 81 | AT163: 34 | AU163: 0 | AV163: 43 | AW163: =IFERROR(AS163/AR163,"") -> 0.51265823 | AX163: 2 | AY163: 7 | AZ163: 2035 | BA163: 127.348 | BB163: 15.98 | BC163: 0.679 | BD163: 37.5 | BE163: 99.45 | BF163: 7.3 | BG163: 5.8 | BH163: 77 | BI163: 328 | BJ163: 2 | BK163: =IFERROR(BI163/AZ163,"") -> 0.16117936 | BL163: =IFERROR(AI163+K163+S163+AA163-F163,"") -> 0 | BM163: =IFERROR(F163+G163-C163,"") -> 0 | BN163: =IF(I163="","",IFERROR(C163*1000/H163-I163,"")) -> 0.043533569
A164: 2400406 | B164: Água Nova | C164: 34552 | D164: 37809 | E164: 42554 | F164: 33061 | G164: 1491 | H164: 3293 | I164: 10492.59 | J164: 14444.7 | K164: 1001 | L164: =IFERROR(K164/F164,"") -> 0.030277366 | M164: =IFERROR(K164*1000/H164,"") -> 303.97814 | N164: =IF(L164="","",RANK(L164,$L$3:$L$168,0)+COUNTIF($L$3:L164,L164)-1) -> 151 | O164: =IF(K164="","",RANK(K164,$K$3:$K$168,0)+COUNTIF($K$3:K164,K164)-1) -> 161 | P164: 11 | Q164: =IFERROR(P164/AR164,"") -> 0.084615385 | R164: 1 | S164: 8887 | T164: =IFERROR(S164/F164,"") -> 0.26880615 | U164: =IFERROR(S164*1000/H164,"") -> 2698.7549 | V164: =IF(T164="","",RANK(T164,$T$3:$T$168,0)+COUNTIF($T$3:T164,T164)-1) -> 76 | W164: =IF(S164="","",RANK(S164,$S$3:$S$168,0)+COUNTIF($S$3:S164,S164)-1) -> 151 | X164: 47 | Y164: 63 | Z164: =IFERROR((X164+Y164)/AR164,"") -> 0.84615385 | AA164: 22038 | AB164: =IFERROR(AA164/F164,"") -> 0.66658601 | AC164: =IFERROR(AA164*1000/H164,"") -> 6692.3778 | AD164: =IF(AB164="","",RANK(AB164,$AB$3:$AB$168,0)+COUNTIF($AB$3:AB164,AB164)-1) -> 24 | AE164: =IF(AA164="","",RANK(AA164,$AA$3:$AA$168,0)+COUNTIF($AA$3:AA164,AA164)-1) -> 158 | AF164: 96.92 | AG164: 32354940 | AH164: =IFERROR(AG164/AZ164,"") -> 10982.668 | AI164: 1135 | AJ164: =IFERROR(AI164/F164,"") -> 0.03433048 | AK164: 50 | AL164: 61 | AM164: 61 | AN164: 302 | AO164: 261 | AP164: 1.8 | AQ164: =IFERROR(AL164*1000/AZ164,"") -> 20.706042 | AR164: 130 | AS164: 47 | AT164: 41 | AU164: 2 | AV164: 40 | AW164: =IFERROR(AS164/AR164,"") -> 0.36153846 | AX164: 1 | AY164: 8 | AZ164: 2946 | BA164: 50.684 | BB164: 58.12 | BC164: 0.616 | BD164: 55.1 | BE164: 100 | BF164: 5.9 | BG164: 4.5 | BH164: 1.05 | BI164: 302 | BJ164: 1.8 | BK164: =IFERROR(BI164/AZ164,"") -> 0.10251188 | BL164: =IFERROR(AI164+K164+S164+AA164-F164,"") -> 0 | BM164: =IFERROR(F164+G164-C164,"") -> 0 | BN164: =IF(I164="","",IFERROR(C164*1000/H164-I164,"")) -> -0.030024294
A165: 2403905 | B165: Francisco Dantas | C165: 32758 | D165: 36904 | E165: 42580 | F165: 31762 | G165: 995 | H165: 2801 | I165: 11694.99 | J165: 15770.38 | K165: 1082 | L165: =IFERROR(K165/F165,"") -> 0.034065865 | M165: =IFERROR(K165*1000/H165,"") -> 386.29061 | N165: =IF(L165="","",RANK(L165,$L$3:$L$168,0)+COUNTIF($L$3:L165,L165)-1) -> 140 | O165: =IF(K165="","",RANK(K165,$K$3:$K$168,0)+COUNTIF($K$3:K165,K165)-1) -> 159 | P165: 11 | Q165: =IFERROR(P165/AR165,"") -> 0.10784314 | R165: 3 | S165: 6640 | T165: =IFERROR(S165/F165,"") -> 0.20905485 | U165: =IFERROR(S165*1000/H165,"") -> 2370.5819 | V165: =IF(T165="","",RANK(T165,$T$3:$T$168,0)+COUNTIF($T$3:T165,T165)-1) -> 139 | W165: =IF(S165="","",RANK(S165,$S$3:$S$168,0)+COUNTIF($S$3:S165,S165)-1) -> 163 | X165: 24 | Y165: 57 | Z165: =IFERROR((X165+Y165)/AR165,"") -> 0.79411765 | AA165: 20834 | AB165: =IFERROR(AA165/F165,"") -> 0.65594106 | AC165: =IFERROR(AA165*1000/H165,"") -> 7438.0578 | AD165: =IF(AB165="","",RANK(AB165,$AB$3:$AB$168,0)+COUNTIF($AB$3:AB165,AB165)-1) -> 28 | AE165: =IF(AA165="","",RANK(AA165,$AA$3:$AA$168,0)+COUNTIF($AA$3:AA165,AA165)-1) -> 161 | AF165: 97.85 | AG165: 29338823 | AH165: =IFERROR(AG165/AZ165,"") -> 10866.231 | AI165: 3207 | AJ165: =IFERROR(AI165/F165,"") -> 0.10096971 | AK165: 58 | AL165: 66 | AM165: 68 | AN165: 374 | AO165: 339 | AP165: 1.5 | AQ165: =IFERROR(AL165*1000/AZ165,"") -> 24.444444 | AR165: 102 | AS165: 29 | AT165: 22 | AU165: 3 | AV165: 48 | AW165: =IFERROR(AS165/AR165,"") -> 0.28431373 | AX165: 1 | AY165: 9 | AZ165: 2700 | BA165: 181.558 | BB165: 14.87 | BC165: 0.606 | BD165: 49 | BE165: 100 | BF165: 5.7 | BG165: 4.4 | BH165: 13.89 | BI165: 374 | BJ165: 1.5 | BK165: =IFERROR(BI165/AZ165,"") -> 0.13851852 | BL165: =IFERROR(AI165+K165+S165+AA165-F165,"") -> 1 | BM165: =IFERROR(F165+G165-C165,"") -> -1 | BN165: =IF(I165="","",IFERROR(C165*1000/H165-I165,"")) -> 0.11888968
A166: 2413805 | B166: Taboleiro Grande | C166: 32472 | D166: 37505 | E166: 43556 | F166: 31296 | G166: 1176 | H166: 2606 | I166: 12460.48 | J166: 18629.47 | K166: 1477 | L166: =IFERROR(K166/F166,"") -> 0.04719453 | M166: =IFERROR(K166*1000/H166,"") -> 566.76899 | N166: =IF(L166="","",RANK(L166,$L$3:$L$168,0)+COUNTIF($L$3:L166,L166)-1) -> 92 | O166: =IF(K166="","",RANK(K166,$K$3:$K$168,0)+COUNTIF($K$3:K166,K166)-1) -> 153 | P166: 19 | Q166: =IFERROR(P166/AR166,"") -> 0.14393939 | R166: 3 | S166: 7701 | T166: =IFERROR(S166/F166,"") -> 0.24606979 | U166: =IFERROR(S166*1000/H166,"") -> 2955.1036 | V166: =IF(T166="","",RANK(T166,$T$3:$T$168,0)+COUNTIF($T$3:T166,T166)-1) -> 94 | W166: =IF(S166="","",RANK(S166,$S$3:$S$168,0)+COUNTIF($S$3:S166,S166)-1) -> 159 | X166: 46 | Y166: 60 | Z166: =IFERROR((X166+Y166)/AR166,"") -> 0.8030303 | AA166: 20648 | AB166: =IFERROR(AA166/F166,"") -> 0.65976483 | AC166: =IFERROR(AA166*1000/H166,"") -> 7923.254 | AD166: =IF(AB166="","",RANK(AB166,$AB$3:$AB$168,0)+COUNTIF($AB$3:AB166,AB166)-1) -> 27 | AE166: =IF(AA166="","",RANK(AA166,$AA$3:$AA$168,0)+COUNTIF($AA$3:AA166,AA166)-1) -> 163 | AF166: 95.09 | AG166: 33725197 | AH166: =IFERROR(AG166/AZ166,"") -> 14424.806 | AI166: 1470 | AJ166: =IFERROR(AI166/F166,"") -> 0.046970859 | AK166: 67 | AL166: 68 | AM166: 68 | AN166: 393 | AO166: 330 | AP166: 1.8 | AQ166: =IFERROR(AL166*1000/AZ166,"") -> 29.084688 | AR166: 132 | AS166: 49 | AT166: 41 | AU166: 5 | AV166: 37 | AW166: =IFERROR(AS166/AR166,"") -> 0.37121212 | AX166: 1 | AY166: 6 | AZ166: 2338 | BA166: 124.093 | BB166: 18.84 | BC166: 0.612 | BD166: 49.5 | BE166: 100 | BF166: 6 | BG166: 4.6 | BH166: 25.32 | BI166: 393 | BJ166: 1.8 | BK166: =IFERROR(BI166/AZ166,"") -> 0.16809239 | BL166: =IFERROR(AI166+K166+S166+AA166-F166,"") -> 0 | BM166: =IFERROR(F166+G166-C166,"") -> 0 | BN166: =IF(I166="","",IFERROR(C166*1000/H166-I166,"")) -> -0.0041749808
A167: 2407906 | B167: Monte das Gameleiras | C167: 32366 | D167: 37849 | E167: 45922 | F167: 31374 | G167: 992 | H167: 2063 | I167: 15688.66 | J167: 20176.56 | K167: 987 | L167: =IFERROR(K167/F167,"") -> 0.03145917 | M167: =IFERROR(K167*1000/H167,"") -> 478.42947 | N167: =IF(L167="","",RANK(L167,$L$3:$L$168,0)+COUNTIF($L$3:L167,L167)-1) -> 146 | O167: =IF(K167="","",RANK(K167,$K$3:$K$168,0)+COUNTIF($K$3:K167,K167)-1) -> 162 | P167: 10 | Q167: =IFERROR(P167/AR167,"") -> 0.079365079 | R167: 3 | S167: 8061 | T167: =IFERROR(S167/F167,"") -> 0.25693249 | U167: =IFERROR(S167*1000/H167,"") -> 3907.4164 | V167: =IF(T167="","",RANK(T167,$T$3:$T$168,0)+COUNTIF($T$3:T167,T167)-1) -> 89 | W167: =IF(S167="","",RANK(S167,$S$3:$S$168,0)+COUNTIF($S$3:S167,S167)-1) -> 156 | X167: 27 | Y167: 81 | Z167: =IFERROR((X167+Y167)/AR167,"") -> 0.85714286 | AA167: 21099 | AB167: =IFERROR(AA167/F167,"") -> 0.67249952 | AC167: =IFERROR(AA167*1000/H167,"") -> 10227.339 | AD167: =IF(AB167="","",RANK(AB167,$AB$3:$AB$168,0)+COUNTIF($AB$3:AB167,AB167)-1) -> 20 | AE167: =IF(AA167="","",RANK(AA167,$AA$3:$AA$168,0)+COUNTIF($AA$3:AA167,AA167)-1) -> 160 | AF167: 93.45 | AG167: 36194717 | AH167: =IFERROR(AG167/AZ167,"") -> 15902.775 | AI167: 1227 | AJ167: =IFERROR(AI167/F167,"") -> 0.039108816 | AK167: 60 | AL167: 76 | AM167: 76 | AN167: 394 | AO167: 339 | AP167: 1.9 | AQ167: =IFERROR(AL167*1000/AZ167,"") -> 33.391916 | AR167: 126 | AS167: 37 | AT167: 36 | AU167: 3 | AV167: 50 | AW167: =IFERROR(AS167/AR167,"") -> 0.29365079 | AX167: 1 | AY167: 7 | AZ167: 2276 | BA167: 71.946 | BB167: 31.63 | BC167: 0.598 | BD167: 50.2 | BE167: 99.42 | BF167: 5.5 | BG167: 4.2 | BH167: 37.35 | BI167: 394 | BJ167: 1.9 | BK167: =IFERROR(BI167/AZ167,"") -> 0.17311072 | BL167: =IFERROR(AI167+K167+S167+AA167-F167,"") -> 0 | BM167: =IFERROR(F167+G167-C167,"") -> 0 | BN167: =IF(I167="","",IFERROR(C167*1000/H167-I167,"")) -> 0.14271449
A168: 2405900 | B168: João Dias | C168: 27991 | D168: 28717 | E168: 33800 | F168: 27290 | G168: 700 | H168: 2653 | I168: 10550.56 | J168: 16281.41 | K168: 560 | L168: =IFERROR(K168/F168,"") -> 0.020520337 | M168: =IFERROR(K168*1000/H168,"") -> 211.08179 | N168: =IF(L168="","",RANK(L168,$L$3:$L$168,0)+COUNTIF($L$3:L168,L168)-1) -> 163 | O168: =IF(K168="","",RANK(K168,$K$3:$K$168,0)+COUNTIF($K$3:K168,K168)-1) -> 166 | P168: 3 | Q168: =IFERROR(P168/AR168,"") -> 0.025862069 | R168: 2 | S168: 5316 | T168: =IFERROR(S168/F168,"") -> 0.19479663 | U168: =IFERROR(S168*1000/H168,"") -> 2003.7693 | V168: =IF(T168="","",RANK(T168,$T$3:$T$168,0)+COUNTIF($T$3:T168,T168)-1) -> 147 | W168: =IF(S168="","",RANK(S168,$S$3:$S$168,0)+COUNTIF($S$3:S168,S168)-1) -> 166 | X168: 25 | Y168: 80 | Z168: =IFERROR((X168+Y168)/AR168,"") -> 0.90517241 | AA168: 19827 | AB168: =IFERROR(AA168/F168,"") -> 0.72652986 | AC168: =IFERROR(AA168*1000/H168,"") -> 7473.4263 | AD168: =IF(AB168="","",RANK(AB168,$AB$3:$AB$168,0)+COUNTIF($AB$3:AB168,AB168)-1) -> 1 | AE168: =IF(AA168="","",RANK(AA168,$AA$3:$AA$168,0)+COUNTIF($AA$3:AA168,AA168)-1) -> 165 | AF168: 98.01 | AG168: 30154072 | AH168: =IFERROR(AG168/AZ168,"") -> 14525.083 | AI168: 1587 | AJ168: =IFERROR(AI168/F168,"") -> 0.05815317 | AK168: 37 | AL168: 45 | AM168: 45 | AN168: 366 | AO168: 344 | AP168: 0.9 | AQ168: =IFERROR(AL168*1000/AZ168,"") -> 21.676301 | AR168: 116 | AS168: 63 | AT168: 14 | AU168: 3 | AV168: 36 | AW168: =IFERROR(AS168/AR168,"") -> 0.54310345 | AX168: 1 | AY168: 7 | AZ168: 2076 | BA168: 88.173 | BB168: 23.54 | BC168: 0.53 | BD168: 61.4 | BE168: 100 | BF168: 4.6 | BG168: 4.8 | BH168: 18.75 | BI168: 366 | BJ168: 0.9 | BK168: =IFERROR(BI168/AZ168,"") -> 0.17630058 | BL168: =IFERROR(AI168+K168+S168+AA168-F168,"") -> 0 | BM168: =IFERROR(F168+G168-C168,"") -> -1 | BN168: =IF(I168="","",IFERROR(C168*1000/H168-I168,"")) -> 0.13732378
A169: 2414902 | B169: Viçosa | C169: 23238 | D169: 25575 | E169: 29717 | F169: 22324 | G169: 914 | H169: 1731 | I169: 13424.72 | J169: 16309.97 | K169: 879 | L169: =IFERROR(K169/F169,"") -> 0.039374664 | M169: =IFERROR(K169*1000/H169,"") -> 507.79896 | N169: =IF(L169="","",RANK(L169,$L$3:$L$168,0)+COUNTIF($L$3:L169,L169)-1) -> #N/A | O169: =IF(K169="","",RANK(K169,$K$3:$K$168,0)+COUNTIF($K$3:K169,K169)-1) -> #N/A | P169: 4 | Q169: =IFERROR(P169/AR169,"") -> 0.037735849 | R169: 0 | S169: 5477 | T169: =IFERROR(S169/F169,"") -> 0.24534134 | U169: =IFERROR(S169*1000/H169,"") -> 3164.067 | V169: =IF(T169="","",RANK(T169,$T$3:$T$168,0)+COUNTIF($T$3:T169,T169)-1) -> #N/A | W169: =IF(S169="","",RANK(S169,$S$3:$S$168,0)+COUNTIF($S$3:S169,S169)-1) -> #N/A | X169: 35 | Y169: 59 | Z169: =IFERROR((X169+Y169)/AR169,"") -> 0.88679245 | AA169: 14892 | AB169: =IFERROR(AA169/F169,"") -> 0.66708475 | AC169: =IFERROR(AA169*1000/H169,"") -> 8603.1196 | AD169: =IF(AB169="","",RANK(AB169,$AB$3:$AB$168,0)+COUNTIF($AB$3:AB169,AB169)-1) -> #N/A | AE169: =IF(AA169="","",RANK(AA169,$AA$3:$AA$168,0)+COUNTIF($AA$3:AA169,AA169)-1) -> #N/A | AF169: 95.78 | AG169: 31347370 | AH169: =IFERROR(AG169/AZ169,"") -> 17204.923 | AI169: 1075 | AJ169: =IFERROR(AI169/F169,"") -> 0.048154453 | AK169: 52 | AL169: 55 | AM169: 56 | AN169: 161 | AO169: 129 | AP169: 1.8 | AQ169: =IFERROR(AL169*1000/AZ169,"") -> 30.186608 | AR169: 106 | AS169: 41 | AT169: 21 | AU169: 3 | AV169: 41 | AW169: =IFERROR(AS169/AR169,"") -> 0.38679245 | AX169: 0 | AY169: 8 | AZ169: 1822 | BA169: 37.905 | BB169: 48.07 | BC169: 0.592 | BD169: 53.5 | BE169: 100 | BF169: 6.4 | BG169: 4.8 | BH169: 95.83 | BI169: 161 | BJ169: 1.8 | BK169: =IFERROR(BI169/AZ169,"") -> 0.088364435 | BL169: =IFERROR(AI169+K169+S169+AA169-F169,"") -> -1 | BM169: =IFERROR(F169+G169-C169,"") -> 0 | BN169: =IF(I169="","",IFERROR(C169*1000/H169-I169,"")) -> -0.10994801
A171: Azul = dado importado da fonte; preto = fórmula. Passe o mouse no cabeçalho para ver a fonte de cada coluna. Linha do RN: valores oficiais do estado (IBGE) e somas (Sebrae). Células vazias = dado inexistente, sigiloso ("X") ou não disponível na fonte.

Sheet Ranking_Setores
A1: Top 15 municípios do RN por setor – VAB 2021 (fórmulas ligadas à aba Municipios_RN)
A2: Participação % = peso do setor no VAB do próprio município (especialização). VAB absoluto = tamanho da economia setorial.
A4: INDÚSTRIA – por participação no VAB municipal | G4: INDÚSTRIA – por VAB absoluto
A5: # | B5: Município | C5: VAB (mil R$) | D5: Part. % | E5: PIB per capita 2021 (R$) | G5: # | H5: Município | I5: VAB (mil R$) | J5: Part. % | K5: PIB per capita 2021 (R$)
A6: 1 | B6: =INDEX(Municipios_RN!$B$3:$B$168,MATCH(A6,Municipios_RN!$N$3:$N$168,0)) -> São Bento do Norte | C6: =INDEX(Municipios_RN!$K$3:$K$168,MATCH(A6,Municipios_RN!$N$3:$N$168,0)) -> 452181 | D6: =INDEX(Municipios_RN!$L$3:$L$168,MATCH(A6,Municipios_RN!$N$3:$N$168,0)) -> 0.8874281 | E6: =INDEX(Municipios_RN!$I$3:$I$168,MATCH(A6,Municipios_RN!$N$3:$N$168,0)) -> 204406.89 | G6: 1 | H6: =INDEX(Municipios_RN!$B$3:$B$168,MATCH(G6,Municipios_RN!$O$3:$O$168,0)) -> Natal | I6: =INDEX(Municipios_RN!$K$3:$K$168,MATCH(G6,Municipios_RN!$O$3:$O$168,0)) -> 2556518 | J6: =INDEX(Municipios_RN!$L$3:$L$168,MATCH(G6,Municipios_RN!$O$3:$O$168,0)) -> 0.12305445 | K6: =INDEX(Municipios_RN!$I$3:$I$168,MATCH(G6,Municipios_RN!$O$3:$O$168,0)) -> 26972.15
A7: 2 | B7: =INDEX(Municipios_RN!$B$3:$B$168,MATCH(A7,Municipios_RN!$N$3:$N$168,0)) -> Parazinho | C7: =INDEX(Municipios_RN!$K$3:$K$168,MATCH(A7,Municipios_RN!$N$3:$N$168,0)) -> 528052 | D7: =INDEX(Municipios_RN!$L$3:$L$168,MATCH(A7,Municipios_RN!$N$3:$N$168,0)) -> 0.88741673 | E7: =INDEX(Municipios_RN!$I$3:$I$168,MATCH(A7,Municipios_RN!$N$3:$N$168,0)) -> 114233.9 | G7: 2 | H7: =INDEX(Municipios_RN!$B$3:$B$168,MATCH(G7,Municipios_RN!$O$3:$O$168,0)) -> Guamaré | I7: =INDEX(Municipios_RN!$K$3:$K$168,MATCH(G7,Municipios_RN!$O$3:$O$168,0)) -> 1471020 | J7: =INDEX(Municipios_RN!$L$3:$L$168,MATCH(G7,Municipios_RN!$O$3:$O$168,0)) -> 0.74999924 | K7: =INDEX(Municipios_RN!$I$3:$I$168,MATCH(G7,Municipios_RN!$O$3:$O$168,0)) -> 125584.68
A8: 3 | B8: =INDEX(Municipios_RN!$B$3:$B$168,MATCH(A8,Municipios_RN!$N$3:$N$168,0)) -> Bodó | C8: =INDEX(Municipios_RN!$K$3:$K$168,MATCH(A8,Municipios_RN!$N$3:$N$168,0)) -> 246251 | D8: =INDEX(Municipios_RN!$L$3:$L$168,MATCH(A8,Municipios_RN!$N$3:$N$168,0)) -> 0.86714205 | E8: =INDEX(Municipios_RN!$I$3:$I$168,MATCH(A8,Municipios_RN!$N$3:$N$168,0)) -> 132000.71 | G8: 3 | H8: =INDEX(Municipios_RN!$B$3:$B$168,MATCH(G8,Municipios_RN!$O$3:$O$168,0)) -> Mossoró | I8: =INDEX(Municipios_RN!$K$3:$K$168,MATCH(G8,Municipios_RN!$O$3:$O$168,0)) -> 1285190 | J8: =INDEX(Municipios_RN!$L$3:$L$168,MATCH(G8,Municipios_RN!$O$3:$O$168,0)) -> 0.18630159 | K8: =INDEX(Municipios_RN!$I$3:$I$168,MATCH(G8,Municipios_RN!$O$3:$O$168,0)) -> 26569.89
A9: 4 | B9: =INDEX(Municipios_RN!$B$3:$B$168,MATCH(A9,Municipios_RN!$N$3:$N$168,0)) -> Pedra Grande | C9: =INDEX(Municipios_RN!$K$3:$K$168,MATCH(A9,Municipios_RN!$N$3:$N$168,0)) -> 213403 | D9: =INDEX(Municipios_RN!$L$3:$L$168,MATCH(A9,Municipios_RN!$N$3:$N$168,0)) -> 0.78084934 | E9: =INDEX(Municipios_RN!$I$3:$I$168,MATCH(A9,Municipios_RN!$N$3:$N$168,0)) -> 92722.93 | G9: 4 | H9: =INDEX(Municipios_RN!$B$3:$B$168,MATCH(G9,Municipios_RN!$O$3:$O$168,0)) -> João Câmara | I9: =INDEX(Municipios_RN!$K$3:$K$168,MATCH(G9,Municipios_RN!$O$3:$O$168,0)) -> 712023 | J9: =INDEX(Municipios_RN!$L$3:$L$168,MATCH(G9,Municipios_RN!$O$3:$O$168,0)) -> 0.59439616 | K9: =INDEX(Municipios_RN!$I$3:$I$168,MATCH(G9,Municipios_RN!$O$3:$O$168,0)) -> 35911.56
A10: 5 | B10: =INDEX(Municipios_RN!$B$3:$B$168,MATCH(A10,Municipios_RN!$N$3:$N$168,0)) -> Guamaré | C10: =INDEX(Municipios_RN!$K$3:$K$168,MATCH(A10,Municipios_RN!$N$3:$N$168,0)) -> 1471020 | D10: =INDEX(Municipios_RN!$L$3:$L$168,MATCH(A10,Municipios_RN!$N$3:$N$168,0)) -> 0.74999924 | E10: =INDEX(Municipios_RN!$I$3:$I$168,MATCH(A10,Municipios_RN!$N$3:$N$168,0)) -> 125584.68 | G10: 5 | H10: =INDEX(Municipios_RN!$B$3:$B$168,MATCH(G10,Municipios_RN!$O$3:$O$168,0)) -> Parnamirim | I10: =INDEX(Municipios_RN!$K$3:$K$168,MATCH(G10,Municipios_RN!$O$3:$O$168,0)) -> 577662 | J10: =INDEX(Municipios_RN!$L$3:$L$168,MATCH(G10,Municipios_RN!$O$3:$O$168,0)) -> 0.10165973 | K10: =INDEX(Municipios_RN!$I$3:$I$168,MATCH(G10,Municipios_RN!$O$3:$O$168,0)) -> 25121.5
A11: 6 | B11: =INDEX(Municipios_RN!$B$3:$B$168,MATCH(A11,Municipios_RN!$N$3:$N$168,0)) -> Serra do Mel | C11: =INDEX(Municipios_RN!$K$3:$K$168,MATCH(A11,Municipios_RN!$N$3:$N$168,0)) -> 565336 | D11: =INDEX(Municipios_RN!$L$3:$L$168,MATCH(A11,Municipios_RN!$N$3:$N$168,0)) -> 0.73239539 | E11: =INDEX(Municipios_RN!$I$3:$I$168,MATCH(A11,Municipios_RN!$N$3:$N$168,0)) -> 70243 | G11: 6 | H11: =INDEX(Municipios_RN!$B$3:$B$168,MATCH(G11,Municipios_RN!$O$3:$O$168,0)) -> Serra do Mel | I11: =INDEX(Municipios_RN!$K$3:$K$168,MATCH(G11,Municipios_RN!$O$3:$O$168,0)) -> 565336 | J11: =INDEX(Municipios_RN!$L$3:$L$168,MATCH(G11,Municipios_RN!$O$3:$O$168,0)) -> 0.73239539 | K11: =INDEX(Municipios_RN!$I$3:$I$168,MATCH(G11,Municipios_RN!$O$3:$O$168,0)) -> 70243
A12: 7 | B12: =INDEX(Municipios_RN!$B$3:$B$168,MATCH(A12,Municipios_RN!$N$3:$N$168,0)) -> Ruy Barbosa | C12: =INDEX(Municipios_RN!$K$3:$K$168,MATCH(A12,Municipios_RN!$N$3:$N$168,0)) -> 84829 | D12: =INDEX(Municipios_RN!$L$3:$L$168,MATCH(A12,Municipios_RN!$N$3:$N$168,0)) -> 0.68346547 | E12: =INDEX(Municipios_RN!$I$3:$I$168,MATCH(A12,Municipios_RN!$N$3:$N$168,0)) -> 35371.66 | G12: 7 | H12: =INDEX(Municipios_RN!$B$3:$B$168,MATCH(G12,Municipios_RN!$O$3:$O$168,0)) -> Macau | I12: =INDEX(Municipios_RN!$K$3:$K$168,MATCH(G12,Municipios_RN!$O$3:$O$168,0)) -> 546975 | J12: =INDEX(Municipios_RN!$L$3:$L$168,MATCH(G12,Municipios_RN!$O$3:$O$168,0)) -> 0.5132831 | K12: =INDEX(Municipios_RN!$I$3:$I$168,MATCH(G12,Municipios_RN!$O$3:$O$168,0)) -> 34442.58
A13: 8 | B13: =INDEX(Municipios_RN!$B$3:$B$168,MATCH(A13,Municipios_RN!$N$3:$N$168,0)) -> São Miguel do Gostoso | C13: =INDEX(Municipios_RN!$K$3:$K$168,MATCH(A13,Municipios_RN!$N$3:$N$168,0)) -> 310242 | D13: =INDEX(Municipios_RN!$L$3:$L$168,MATCH(A13,Municipios_RN!$N$3:$N$168,0)) -> 0.66665521 | E13: =INDEX(Municipios_RN!$I$3:$I$168,MATCH(A13,Municipios_RN!$N$3:$N$168,0)) -> 47182.94 | G13: 8 | H13: =INDEX(Municipios_RN!$B$3:$B$168,MATCH(G13,Municipios_RN!$O$3:$O$168,0)) -> Parazinho | I13: =INDEX(Municipios_RN!$K$3:$K$168,MATCH(G13,Municipios_RN!$O$3:$O$168,0)) -> 528052 | J13: =INDEX(Municipios_RN!$L$3:$L$168,MATCH(G13,Municipios_RN!$O$3:$O$168,0)) -> 0.88741673 | K13: =INDEX(Municipios_RN!$I$3:$I$168,MATCH(G13,Municipios_RN!$O$3:$O$168,0)) -> 114233.9
A14: 9 | B14: =INDEX(Municipios_RN!$B$3:$B$168,MATCH(A14,Municipios_RN!$N$3:$N$168,0)) -> João Câmara | C14: =INDEX(Municipios_RN!$K$3:$K$168,MATCH(A14,Municipios_RN!$N$3:$N$168,0)) -> 712023 | D14: =INDEX(Municipios_RN!$L$3:$L$168,MATCH(A14,Municipios_RN!$N$3:$N$168,0)) -> 0.59439616 | E14: =INDEX(Municipios_RN!$I$3:$I$168,MATCH(A14,Municipios_RN!$N$3:$N$168,0)) -> 35911.56 | G14: 9 | H14: =INDEX(Municipios_RN!$B$3:$B$168,MATCH(G14,Municipios_RN!$O$3:$O$168,0)) -> Macaíba | I14: =INDEX(Municipios_RN!$K$3:$K$168,MATCH(G14,Municipios_RN!$O$3:$O$168,0)) -> 485851 | J14: =INDEX(Municipios_RN!$L$3:$L$168,MATCH(G14,Municipios_RN!$O$3:$O$168,0)) -> 0.31123386 | K14: =INDEX(Municipios_RN!$I$3:$I$168,MATCH(G14,Municipios_RN!$O$3:$O$168,0)) -> 22071.55
A15: 10 | B15: =INDEX(Municipios_RN!$B$3:$B$168,MATCH(A15,Municipios_RN!$N$3:$N$168,0)) -> Alto do Rodrigues | C15: =INDEX(Municipios_RN!$K$3:$K$168,MATCH(A15,Municipios_RN!$N$3:$N$168,0)) -> 304515 | D15: =INDEX(Municipios_RN!$L$3:$L$168,MATCH(A15,Municipios_RN!$N$3:$N$168,0)) -> 0.52828483 | E15: =INDEX(Municipios_RN!$I$3:$I$168,MATCH(A15,Municipios_RN!$N$3:$N$168,0)) -> 41300.16 | G15: 10 | H15: =INDEX(Municipios_RN!$B$3:$B$168,MATCH(G15,Municipios_RN!$O$3:$O$168,0)) -> Assú | I15: =INDEX(Municipios_RN!$K$3:$K$168,MATCH(G15,Municipios_RN!$O$3:$O$168,0)) -> 483176 | J15: =INDEX(Municipios_RN!$L$3:$L$168,MATCH(G15,Municipios_RN!$O$3:$O$168,0)) -> 0.35316372 | K15: =INDEX(Municipios_RN!$I$3:$I$168,MATCH(G15,Municipios_RN!$O$3:$O$168,0)) -> 24982.76
A16: 11 | B16: =INDEX(Municipios_RN!$B$3:$B$168,MATCH(A16,Municipios_RN!$N$3:$N$168,0)) -> Macau | C16: =INDEX(Municipios_RN!$K$3:$K$168,MATCH(A16,Municipios_RN!$N$3:$N$168,0)) -> 546975 | D16: =INDEX(Municipios_RN!$L$3:$L$168,MATCH(A16,Municipios_RN!$N$3:$N$168,0)) -> 0.5132831 | E16: =INDEX(Municipios_RN!$I$3:$I$168,MATCH(A16,Municipios_RN!$N$3:$N$168,0)) -> 34442.58 | G16: 11 | H16: =INDEX(Municipios_RN!$B$3:$B$168,MATCH(G16,Municipios_RN!$O$3:$O$168,0)) -> São Bento do Norte | I16: =INDEX(Municipios_RN!$K$3:$K$168,MATCH(G16,Municipios_RN!$O$3:$O$168,0)) -> 452181 | J16: =INDEX(Municipios_RN!$L$3:$L$168,MATCH(G16,Municipios_RN!$O$3:$O$168,0)) -> 0.8874281 | K16: =INDEX(Municipios_RN!$I$3:$I$168,MATCH(G16,Municipios_RN!$O$3:$O$168,0)) -> 204406.89
A17: 12 | B17: =INDEX(Municipios_RN!$B$3:$B$168,MATCH(A17,Municipios_RN!$N$3:$N$168,0)) -> Galinhos | C17: =INDEX(Municipios_RN!$K$3:$K$168,MATCH(A17,Municipios_RN!$N$3:$N$168,0)) -> 78754 | D17: =INDEX(Municipios_RN!$L$3:$L$168,MATCH(A17,Municipios_RN!$N$3:$N$168,0)) -> 0.51274806 | E17: =INDEX(Municipios_RN!$I$3:$I$168,MATCH(A17,Municipios_RN!$N$3:$N$168,0)) -> 56016.48 | G17: 12 | H17: =INDEX(Municipios_RN!$B$3:$B$168,MATCH(G17,Municipios_RN!$O$3:$O$168,0)) -> Areia Branca | I17: =INDEX(Municipios_RN!$K$3:$K$168,MATCH(G17,Municipios_RN!$O$3:$O$168,0)) -> 388193 | J17: =INDEX(Municipios_RN!$L$3:$L$168,MATCH(G17,Municipios_RN!$O$3:$O$168,0)) -> 0.45332703 | K17: =INDEX(Municipios_RN!$I$3:$I$168,MATCH(G17,Municipios_RN!$O$3:$O$168,0)) -> 33242.23
... A20: 15 | B20: =INDEX(Municipios_RN!$B$3:$B$168,MATCH(A20,Municipios_RN!$N$3:$N$168,0)) -> Governador Dix-Sept Rosado | C20: =INDEX(Municipios_RN!$K$3:$K$168,MATCH(A20,Municipios_RN!$N$3:$N$168,0)) -> 171946 | D20: =INDEX(Municipios_RN!$L$3:$L$168,MATCH(A20,Municipios_RN!$N$3:$N$168,0)) -> 0.4674567 | E20: =INDEX(Municipios_RN!$I$3:$I$168,MATCH(A20,Municipios_RN!$N$3:$N$168,0)) -> 29451.69 | G20: 15 | H20: =INDEX(Municipios_RN!$B$3:$B$168,MATCH(G20,Municipios_RN!$O$3:$O$168,0)) -> Touros | I20: =INDEX(Municipios_RN!$K$3:$K$168,MATCH(G20,Municipios_RN!$O$3:$O$168,0)) -> 286754 | J20: =INDEX(Municipios_RN!$L$3:$L$168,MATCH(G20,Municipios_RN!$O$3:$O$168,0)) -> 0.37390097 | K20: =INDEX(Municipios_RN!$I$3:$I$168,MATCH(G20,Municipios_RN!$O$3:$O$168,0)) -> 24167.69
A23: SERVIÇOS – por participação no VAB municipal | G23: SERVIÇOS – por VAB absoluto
A24: # | B24: Município | C24: VAB (mil R$) | D24: Part. % | E24: PIB per capita 2021 (R$) | G24: # | H24: Município | I24: VAB (mil R$) | J24: Part. % | K24: PIB per capita 2021 (R$)
A25: 1 | B25: =INDEX(Municipios_RN!$B$3:$B$168,MATCH(A25,Municipios_RN!$V$3:$V$168,0)) -> Natal | C25: =INDEX(Municipios_RN!$S$3:$S$168,MATCH(A25,Municipios_RN!$V$3:$V$168,0)) -> 13347894 | D25: =INDEX(Municipios_RN!$T$3:$T$168,MATCH(A25,Municipios_RN!$V$3:$V$168,0)) -> 0.64248238 | E25: =INDEX(Municipios_RN!$I$3:$I$168,MATCH(A25,Municipios_RN!$V$3:$V$168,0)) -> 26972.15 | G25: 1 | H25: =INDEX(Municipios_RN!$B$3:$B$168,MATCH(G25,Municipios_RN!$W$3:$W$168,0)) -> Natal | I25: =INDEX(Municipios_RN!$S$3:$S$168,MATCH(G25,Municipios_RN!$W$3:$W$168,0)) -> 13347894 | J25: =INDEX(Municipios_RN!$T$3:$T$168,MATCH(G25,Municipios_RN!$W$3:$W$168,0)) -> 0.64248238 | K25: =INDEX(Municipios_RN!$I$3:$I$168,MATCH(G25,Municipios_RN!$W$3:$W$168,0)) -> 26972.15
A26: 2 | B26: =INDEX(Municipios_RN!$B$3:$B$168,MATCH(A26,Municipios_RN!$V$3:$V$168,0)) -> Pau dos Ferros | C26: =INDEX(Municipios_RN!$S$3:$S$168,MATCH(A26,Municipios_RN!$V$3:$V$168,0)) -> 389068 | D26: =INDEX(Municipios_RN!$T$3:$T$168,MATCH(A26,Municipios_RN!$V$3:$V$168,0)) -> 0.63507205 | E26: =INDEX(Municipios_RN!$I$3:$I$168,MATCH(A26,Municipios_RN!$V$3:$V$168,0)) -> 23028.64 | G26: 2 | H26: =INDEX(Municipios_RN!$B$3:$B$168,MATCH(G26,Municipios_RN!$W$3:$W$168,0)) -> Mossoró | I26: =INDEX(Municipios_RN!$S$3:$S$168,MATCH(G26,Municipios_RN!$W$3:$W$168,0)) -> 3766138 | J26: =INDEX(Municipios_RN!$T$3:$T$168,MATCH(G26,Municipios_RN!$W$3:$W$168,0)) -> 0.54594069 | K26: =INDEX(Municipios_RN!$I$3:$I$168,MATCH(G26,Municipios_RN!$W$3:$W$168,0)) -> 26569.89
A27: 3 | B27: =INDEX(Municipios_RN!$B$3:$B$168,MATCH(A27,Municipios_RN!$V$3:$V$168,0)) -> Parnamirim | C27: =INDEX(Municipios_RN!$S$3:$S$168,MATCH(A27,Municipios_RN!$V$3:$V$168,0)) -> 3470184 | D27: =INDEX(Municipios_RN!$T$3:$T$168,MATCH(A27,Municipios_RN!$V$3:$V$168,0)) -> 0.61069963 | E27: =INDEX(Municipios_RN!$I$3:$I$168,MATCH(A27,Municipios_RN!$V$3:$V$168,0)) -> 25121.5 | G27: 3 | H27: =INDEX(Municipios_RN!$B$3:$B$168,MATCH(G27,Municipios_RN!$W$3:$W$168,0)) -> Parnamirim | I27: =INDEX(Municipios_RN!$S$3:$S$168,MATCH(G27,Municipios_RN!$W$3:$W$168,0)) -> 3470184 | J27: =INDEX(Municipios_RN!$T$3:$T$168,MATCH(G27,Municipios_RN!$W$3:$W$168,0)) -> 0.61069963 | K27: =INDEX(Municipios_RN!$I$3:$I$168,MATCH(G27,Municipios_RN!$W$3:$W$168,0)) -> 25121.5
A28: 4 | B28: =INDEX(Municipios_RN!$B$3:$B$168,MATCH(A28,Municipios_RN!$V$3:$V$168,0)) -> Tibau do Sul | C28: =INDEX(Municipios_RN!$S$3:$S$168,MATCH(A28,Municipios_RN!$V$3:$V$168,0)) -> 228062 | D28: =INDEX(Municipios_RN!$T$3:$T$168,MATCH(A28,Municipios_RN!$V$3:$V$168,0)) -> 0.59719916 | E28: =INDEX(Municipios_RN!$I$3:$I$168,MATCH(A28,Municipios_RN!$V$3:$V$168,0)) -> 28299.21 | G28: 4 | H28: =INDEX(Municipios_RN!$B$3:$B$168,MATCH(G28,Municipios_RN!$W$3:$W$168,0)) -> São Gonçalo do Amarante | I28: =INDEX(Municipios_RN!$S$3:$S$168,MATCH(G28,Municipios_RN!$W$3:$W$168,0)) -> 878071 | J28: =INDEX(Municipios_RN!$T$3:$T$168,MATCH(G28,Municipios_RN!$W$3:$W$168,0)) -> 0.5241708 | K28: =INDEX(Municipios_RN!$I$3:$I$168,MATCH(G28,Municipios_RN!$W$3:$W$168,0)) -> 18162.97
A29: 5 | B29: =INDEX(Municipios_RN!$B$3:$B$168,MATCH(A29,Municipios_RN!$V$3:$V$168,0)) -> Caicó | C29: =INDEX(Municipios_RN!$S$3:$S$168,MATCH(A29,Municipios_RN!$V$3:$V$168,0)) -> 687110 | D29: =INDEX(Municipios_RN!$T$3:$T$168,MATCH(A29,Municipios_RN!$V$3:$V$168,0)) -> 0.56572145 | E29: =INDEX(Municipios_RN!$I$3:$I$168,MATCH(A29,Municipios_RN!$V$3:$V$168,0)) -> 20295.64 | G29: 5 | H29: =INDEX(Municipios_RN!$B$3:$B$168,MATCH(G29,Municipios_RN!$W$3:$W$168,0)) -> Caicó | I29: =INDEX(Municipios_RN!$S$3:$S$168,MATCH(G29,Municipios_RN!$W$3:$W$168,0)) -> 687110 | J29: =INDEX(Municipios_RN!$T$3:$T$168,MATCH(G29,Municipios_RN!$W$3:$W$168,0)) -> 0.56572145 | K29: =INDEX(Municipios_RN!$I$3:$I$168,MATCH(G29,Municipios_RN!$W$3:$W$168,0)) -> 20295.64
A30: 6 | B30: =INDEX(Municipios_RN!$B$3:$B$168,MATCH(A30,Municipios_RN!$V$3:$V$168,0)) -> Mossoró | C30: =INDEX(Municipios_RN!$S$3:$S$168,MATCH(A30,Municipios_RN!$V$3:$V$168,0)) -> 3766138 | D30: =INDEX(Municipios_RN!$T$3:$T$168,MATCH(A30,Municipios_RN!$V$3:$V$168,0)) -> 0.54594069 | E30: =INDEX(Municipios_RN!$I$3:$I$168,MATCH(A30,Municipios_RN!$V$3:$V$168,0)) -> 26569.89 | G30: 6 | H30: =INDEX(Municipios_RN!$B$3:$B$168,MATCH(G30,Municipios_RN!$W$3:$W$168,0)) -> Macaíba | I30: =INDEX(Municipios_RN!$S$3:$S$168,MATCH(G30,Municipios_RN!$W$3:$W$168,0)) -> 605895 | J30: =INDEX(Municipios_RN!$T$3:$T$168,MATCH(G30,Municipios_RN!$W$3:$W$168,0)) -> 0.38813348 | K30: =INDEX(Municipios_RN!$I$3:$I$168,MATCH(G30,Municipios_RN!$W$3:$W$168,0)) -> 22071.55
A31: 7 | B31: =INDEX(Municipios_RN!$B$3:$B$168,MATCH(A31,Municipios_RN!$V$3:$V$168,0)) -> São Gonçalo do Amarante | C31: =INDEX(Municipios_RN!$S$3:$S$168,MATCH(A31,Municipios_RN!$V$3:$V$168,0)) -> 878071 | D31: =INDEX(Municipios_RN!$T$3:$T$168,MATCH(A31,Municipios_RN!$V$3:$V$168,0)) -> 0.5241708 | E31: =INDEX(Municipios_RN!$I$3:$I$168,MATCH(A31,Municipios_RN!$V$3:$V$168,0)) -> 18162.97 | G31: 7 | H31: =INDEX(Municipios_RN!$B$3:$B$168,MATCH(G31,Municipios_RN!$W$3:$W$168,0)) -> Assú | I31: =INDEX(Municipios_RN!$S$3:$S$168,MATCH(G31,Municipios_RN!$W$3:$W$168,0)) -> 518977 | J31: =INDEX(Municipios_RN!$T$3:$T$168,MATCH(G31,Municipios_RN!$W$3:$W$168,0)) -> 0.37933144 | K31: =INDEX(Municipios_RN!$I$3:$I$168,MATCH(G31,Municipios_RN!$W$3:$W$168,0)) -> 24982.76
A32: 8 | B32: =INDEX(Municipios_RN!$B$3:$B$168,MATCH(A32,Municipios_RN!$V$3:$V$168,0)) -> Currais Novos | C32: =INDEX(Municipios_RN!$S$3:$S$168,MATCH(A32,Municipios_RN!$V$3:$V$168,0)) -> 364932 | D32: =INDEX(Municipios_RN!$T$3:$T$168,MATCH(A32,Municipios_RN!$V$3:$V$168,0)) -> 0.50896361 | E32: =INDEX(Municipios_RN!$I$3:$I$168,MATCH(A32,Municipios_RN!$V$3:$V$168,0)) -> 17862.92 | G32: 8 | H32: =INDEX(Municipios_RN!$B$3:$B$168,MATCH(G32,Municipios_RN!$W$3:$W$168,0)) -> São José de Mipibu | I32: =INDEX(Municipios_RN!$S$3:$S$168,MATCH(G32,Municipios_RN!$W$3:$W$168,0)) -> 435717 | J32: =INDEX(Municipios_RN!$T$3:$T$168,MATCH(G32,Municipios_RN!$W$3:$W$168,0)) -> 0.49587056 | K32: =INDEX(Municipios_RN!$I$3:$I$168,MATCH(G32,Municipios_RN!$W$3:$W$168,0)) -> 23357.62
A33: 9 | B33: =INDEX(Municipios_RN!$B$3:$B$168,MATCH(A33,Municipios_RN!$V$3:$V$168,0)) -> São José de Mipibu | C33: =INDEX(Municipios_RN!$S$3:$S$168,MATCH(A33,Municipios_RN!$V$3:$V$168,0)) -> 435717 | D33: =INDEX(Municipios_RN!$T$3:$T$168,MATCH(A33,Municipios_RN!$V$3:$V$168,0)) -> 0.49587056 | E33: =INDEX(Municipios_RN!$I$3:$I$168,MATCH(A33,Municipios_RN!$V$3:$V$168,0)) -> 23357.62 | G33: 9 | H33: =INDEX(Municipios_RN!$B$3:$B$168,MATCH(G33,Municipios_RN!$W$3:$W$168,0)) -> Pau dos Ferros | I33: =INDEX(Municipios_RN!$S$3:$S$168,MATCH(G33,Municipios_RN!$W$3:$W$168,0)) -> 389068 | J33: =INDEX(Municipios_RN!$T$3:$T$168,MATCH(G33,Municipios_RN!$W$3:$W$168,0)) -> 0.63507205 | K33: =INDEX(Municipios_RN!$I$3:$I$168,MATCH(G33,Municipios_RN!$W$3:$W$168,0)) -> 23028.64
A34: 10 | B34: =INDEX(Municipios_RN!$B$3:$B$168,MATCH(A34,Municipios_RN!$V$3:$V$168,0)) -> Santa Cruz | C34: =INDEX(Municipios_RN!$S$3:$S$168,MATCH(A34,Municipios_RN!$V$3:$V$168,0)) -> 268281 | D34: =INDEX(Municipios_RN!$T$3:$T$168,MATCH(A34,Municipios_RN!$V$3:$V$168,0)) -> 0.48134499 | E34: =INDEX(Municipios_RN!$I$3:$I$168,MATCH(A34,Municipios_RN!$V$3:$V$168,0)) -> 15362.6 | G34: 10 | H34: =INDEX(Municipios_RN!$B$3:$B$168,MATCH(G34,Municipios_RN!$W$3:$W$168,0)) -> Ceará-Mirim | I34: =INDEX(Municipios_RN!$S$3:$S$168,MATCH(G34,Municipios_RN!$W$3:$W$168,0)) -> 365315 | J34: =INDEX(Municipios_RN!$T$3:$T$168,MATCH(G34,Municipios_RN!$W$3:$W$168,0)) -> 0.4037714 | K34: =INDEX(Municipios_RN!$I$3:$I$168,MATCH(G34,Municipios_RN!$W$3:$W$168,0)) -> 13494.28
A35: 11 | B35: =INDEX(Municipios_RN!$B$3:$B$168,MATCH(A35,Municipios_RN!$V$3:$V$168,0)) -> Angicos | C35: =INDEX(Municipios_RN!$S$3:$S$168,MATCH(A35,Municipios_RN!$V$3:$V$168,0)) -> 78364 | D35: =INDEX(Municipios_RN!$T$3:$T$168,MATCH(A35,Municipios_RN!$V$3:$V$168,0)) -> 0.48035995 | E35: =INDEX(Municipios_RN!$I$3:$I$168,MATCH(A35,Municipios_RN!$V$3:$V$168,0)) -> 15405.14 | G35: 11 | H35: =INDEX(Municipios_RN!$B$3:$B$168,MATCH(G35,Municipios_RN!$W$3:$W$168,0)) -> Currais Novos | I35: =INDEX(Municipios_RN!$S$3:$S$168,MATCH(G35,Municipios_RN!$W$3:$W$168,0)) -> 364932 | J35: =INDEX(Municipios_RN!$T$3:$T$168,MATCH(G35,Municipios_RN!$W$3:$W$168,0)) -> 0.50896361 | K35: =INDEX(Municipios_RN!$I$3:$I$168,MATCH(G35,Municipios_RN!$W$3:$W$168,0)) -> 17862.92
A36: 12 | B36: =INDEX(Municipios_RN!$B$3:$B$168,MATCH(A36,Municipios_RN!$V$3:$V$168,0)) -> Nova Cruz | C36: =INDEX(Municipios_RN!$S$3:$S$168,MATCH(A36,Municipios_RN!$V$3:$V$168,0)) -> 234694 | D36: =INDEX(Municipios_RN!$T$3:$T$168,MATCH(A36,Municipios_RN!$V$3:$V$168,0)) -> 0.47641416 | E36: =INDEX(Municipios_RN!$I$3:$I$168,MATCH(A36,Municipios_RN!$V$3:$V$168,0)) -> 14925.04 | G36: 12 | H36: =INDEX(Municipios_RN!$B$3:$B$168,MATCH(G36,Municipios_RN!$W$3:$W$168,0)) -> Macau | I36: =INDEX(Municipios_RN!$S$3:$S$168,MATCH(G36,Municipios_RN!$W$3:$W$168,0)) -> 290912 | J36: =INDEX(Municipios_RN!$T$3:$T$168,MATCH(G36,Municipios_RN!$W$3:$W$168,0)) -> 0.27299276 | K36: =INDEX(Municipios_RN!$I$3:$I$168,MATCH(G36,Municipios_RN!$W$3:$W$168,0)) -> 34442.58
... A39: 15 | B39: =INDEX(Municipios_RN!$B$3:$B$168,MATCH(A39,Municipios_RN!$V$3:$V$168,0)) -> Patu | C39: =INDEX(Municipios_RN!$S$3:$S$168,MATCH(A39,Municipios_RN!$V$3:$V$168,0)) -> 64954 | D39: =INDEX(Municipios_RN!$T$3:$T$168,MATCH(A39,Municipios_RN!$V$3:$V$168,0)) -> 0.44203535 | E39: =INDEX(Municipios_RN!$I$3:$I$168,MATCH(A39,Municipios_RN!$V$3:$V$168,0)) -> 12511.61 | G39: 15 | H39: =INDEX(Municipios_RN!$B$3:$B$168,MATCH(G39,Municipios_RN!$W$3:$W$168,0)) -> Guamaré | I39: =INDEX(Municipios_RN!$S$3:$S$168,MATCH(G39,Municipios_RN!$W$3:$W$168,0)) -> 258287 | J39: =INDEX(Municipios_RN!$T$3:$T$168,MATCH(G39,Municipios_RN!$W$3:$W$168,0)) -> 0.13168757 | K39: =INDEX(Municipios_RN!$I$3:$I$168,MATCH(G39,Municipios_RN!$W$3:$W$168,0)) -> 125584.68
A42: ADMINISTRAÇÃO PÚBLICA – por participação no VAB municipal | G42: ADMINISTRAÇÃO PÚBLICA – por VAB absoluto
A43: # | B43: Município | C43: VAB (mil R$) | D43: Part. % | E43: PIB per capita 2021 (R$) | G43: # | H43: Município | I43: VAB (mil R$) | J43: Part. % | K43: PIB per capita 2021 (R$)
A44: 1 | B44: =INDEX(Municipios_RN!$B$3:$B$168,MATCH(A44,Municipios_RN!$AD$3:$AD$168,0)) -> João Dias | C44: =INDEX(Municipios_RN!$AA$3:$AA$168,MATCH(A44,Municipios_RN!$AD$3:$AD$168,0)) -> 19827 | D44: =INDEX(Municipios_RN!$AB$3:$AB$168,MATCH(A44,Municipios_RN!$AD$3:$AD$168,0)) -> 0.72652986 | E44: =INDEX(Municipios_RN!$I$3:$I$168,MATCH(A44,Municipios_RN!$AD$3:$AD$168,0)) -> 10550.56 | G44: 1 | H44: =INDEX(Municipios_RN!$B$3:$B$168,MATCH(G44,Municipios_RN!$AE$3:$AE$168,0)) -> Natal | I44: =INDEX(Municipios_RN!$AA$3:$AA$168,MATCH(G44,Municipios_RN!$AE$3:$AE$168,0)) -> 4851091 | J44: =INDEX(Municipios_RN!$AB$3:$AB$168,MATCH(G44,Municipios_RN!$AE$3:$AE$168,0)) -> 0.23350054 | K44: =INDEX(Municipios_RN!$I$3:$I$168,MATCH(G44,Municipios_RN!$AE$3:$AE$168,0)) -> 26972.15
A45: 2 | B45: =INDEX(Municipios_RN!$B$3:$B$168,MATCH(A45,Municipios_RN!$AD$3:$AD$168,0)) -> Venha-Ver | C45: =INDEX(Municipios_RN!$AA$3:$AA$168,MATCH(A45,Municipios_RN!$AD$3:$AD$168,0)) -> 30311 | D45: =INDEX(Municipios_RN!$AB$3:$AB$168,MATCH(A45,Municipios_RN!$AD$3:$AD$168,0)) -> 0.72391393 | E45: =INDEX(Municipios_RN!$I$3:$I$168,MATCH(A45,Municipios_RN!$AD$3:$AD$168,0)) -> 10208.37 | G45: 2 | H45: =INDEX(Municipios_RN!$B$3:$B$168,MATCH(G45,Municipios_RN!$AE$3:$AE$168,0)) -> Mossoró | I45: =INDEX(Municipios_RN!$AA$3:$AA$168,MATCH(G45,Municipios_RN!$AE$3:$AE$168,0)) -> 1662885 | J45: =INDEX(Municipios_RN!$AB$3:$AB$168,MATCH(G45,Municipios_RN!$AE$3:$AE$168,0)) -> 0.24105239 | K45: =INDEX(Municipios_RN!$I$3:$I$168,MATCH(G45,Municipios_RN!$AE$3:$AE$168,0)) -> 26569.89
A46: 3 | B46: =INDEX(Municipios_RN!$B$3:$B$168,MATCH(A46,Municipios_RN!$AD$3:$AD$168,0)) -> Campo Redondo | C46: =INDEX(Municipios_RN!$AA$3:$AA$168,MATCH(A46,Municipios_RN!$AD$3:$AD$168,0)) -> 73375 | D46: =INDEX(Municipios_RN!$AB$3:$AB$168,MATCH(A46,Municipios_RN!$AD$3:$AD$168,0)) -> 0.71041294 | E46: =INDEX(Municipios_RN!$I$3:$I$168,MATCH(A46,Municipios_RN!$AD$3:$AD$168,0)) -> 9413.46 | G46: 3 | H46: =INDEX(Municipios_RN!$B$3:$B$168,MATCH(G46,Municipios_RN!$AE$3:$AE$168,0)) -> Parnamirim | I46: =INDEX(Municipios_RN!$AA$3:$AA$168,MATCH(G46,Municipios_RN!$AE$3:$AE$168,0)) -> 1550432 | J46: =INDEX(Municipios_RN!$AB$3:$AB$168,MATCH(G46,Municipios_RN!$AE$3:$AE$168,0)) -> 0.27285246 | K46: =INDEX(Municipios_RN!$I$3:$I$168,MATCH(G46,Municipios_RN!$AE$3:$AE$168,0)) -> 25121.5
A47: 4 | B47: =INDEX(Municipios_RN!$B$3:$B$168,MATCH(A47,Municipios_RN!$AD$3:$AD$168,0)) -> Coronel João Pessoa | C47: =INDEX(Municipios_RN!$AA$3:$AA$168,MATCH(A47,Municipios_RN!$AD$3:$AD$168,0)) -> 33140 | D47: =INDEX(Municipios_RN!$AB$3:$AB$168,MATCH(A47,Municipios_RN!$AD$3:$AD$168,0)) -> 0.70966637 | E47: =INDEX(Municipios_RN!$I$3:$I$168,MATCH(A47,Municipios_RN!$AD$3:$AD$168,0)) -> 9793.87 | G47: 4 | H47: =INDEX(Municipios_RN!$B$3:$B$168,MATCH(G47,Municipios_RN!$AE$3:$AE$168,0)) -> São Gonçalo do Amarante | I47: =INDEX(Municipios_RN!$AA$3:$AA$168,MATCH(G47,Municipios_RN!$AE$3:$AE$168,0)) -> 589005 | J47: =INDEX(Municipios_RN!$AB$3:$AB$168,MATCH(G47,Municipios_RN!$AE$3:$AE$168,0)) -> 0.35161077 | K47: =INDEX(Municipios_RN!$I$3:$I$168,MATCH(G47,Municipios_RN!$AE$3:$AE$168,0)) -> 18162.97
A48: 5 | B48: =INDEX(Municipios_RN!$B$3:$B$168,MATCH(A48,Municipios_RN!$AD$3:$AD$168,0)) -> Jundiá | C48: =INDEX(Municipios_RN!$AA$3:$AA$168,MATCH(A48,Municipios_RN!$AD$3:$AD$168,0)) -> 29090 | D48: =INDEX(Municipios_RN!$AB$3:$AB$168,MATCH(A48,Municipios_RN!$AD$3:$AD$168,0)) -> 0.70778589 | E48: =INDEX(Municipios_RN!$I$3:$I$168,MATCH(A48,Municipios_RN!$AD$3:$AD$168,0)) -> 10683.63 | G48: 5 | H48: =INDEX(Municipios_RN!$B$3:$B$168,MATCH(G48,Municipios_RN!$AE$3:$AE$168,0)) -> Macaíba | I48: =INDEX(Municipios_RN!$AA$3:$AA$168,MATCH(G48,Municipios_RN!$AE$3:$AE$168,0)) -> 433168 | J48: =INDEX(Municipios_RN!$AB$3:$AB$168,MATCH(G48,Municipios_RN!$AE$3:$AE$168,0)) -> 0.27748538 | K48: =INDEX(Municipios_RN!$I$3:$I$168,MATCH(G48,Municipios_RN!$AE$3:$AE$168,0)) -> 22071.55
A49: 6 | B49: =INDEX(Municipios_RN!$B$3:$B$168,MATCH(A49,Municipios_RN!$AD$3:$AD$168,0)) -> Luís Gomes | C49: =INDEX(Municipios_RN!$AA$3:$AA$168,MATCH(A49,Municipios_RN!$AD$3:$AD$168,0)) -> 59670 | D49: =INDEX(Municipios_RN!$AB$3:$AB$168,MATCH(A49,Municipios_RN!$AD$3:$AD$168,0)) -> 0.70653847 | E49: =INDEX(Municipios_RN!$I$3:$I$168,MATCH(A49,Municipios_RN!$AD$3:$AD$168,0)) -> 8631.46 | G49: 6 | H49: =INDEX(Municipios_RN!$B$3:$B$168,MATCH(G49,Municipios_RN!$AE$3:$AE$168,0)) -> Ceará-Mirim | I49: =INDEX(Municipios_RN!$AA$3:$AA$168,MATCH(G49,Municipios_RN!$AE$3:$AE$168,0)) -> 419272 | J49: =INDEX(Municipios_RN!$AB$3:$AB$168,MATCH(G49,Municipios_RN!$AE$3:$AE$168,0)) -> 0.46340841 | K49: =INDEX(Municipios_RN!$I$3:$I$168,MATCH(G49,Municipios_RN!$AE$3:$AE$168,0)) -> 13494.28
A50: 7 | B50: =INDEX(Municipios_RN!$B$3:$B$168,MATCH(A50,Municipios_RN!$AD$3:$AD$168,0)) -> Paraná | C50: =INDEX(Municipios_RN!$AA$3:$AA$168,MATCH(A50,Municipios_RN!$AD$3:$AD$168,0)) -> 29928 | D50: =INDEX(Municipios_RN!$AB$3:$AB$168,MATCH(A50,Municipios_RN!$AD$3:$AD$168,0)) -> 0.70390667 | E50: =INDEX(Municipios_RN!$I$3:$I$168,MATCH(A50,Municipios_RN!$AD$3:$AD$168,0)) -> 10221.11 | G50: 7 | H50: =INDEX(Municipios_RN!$B$3:$B$168,MATCH(G50,Municipios_RN!$AE$3:$AE$168,0)) -> Caicó | I50: =INDEX(Municipios_RN!$AA$3:$AA$168,MATCH(G50,Municipios_RN!$AE$3:$AE$168,0)) -> 392190 | J50: =INDEX(Municipios_RN!$AB$3:$AB$168,MATCH(G50,Municipios_RN!$AE$3:$AE$168,0)) -> 0.3229036 | K50: =INDEX(Municipios_RN!$I$3:$I$168,MATCH(G50,Municipios_RN!$AE$3:$AE$168,0)) -> 20295.64
A51: 8 | B51: =INDEX(Municipios_RN!$B$3:$B$168,MATCH(A51,Municipios_RN!$AD$3:$AD$168,0)) -> São Bento do Trairí | C51: =INDEX(Municipios_RN!$AA$3:$AA$168,MATCH(A51,Municipios_RN!$AD$3:$AD$168,0)) -> 30965 | D51: =INDEX(Municipios_RN!$AB$3:$AB$168,MATCH(A51,Municipios_RN!$AD$3:$AD$168,0)) -> 0.69961591 | E51: =INDEX(Municipios_RN!$I$3:$I$168,MATCH(A51,Municipios_RN!$AD$3:$AD$168,0)) -> 10046.8 | G51: 8 | H51: =INDEX(Municipios_RN!$B$3:$B$168,MATCH(G51,Municipios_RN!$AE$3:$AE$168,0)) -> Assú | I51: =INDEX(Municipios_RN!$AA$3:$AA$168,MATCH(G51,Municipios_RN!$AE$3:$AE$168,0)) -> 330939 | J51: =INDEX(Municipios_RN!$AB$3:$AB$168,MATCH(G51,Municipios_RN!$AE$3:$AE$168,0)) -> 0.24189043 | K51: =INDEX(Municipios_RN!$I$3:$I$168,MATCH(G51,Municipios_RN!$AE$3:$AE$168,0)) -> 24982.76
A52: 9 | B52: =INDEX(Municipios_RN!$B$3:$B$168,MATCH(A52,Municipios_RN!$AD$3:$AD$168,0)) -> Sítio Novo | C52: =INDEX(Municipios_RN!$AA$3:$AA$168,MATCH(A52,Municipios_RN!$AD$3:$AD$168,0)) -> 36020 | D52: =INDEX(Municipios_RN!$AB$3:$AB$168,MATCH(A52,Municipios_RN!$AD$3:$AD$168,0)) -> 0.69385318 | E52: =INDEX(Municipios_RN!$I$3:$I$168,MATCH(A52,Municipios_RN!$AD$3:$AD$168,0)) -> 9604.13 | G52: 9 | H52: =INDEX(Municipios_RN!$B$3:$B$168,MATCH(G52,Municipios_RN!$AE$3:$AE$168,0)) -> São José de Mipibu | I52: =INDEX(Municipios_RN!$AA$3:$AA$168,MATCH(G52,Municipios_RN!$AE$3:$AE$168,0)) -> 261506 | J52: =INDEX(Municipios_RN!$AB$3:$AB$168,MATCH(G52,Municipios_RN!$AE$3:$AE$168,0)) -> 0.2976086 | K52: =INDEX(Municipios_RN!$I$3:$I$168,MATCH(G52,Municipios_RN!$AE$3:$AE$168,0)) -> 23357.62
A53: 10 | B53: =INDEX(Municipios_RN!$B$3:$B$168,MATCH(A53,Municipios_RN!$AD$3:$AD$168,0)) -> Januário Cicco | C53: =INDEX(Municipios_RN!$AA$3:$AA$168,MATCH(A53,Municipios_RN!$AD$3:$AD$168,0)) -> 55623 | D53: =INDEX(Municipios_RN!$AB$3:$AB$168,MATCH(A53,Municipios_RN!$AD$3:$AD$168,0)) -> 0.69237089 | E53: =INDEX(Municipios_RN!$I$3:$I$168,MATCH(A53,Municipios_RN!$AD$3:$AD$168,0)) -> 8189.32 | G53: 10 | H53: =INDEX(Municipios_RN!$B$3:$B$168,MATCH(G53,Municipios_RN!$AE$3:$AE$168,0)) -> Currais Novos | I53: =INDEX(Municipios_RN!$AA$3:$AA$168,MATCH(G53,Municipios_RN!$AE$3:$AE$168,0)) -> 252593 | J53: =INDEX(Municipios_RN!$AB$3:$AB$168,MATCH(G53,Municipios_RN!$AE$3:$AE$168,0)) -> 0.35228658 | K53: =INDEX(Municipios_RN!$I$3:$I$168,MATCH(G53,Municipios_RN!$AE$3:$AE$168,0)) -> 17862.92
A54: 11 | B54: =INDEX(Municipios_RN!$B$3:$B$168,MATCH(A54,Municipios_RN!$AD$3:$AD$168,0)) -> Japi | C54: =INDEX(Municipios_RN!$AA$3:$AA$168,MATCH(A54,Municipios_RN!$AD$3:$AD$168,0)) -> 34372 | D54: =INDEX(Municipios_RN!$AB$3:$AB$168,MATCH(A54,Municipios_RN!$AD$3:$AD$168,0)) -> 0.68811435 | E54: =INDEX(Municipios_RN!$I$3:$I$168,MATCH(A54,Municipios_RN!$AD$3:$AD$168,0)) -> 10445.13 | G54: 11 | H54: =INDEX(Municipios_RN!$B$3:$B$168,MATCH(G54,Municipios_RN!$AE$3:$AE$168,0)) -> Santa Cruz | I54: =INDEX(Municipios_RN!$AA$3:$AA$168,MATCH(G54,Municipios_RN!$AE$3:$AE$168,0)) -> 224065 | J54: =INDEX(Municipios_RN!$AB$3:$AB$168,MATCH(G54,Municipios_RN!$AE$3:$AE$168,0)) -> 0.40201343 | K54: =INDEX(Municipios_RN!$I$3:$I$168,MATCH(G54,Municipios_RN!$AE$3:$AE$168,0)) -> 15362.6
A55: 12 | B55: =INDEX(Municipios_RN!$B$3:$B$168,MATCH(A55,Municipios_RN!$AD$3:$AD$168,0)) -> Barcelona | C55: =INDEX(Municipios_RN!$AA$3:$AA$168,MATCH(A55,Municipios_RN!$AD$3:$AD$168,0)) -> 30481 | D55: =INDEX(Municipios_RN!$AB$3:$AB$168,MATCH(A55,Municipios_RN!$AD$3:$AD$168,0)) -> 0.68790341 | E55: =INDEX(Municipios_RN!$I$3:$I$168,MATCH(A55,Municipios_RN!$AD$3:$AD$168,0)) -> 11497.52 | G55: 12 | H55: =INDEX(Municipios_RN!$B$3:$B$168,MATCH(G55,Municipios_RN!$AE$3:$AE$168,0)) -> João Câmara | I55: =INDEX(Municipios_RN!$AA$3:$AA$168,MATCH(G55,Municipios_RN!$AE$3:$AE$168,0)) -> 222640 | J55: =INDEX(Municipios_RN!$AB$3:$AB$168,MATCH(G55,Municipios_RN!$AE$3:$AE$168,0)) -> 0.18585967 | K55: =INDEX(Municipios_RN!$I$3:$I$168,MATCH(G55,Municipios_RN!$AE$3:$AE$168,0)) -> 35911.56
... A58: 15 | B58: =INDEX(Municipios_RN!$B$3:$B$168,MATCH(A58,Municipios_RN!$AD$3:$AD$168,0)) -> Riacho de Santana | C58: =INDEX(Municipios_RN!$AA$3:$AA$168,MATCH(A58,Municipios_RN!$AD$3:$AD$168,0)) -> 28696 | D58: =INDEX(Municipios_RN!$AB$3:$AB$168,MATCH(A58,Municipios_RN!$AD$3:$AD$168,0)) -> 0.68142097 | E58: =INDEX(Municipios_RN!$I$3:$I$168,MATCH(A58,Municipios_RN!$AD$3:$AD$168,0)) -> 10374.93 | G58: 15 | H58: =INDEX(Municipios_RN!$B$3:$B$168,MATCH(G58,Municipios_RN!$AE$3:$AE$168,0)) -> Canguaretama | I58: =INDEX(Municipios_RN!$AA$3:$AA$168,MATCH(G58,Municipios_RN!$AE$3:$AE$168,0)) -> 197510 | J58: =INDEX(Municipios_RN!$AB$3:$AB$168,MATCH(G58,Municipios_RN!$AE$3:$AE$168,0)) -> 0.35568546 | K58: =INDEX(Municipios_RN!$I$3:$I$168,MATCH(G58,Municipios_RN!$AE$3:$AE$168,0)) -> 17397.39

Sheet Correlacoes
A1: Correlação de Pearson entre a estrutura do VAB e variáveis socioeconômicas/empresariais – 167 municípios do RN
A2: CORREL ignora células vazias. Leitura: |r| < 0,3 fraca · 0,3–0,6 moderada · > 0,6 forte. Correlação não é causalidade; use como pista para os "fatores".
A4: Variável do VAB ↓ × Variável → | B4: IDHM 2010 | C4: % renda ≤ ½ SM 2010 | D4: Salário médio formal 2024 | E4: % pop. em emprego formal | F4: IDEB anos finais 2025 | G4: Escolarização 6–14 (2022) | H4: Esgotamento adequado 2022 | I4: Densidade 2022 | J4: Empresas por mil hab. 2024 | K4: % MEI nos estab. | L4: % receita de transferências
A5: Part. Indústria no VAB (%) | B5: =CORREL(Municipios_RN!$L$3:$L$168,Municipios_RN!$BC$3:$BC$168) -> -0.015173354 | C5: =CORREL(Municipios_RN!$L$3:$L$168,Municipios_RN!$BD$3:$BD$168) -> 0.0011517 | D5: =CORREL(Municipios_RN!$L$3:$L$168,Municipios_RN!$BJ$3:$BJ$168) -> 0.30713204 | E5: =CORREL(Municipios_RN!$L$3:$L$168,Municipios_RN!$BK$3:$BK$168) -> 0.34047418 | F5: =CORREL(Municipios_RN!$L$3:$L$168,Municipios_RN!$BG$3:$BG$168) -> -0.033136676 | G5: =CORREL(Municipios_RN!$L$3:$L$168,Municipios_RN!$BE$3:$BE$168) -> -0.19555464 | H5: =CORREL(Municipios_RN!$L$3:$L$168,Municipios_RN!$BH$3:$BH$168) -> -0.089191404 | I5: =CORREL(Municipios_RN!$L$3:$L$168,Municipios_RN!$BB$3:$BB$168) -> -0.036873338 | J5: =CORREL(Municipios_RN!$L$3:$L$168,Municipios_RN!$AQ$3:$AQ$168) -> 0.18103728 | K5: =CORREL(Municipios_RN!$L$3:$L$168,Municipios_RN!$AW$3:$AW$168) -> -0.15255639 | L5: =CORREL(Municipios_RN!$L$3:$L$168,Municipios_RN!$AF$3:$AF$168) -> -0.18618838
A6: Part. Serviços no VAB (%) | B6: =CORREL(Municipios_RN!$T$3:$T$168,Municipios_RN!$BC$3:$BC$168) -> 0.60913654 | C6: =CORREL(Municipios_RN!$T$3:$T$168,Municipios_RN!$BD$3:$BD$168) -> -0.51578833 | D6: =CORREL(Municipios_RN!$T$3:$T$168,Municipios_RN!$BJ$3:$BJ$168) -> -0.10710495 | E6: =CORREL(Municipios_RN!$T$3:$T$168,Municipios_RN!$BK$3:$BK$168) -> 0.26733292 | F6: =CORREL(Municipios_RN!$T$3:$T$168,Municipios_RN!$BG$3:$BG$168) -> -0.003875798 | G6: =CORREL(Municipios_RN!$T$3:$T$168,Municipios_RN!$BE$3:$BE$168) -> -0.021874156 | H6: =CORREL(Municipios_RN!$T$3:$T$168,Municipios_RN!$BH$3:$BH$168) -> 0.25360028 | I6: =CORREL(Municipios_RN!$T$3:$T$168,Municipios_RN!$BB$3:$BB$168) -> 0.38297916 | J6: =CORREL(Municipios_RN!$T$3:$T$168,Municipios_RN!$AQ$3:$AQ$168) -> 0.33521536 | K6: =CORREL(Municipios_RN!$T$3:$T$168,Municipios_RN!$AW$3:$AW$168) -> 0.22877589 | L6: =CORREL(Municipios_RN!$T$3:$T$168,Municipios_RN!$AF$3:$AF$168) -> -0.47845681
A7: Part. Adm. pública no VAB (%) | B7: =CORREL(Municipios_RN!$AB$3:$AB$168,Municipios_RN!$BC$3:$BC$168) -> -0.31405308 | C7: =CORREL(Municipios_RN!$AB$3:$AB$168,Municipios_RN!$BD$3:$BD$168) -> 0.36041383 | D7: =CORREL(Municipios_RN!$AB$3:$AB$168,Municipios_RN!$BJ$3:$BJ$168) -> -0.19398638 | E7: =CORREL(Municipios_RN!$AB$3:$AB$168,Municipios_RN!$BK$3:$BK$168) -> -0.56551697 | F7: =CORREL(Municipios_RN!$AB$3:$AB$168,Municipios_RN!$BG$3:$BG$168) -> 0.044747429 | G7: =CORREL(Municipios_RN!$AB$3:$AB$168,Municipios_RN!$BE$3:$BE$168) -> 0.18626988 | H7: =CORREL(Municipios_RN!$AB$3:$AB$168,Municipios_RN!$BH$3:$BH$168) -> -0.061127419 | I7: =CORREL(Municipios_RN!$AB$3:$AB$168,Municipios_RN!$BB$3:$BB$168) -> -0.15699695 | J7: =CORREL(Municipios_RN!$AB$3:$AB$168,Municipios_RN!$AQ$3:$AQ$168) -> -0.37746159 | K7: =CORREL(Municipios_RN!$AB$3:$AB$168,Municipios_RN!$AW$3:$AW$168) -> -0.047697458 | L7: =CORREL(Municipios_RN!$AB$3:$AB$168,Municipios_RN!$AF$3:$AF$168) -> 0.42687919
A8: PIB per capita 2021 (R$) | B8: =CORREL(Municipios_RN!$I$3:$I$168,Municipios_RN!$BC$3:$BC$168) -> -0.032252493 | C8: =CORREL(Municipios_RN!$I$3:$I$168,Municipios_RN!$BD$3:$BD$168) -> -0.044017084 | D8: =CORREL(Municipios_RN!$I$3:$I$168,Municipios_RN!$BJ$3:$BJ$168) -> 0.29390125 | E8: =CORREL(Municipios_RN!$I$3:$I$168,Municipios_RN!$BK$3:$BK$168) -> 0.36587217 | F8: =CORREL(Municipios_RN!$I$3:$I$168,Municipios_RN!$BG$3:$BG$168) -> -0.035685936 | G8: =CORREL(Municipios_RN!$I$3:$I$168,Municipios_RN!$BE$3:$BE$168) -> -0.11746973 | H8: =CORREL(Municipios_RN!$I$3:$I$168,Municipios_RN!$BH$3:$BH$168) -> -0.073368814 | I8: =CORREL(Municipios_RN!$I$3:$I$168,Municipios_RN!$BB$3:$BB$168) -> 0.015173795 | J8: =CORREL(Municipios_RN!$I$3:$I$168,Municipios_RN!$AQ$3:$AQ$168) -> 0.24146262 | K8: =CORREL(Municipios_RN!$I$3:$I$168,Municipios_RN!$AW$3:$AW$168) -> -0.12183348 | L8: =CORREL(Municipios_RN!$I$3:$I$168,Municipios_RN!$AF$3:$AF$168) -> -0.21831167

Sheet Serie_Historica
A1: Código IBGE | B1: Município | C1: Fonte | D1: Série | E1: Preços | F1: Unidade | G1: 2002 | H1: 2003 | I1: 2004 | J1: 2005 | K1: 2006 | L1: 2007 | M1: 2008 | N1: 2009 | O1: 2010 | P1: 2011 | Q1: 2012 | R1: 2013 | S1: 2014 | T1: 2015 | U1: 2016 | V1: 2017 | W1: 2018 | X1: 2019 | Y1: 2020 | Z1: 2021 | AA1: 2022 | AB1: 2023 | AC1: Var. real 2002–2021 (%) | AD1: Cresc. médio anual real 2002–2021 (%)
A2: 24 | B2: RIO GRANDE DO NORTE (total) | C2: IBGE/SIDRA tab. 5938 | D2: PIB | E2: Correntes | F2: mil R$ | G2: 13566803 | H2: 14865441 | I2: 17252398 | J2: 19966918 | K2: 22890124 | L2: 26318259 | M2: 28898860 | N2: 30941054 | O2: 36184502 | P2: 40992925 | Q2: 46412208 | R2: 51518457 | S2: 54022584 | T2: 57250867 | U2: 59677389 | V2: 64305995 | W2: 66969562 | X2: 71336780 | Y2: 71577107 | Z2: 80180733 | AA2: 93819291 | AB2: 101740275
A3: 24 | B3: RIO GRANDE DO NORTE (total) | C3: IBGE/SIDRA tab. 5938 | D3: VAB total | E3: Correntes | F3: mil R$ | G3: 12082744 | H3: 13181222 | I3: 15296138 | J3: 17753703 | K3: 20252165 | L3: 23513864 | M3: 25678022 | N3: 27525533 | O3: 32149190 | P3: 36403024 | Q3: 41257031 | R3: 45903800 | S3: 48235009 | T3: 51183888 | U3: 53133028 | V3: 57389774 | W3: 59575711 | X3: 63866962 | Y3: 63816254 | Z3: 71064332
A4: 24 | B4: RIO GRANDE DO NORTE (total) | C4: IBGE/SIDRA tab. 5938 | D4: VAB Indústria | E4: Correntes | F4: mil R$ | G4: 3583308 | H4: 3329619 | I4: 4126394 | J4: 5095576 | K4: 5593218 | L4: 6684589 | M4: 7287363 | N4: 5827912 | O4: 7683076 | P4: 8955950 | Q4: 10261649 | R4: 10736594 | S4: 10559610 | T4: 10741879 | U4: 10096238 | V4: 10694795 | W4: 11372518 | X4: 11751480 | Y4: 11811274 | Z4: 14728096
A5: 24 | B5: RIO GRANDE DO NORTE (total) | C5: IBGE/SIDRA tab. 5938 | D5: VAB Serviços (exc. adm. pública) | E5: Correntes | F5: mil R$ | G5: 4644959 | H5: 5362006 | I5: 6232894 | J5: 7046830 | K5: 8216777 | L5: 9487810 | M5: 10170111 | N5: 12295758 | O5: 14253228 | P5: 15864659 | Q5: 18625292 | R5: 20935627 | S5: 22328626 | T5: 23931525 | U5: 25368841 | V5: 27524283 | W5: 28127591 | X5: 30468869 | Y5: 29207942 | Z5: 32321165
A6: 24 | B6: RIO GRANDE DO NORTE (total) | C6: IBGE/SIDRA tab. 5938 | D6: VAB Adm. pública | E6: Correntes | F6: mil R$ | G6: 3301515 | H6: 3635129 | I6: 4037607 | J6: 4741070 | K6: 5441218 | L6: 6452111 | M6: 7204441 | N6: 8151092 | O6: 9064264 | P6: 10250044 | Q6: 11068186 | R6: 12746686 | S6: 13806018 | T6: 14871849 | U6: 15801841 | V6: 17010128 | W6: 17478831 | X6: 18952562 | Y6: 19786450 | Z6: 20873316
A7: 2400109 | B7: Acari | C7: IBGE/SIDRA tab. 5938 | D7: PIB | E7: Correntes | F7: mil R$ | G7: 25575 | H7: 28144 | I7: 31036 | J7: 35205 | K7: 39731 | L7: 43491 | M7: 48200 | N7: 53885 | O7: 60084 | P7: 72737 | Q7: 87926 | R7: 98156 | S7: 105627 | T7: 112644 | U7: 109315 | V7: 119101 | W7: 124825 | X7: 129939 | Y7: 132249 | Z7: 141992 | AA7: 173700 | AB7: 195828
A8: 2400109 | B8: Acari | C8: IBGE/SIDRA tab. 5938 | D8: VAB total | E8: Correntes | F8: mil R$ | G8: 24455 | H8: 27040 | I8: 29631 | J8: 33467 | K8: 37290 | L8: 40626 | M8: 45166 | N8: 50558 | O8: 55263 | P8: 66150 | Q8: 78801 | R8: 88387 | S8: 95385 | T8: 101580 | U8: 103757 | V8: 113378 | W8: 116168 | X8: 121379 | Y8: 123671 | Z8: 130775
A9: 2400109 | B9: Acari | C9: IBGE/SIDRA tab. 5938 | D9: VAB Indústria | E9: Correntes | F9: mil R$ | G9: 2123 | H9: 1911 | I9: 2034 | J9: 2354 | K9: 2808 | L9: 3200 | M9: 3439 | N9: 3304 | O9: 3781 | P9: 4295 | Q9: 6462 | R9: 7171 | S9: 8607 | T9: 7522 | U9: 9551 | V9: 10001 | W9: 9594 | X9: 8865 | Y9: 8348 | Z9: 8762
A10: 2400109 | B10: Acari | C10: IBGE/SIDRA tab. 5938 | D10: VAB Serviços (exc. adm. pública) | E10: Correntes | F10: mil R$ | G10: 6424 | H10: 6980 | I10: 7725 | J10: 8296 | K10: 9010 | L10: 10064 | M10: 9844 | N10: 11328 | O10: 13216 | P10: 15945 | Q10: 24719 | R10: 26658 | S10: 29252 | T10: 31765 | U10: 30592 | V10: 34840 | W10: 37273 | X10: 39854 | Y10: 38915 | Z10: 41690
A11: 2400109 | B11: Acari | C11: IBGE/SIDRA tab. 5938 | D11: VAB Adm. pública | E11: Correntes | F11: mil R$ | G11: 12857 | H11: 14121 | I11: 14956 | J11: 17822 | K11: 20201 | L11: 23253 | M11: 26271 | N11: 28326 | O11: 31252 | P11: 35049 | Q11: 37650 | R11: 42709 | S11: 45112 | T11: 49105 | U11: 51034 | V11: 55724 | W11: 55327 | X11: 60058 | Y11: 62026 | Z11: 63154
A12: 2400109 | B12: Acari | C12: IpeaData (IBGE) | D12: PIB | E12: Constantes de 2010 | F12: mil R$ de 2010 | G12: 48585.7 | H12: 46862.5 | I12: 47960 | J12: 50639.9 | K12: 53523.8 | L12: 55045.2 | M12: 56082.5 | N12: 58423.9 | O12: 60084 | P12: 67151 | Q12: 75200.3 | R12: 78089.4 | S12: 77919 | T12: 77250.4 | U12: 69347.7 | V12: 72880.1 | W12: 73098 | X12: 73008.7 | Y12: 69789.5 | Z12: 66282.9 | AC12: =IFERROR(Z12/G12-1,"") -> 0.36424709 | AD12: =IFERROR((Z12/G12)^(1/19)-1,"") -> 0.016481862
A13: 2400109 | B13: Acari | C13: IpeaData (IBGE) | D13: VAB Indústria | E13: Constantes de 2010 | F13: mil R$ de 2010 | G13: 4032.4 | H13: 3182.3 | I13: 3143.8 | J13: 3385.7 | K13: 3782.2 | L13: 4050.1 | M13: 4001.5 | N13: 3582.3 | O13: 3781 | P13: 3965.2 | Q13: 5526.7 | R13: 5705 | S13: 6349.2 | T13: 5158.5 | U13: 6059 | V13: 6119.8 | W13: 5618.3 | X13: 4981 | Y13: 4405.3 | Z13: 4090.2 | AC13: =IFERROR(Z13/G13-1,"") -> 0.014333895 | AD13: =IFERROR((Z13/G13)^(1/19)-1,"") -> 0.00074934043
A14: 2400109 | B14: Acari | C14: IpeaData (IBGE) | D14: VAB Serviços (exc. adm. pública) | E14: Constantes de 2010 | F14: mil R$ de 2010 | G14: 12203.2 | H14: 11622.6 | I14: 11936.8 | J14: 11933.1 | K14: 12138.4 | L14: 12737.9 | M14: 11453.9 | N14: 12282.2 | O14: 13216 | P14: 14720.5 | Q14: 21141.4 | R14: 21208.1 | S14: 21578.6 | T14: 21784.2 | U14: 19407.1 | V14: 21319.2 | W14: 21827.2 | X14: 22392.7 | Y14: 20535.9 | Z14: 19461.7 | AC14: =IFERROR(Z14/G14-1,"") -> 0.594803 | AD14: =IFERROR((Z14/G14)^(1/19)-1,"") -> 0.024870026
A15: 2400109 | B15: Acari | C15: IpeaData (IBGE) | D15: VAB Adm. pública | E15: Constantes de 2010 | F15: mil R$ de 2010 | G15: 24424.7 | H15: 23513 | I15: 23111.4 | J15: 25635 | K15: 27214.2 | L15: 29431.1 | M15: 30566.8 | N15: 30712 | O15: 31252 | P15: 32357.3 | Q15: 32200.8 | R15: 33977.7 | S15: 33278.2 | T15: 33675.8 | U15: 32375.2 | V15: 34098.5 | W15: 32399.7 | X15: 33744.7 | Y15: 32731.9 | Z15: 29481.2 | AC15: =IFERROR(Z15/G15-1,"") -> 0.20702404 | AD15: =IFERROR((Z15/G15)^(1/19)-1,"") -> 0.0099522425
A16: 2400109 | B16: Acari | C16: IpeaData (IBGE) | D16: VAB Agropecuária | E16: Constantes de 2010 | F16: mil R$ de 2010 | G16: 5797.3 | H16: 6706.3 | I16: 7596.9 | J16: 7185.9 | K16: 7100.4 | L16: 5200.4 | M16: 6529.5 | N16: 8240.2 | O16: 7014 | P16: 10026 | Q16: 8527.9 | R16: 9427.4 | S16: 9157.6 | T16: 9044.2 | U16: 7980.6 | V16: 7840.5 | W16: 8183.2 | X16: 7080.7 | Y16: 7589 | Z16: 8014.6 | AC16: =IFERROR(Z16/G16-1,"") -> 0.38247115 | AD16: =IFERROR((Z16/G16)^(1/19)-1,"") -> 0.017192036
A17: 2400208 | B17: Assú | C17: IBGE/SIDRA tab. 5938 | D17: PIB | E17: Correntes | F17: mil R$ | G17: 202278 | H17: 192702 | I17: 215069 | J17: 265624 | K17: 286096 | L17: 323551 | M17: 358395 | N17: 351654 | O17: 442987 | P17: 605536 | Q17: 699354 | R17: 818416 | S17: 830663 | T17: 853302 | U17: 780970 | V17: 894304 | W17: 1134910 | X17: 1278677 | Y17: 1169390 | Z17: 1467562 | AA17: 2146108 | AB17: 2170177
A18: 2400208 | B18: Assú | C18: IBGE/SIDRA tab. 5938 | D18: VAB total | E18: Correntes | F18: mil R$ | G18: 194927 | H18: 184748 | I18: 205662 | J18: 253711 | K18: 272715 | L18: 306932 | M18: 339211 | N18: 331506 | O18: 416423 | P18: 572134 | Q18: 658911 | R18: 766528 | S18: 782781 | T18: 794969 | U18: 718414 | V18: 824196 | W18: 1049846 | X18: 1195857 | Y18: 1082354 | Z18: 1368136
A19: 2400208 | B19: Assú | C19: IBGE/SIDRA tab. 5938 | D19: VAB Indústria | E19: Correntes | F19: mil R$ | G19: 80294 | H19: 60358 | I19: 66252 | J19: 96220 | K19: 96938 | L19: 102252 | M19: 120243 | N19: 81827 | O19: 124631 | P19: 208583 | Q19: 235206 | R19: 268381 | S19: 258084 | T19: 221817 | U19: 123623 | V19: 168078 | W19: 320991 | X19: 384654 | Y19: 266296 | Z19: 483176
A20: 2400208 | B20: Assú | C20: IBGE/SIDRA tab. 5938 | D20: VAB Serviços (exc. adm. pública) | E20: Correntes | F20: mil R$ | G20: 55513 | H20: 57657 | I20: 66780 | J20: 74419 | K20: 84009 | L20: 97089 | M20: 99379 | N20: 112815 | O20: 140599 | P20: 191148 | Q20: 238543 | R20: 283376 | S20: 293910 | T20: 323652 | U20: 322613 | V20: 369740 | W20: 438998 | X20: 487758 | Y20: 472291 | Z20: 518977
A21: 2400208 | B21: Assú | C21: IBGE/SIDRA tab. 5938 | D21: VAB Adm. pública | E21: Correntes | F21: mil R$ | G21: 51878 | H21: 56399 | I21: 62443 | J21: 72201 | K21: 80921 | L21: 97223 | M21: 109888 | N21: 123095 | O21: 138255 | P21: 157601 | Q21: 170966 | R21: 198368 | S21: 213728 | T21: 231216 | U21: 252411 | V21: 265222 | W21: 268791 | X21: 293134 | Y21: 313417 | Z21: 330939
A22: 2400208 | B22: Assú | C22: IpeaData (IBGE) | D22: PIB | E22: Constantes de 2010 | F22: mil R$ de 2010 | G22: 384277.1 | H22: 320870.9 | I22: 332350.1 | J22: 382081.5 | K22: 385419.6 | L22: 409508.8 | M22: 417002.8 | N22: 381275 | O22: 442987 | P22: 559032.4 | Q22: 598134.8 | R22: 651102.3 | S22: 612763.7 | T22: 585187.8 | U22: 495435 | V22: 547240.9 | W22: 664607.7 | X22: 718449.1 | Y22: 617102.2 | Z22: 685068.6 | AC22: =IFERROR(Z22/G22-1,"") -> 0.78274636 | AD22: =IFERROR((Z22/G22)^(1/19)-1,"") -> 0.030896915
A23: 2400208 | B23: Assú | C23: IpeaData (IBGE) | D23: VAB Indústria | E23: Constantes de 2010 | F23: mil R$ de 2010 | G23: 152537.6 | H23: 100503.3 | I23: 102380.1 | J23: 138404.8 | K23: 130591.8 | L23: 129417.5 | M23: 139906 | N23: 88719.6 | O23: 124631 | P23: 192564.4 | Q23: 201164.1 | R23: 213514.2 | S23: 190383.5 | T23: 152120.3 | U23: 78424.5 | V23: 102850 | W23: 187973.6 | X23: 216125.2 | Y23: 140527.8 | Z23: 225550.1 | AC23: =IFERROR(Z23/G23-1,"") -> 0.47865248 | AD23: =IFERROR((Z23/G23)^(1/19)-1,"") -> 0.020799202
A24: 2400208 | B24: Assú | C24: IpeaData (IBGE) | D24: VAB Serviços (exc. adm. pública) | E24: Constantes de 2010 | F24: mil R$ de 2010 | G24: 105461.1 | H24: 96005.8 | I24: 103196.8 | J24: 107046.4 | K24: 113173.7 | L24: 122883.1 | M24: 115630.4 | N24: 122317.8 | O24: 140599 | P24: 176468.3 | Q24: 204018.1 | R24: 225443.7 | S24: 216811.6 | T24: 221958 | U24: 204660.6 | V24: 226250.6 | W24: 257079 | X24: 274056.2 | Y24: 249234.1 | Z24: 242263.2 | AC24: =IFERROR(Z24/G24-1,"") -> 1.2971807 | AD24: =IFERROR((Z24/G24)^(1/19)-1,"") -> 0.044744927
A25: 2400208 | B25: Assú | C25: IpeaData (IBGE) | D25: VAB Adm. pública | E25: Constantes de 2010 | F25: mil R$ de 2010 | G25: 98554.5 | H25: 93911.2 | I25: 96493.9 | J25: 103856.2 | K25: 109013.7 | L25: 123052.3 | M25: 127858 | N25: 133463.7 | O25: 138255 | P25: 145497.6 | Q25: 146221.7 | R25: 157814.4 | S25: 157662.9 | T25: 158566.1 | U25: 160125.5 | V25: 162294.2 | W25: 157405.1 | X25: 164702.9 | Y25: 165394.2 | Z25: 154488 | AC25: =IFERROR(Z25/G25-1,"") -> 0.56753877 | AD25: =IFERROR((Z25/G25)^(1/19)-1,"") -> 0.023940325
A26: 2400208 | B26: Assú | C26: IpeaData (IBGE) | D26: VAB Agropecuária | E26: Constantes de 2010 | F26: mil R$ de 2010 | G26: 13758.7 | H26: 17205.7 | I26: 15742.4 | J26: 15637.8 | K26: 14612.6 | L26: 13121.4 | M26: 11287.8 | N26: 14928.8 | O26: 12938 | P26: 13664.3 | Q26: 12140.5 | R26: 13049.6 | S26: 12584.1 | T26: 12539 | U26: 12540.5 | V26: 12945.7 | W26: 12336.9 | X26: 17030.8 | Y26: 16016.1 | Z26: 16358.8 | AC26: =IFERROR(Z26/G26-1,"") -> 0.18897861 | AD26: =IFERROR((Z26/G26)^(1/19)-1,"") -> 0.0091518681
A27: 2400307 | B27: Afonso Bezerra | C27: IBGE/SIDRA tab. 5938 | D27: PIB | E27: Correntes | F27: mil R$ | G27: 18553 | H27: 22245 | I27: 25580 | J27: 27537 | K27: 29493 | L27: 33756 | M27: 33815 | N27: 42163 | O27: 47835 | P27: 51449 | Q27: 58794 | R27: 65569 | S27: 67542 | T27: 79301 | U27: 84824 | V27: 95929 | W27: 95641 | X27: 101916 | Y27: 138830 | Z27: 138262 | AA27: 193263 | AB27: 160921
A28: 2400307 | B28: Afonso Bezerra | C28: IBGE/SIDRA tab. 5938 | D28: VAB total | E28: Correntes | F28: mil R$ | G28: 18084 | H28: 21690 | I28: 24878 | J28: 26692 | K28: 28328 | L28: 31910 | M28: 32346 | N28: 40563 | O28: 45603 | P28: 48627 | Q28: 55217 | R28: 62368 | S28: 64066 | T28: 74803 | U28: 81595 | V28: 92791 | W28: 91888 | X28: 98363 | Y28: 134600 | Z28: 132004
A29: 2400307 | B29: Afonso Bezerra | C29: IBGE/SIDRA tab. 5938 | D29: VAB Indústria | E29: Correntes | F29: mil R$ | G29: 1565 | H29: 1827 | I29: 2562 | J29: 1371 | K29: 1043 | L29: 1366 | M29: 1169 | N29: 1543 | O29: 2266 | P29: 1855 | Q29: 2314 | R29: 2171 | S29: 2066 | T29: 3009 | U29: 3484 | V29: 3562 | W29: 3679 | X29: 4338 | Y29: 29599 | Z29: 21455
A30: 2400307 | B30: Afonso Bezerra | C30: IBGE/SIDRA tab. 5938 | D30: VAB Serviços (exc. adm. pública) | E30: Correntes | F30: mil R$ | G30: 3737 | H30: 4396 | I30: 5084 | J30: 5460 | K30: 5813 | L30: 6636 | M30: 6043 | N30: 7793 | O30: 9063 | P30: 10187 | Q30: 12127 | R30: 13755 | S30: 13956 | T30: 17467 | U30: 18887 | V30: 21481 | W30: 20156 | X30: 21516 | Y30: 26497 | Z30: 28612
A31: 2400307 | B31: Afonso Bezerra | C31: IBGE/SIDRA tab. 5938 | D31: VAB Adm. pública | E31: Correntes | F31: mil R$ | G31: 11490 | H31: 12795 | I31: 14156 | J31: 16996 | K31: 18688 | L31: 20938 | M31: 22614 | N31: 27781 | O31: 31499 | P31: 32781 | Q31: 37352 | R31: 42771 | S31: 44035 | T31: 49711 | U31: 53203 | V31: 61385 | W31: 59240 | X31: 65458 | Y31: 68103 | Z31: 73059
A32: 2400307 | B32: Afonso Bezerra | C32: IpeaData (IBGE) | D32: PIB | E32: Constantes de 2010 | F32: mil R$ de 2010 | G32: 35245.2 | H32: 37040.6 | I32: 39528.8 | J32: 39609.4 | K32: 39731.5 | L32: 42724.4 | M32: 39344.9 | N32: 45714.5 | O32: 47835 | P32: 47497.8 | Q32: 50284.6 | R32: 52164.3 | S32: 49824.4 | T32: 54384 | U32: 53811 | V32: 58700.7 | W32: 56007.7 | X32: 57263.5 | Y32: 73262.4 | Z32: 64541.7 | AC32: =IFERROR(Z32/G32-1,"") -> 0.83121957 | AD32: =IFERROR((Z32/G32)^(1/19)-1,"") -> 0.032353521
A33: 2400307 | B33: Afonso Bezerra | C33: IpeaData (IBGE) | D33: VAB Indústria | E33: Constantes de 2010 | F33: mil R$ de 2010 | G33: 2973.5 | H33: 3041.4 | I33: 3959.2 | J33: 1972.7 | K33: 1405.1 | L33: 1729.4 | M33: 1359.9 | N33: 1673 | O33: 2266 | P33: 1712.5 | Q33: 1979.1 | R33: 1727.2 | S33: 1524 | T33: 2063.5 | U33: 2210.2 | V33: 2179.7 | W33: 2154.4 | X33: 2437.4 | Y33: 15619.8 | Z33: 10015.4 | AC33: =IFERROR(Z33/G33-1,"") -> 2.3682193 | AD33: =IFERROR((Z33/G33)^(1/19)-1,"") -> 0.06600174
